Workbook
Name FLEXVORPCalc: 'Manual VARG'!$C$6
Name IN_SEASON: Constants!$C$2
Name QBVORPCalc: 'Manual VARG'!$C$2
Name RAISES_ENABLED: Constants!$C$4
Name RBVORPCalc: 'Manual VARG'!$C$3
Name SEASON: Constants!$C$3
Name TEVORPCalc: 'Manual VARG'!$C$5
Name VARG: Constants!$C$1
Name WRTEVORPCalc: 'Manual VARG'!$C$8
Name WRVORPCalc: 'Manual VARG'!$C$4

Sheet 2018 Projections
A1: Year | B1: PLAYER | C1: TEAM | D1: POS | E1: PASSING COMP | F1: PASSING ATT | G1: PASSING YDS | H1: PASSING TD | I1: PASSING INT | J1: RUSH ATT | K1: RUSH YDS | L1: RUSH TD | M1: REC | N1: REC YDS | O1: REC TD | P1: PROJ TOTAL PTS | Q1: ReplacementValue | R1: VAR | S1: VAR/G | T1: Rookie | U1: LastProj | V1: VAR/G CHG | W1: Keeper? | X1: RFA? | Y1: VAWG | Z1: VAWG $ | AB1: Total Free Agent $ Pool | AC1: 2760
A2: 2018 | B2: Aaron Rodgers | C2: GB | D2: QB | E2: 361 | F2: 566 | G2: 4024 | H2: 34 | I2: 9 | J2: 58 | K2: 309 | L2: 2 | M2: 0 | N2: 0 | O2: 0 | P2: 321.86 | Q2: 278.68 | R2: 43.18 | S2: 2.69875 | U2: 321.86 | V2: =IF(ABS(Proj2018[[#This Row],[LastProj]]-Proj2018[[#This Row],[PROJ TOTAL PTS]])<0.5,"",(Proj2018[[#This Row],[PROJ TOTAL PTS]]-Proj2018[[#This Row],[LastProj]])/16) | W2: K | Y2: =IF(Proj2018[[#This Row],[POS]]="K",-100,Proj2018[[#This Row],[VAR/G]]+1.5) -> 4.19875 | Z2: =ROUND(MAX(Proj2018[[#This Row],[VAWG]],0)*$AC$9,0)+1 -> 483 | AB2: Free Agent $/VARG | AC2: 12.194044
A3: 2018 | B3: Tom Brady | C3: NE | D3: QB | E3: 391 | F3: 606 | G3: 4729 | H3: 33 | I3: 8 | J3: 30 | K3: 30 | L3: 2 | M3: 0 | N3: 0 | O3: 0 | P3: 320.16 | Q3: 278.68 | R3: 41.48 | S3: 2.5925 | U3: 320.16 | V3: =IF(ABS(Proj2018[[#This Row],[LastProj]]-Proj2018[[#This Row],[PROJ TOTAL PTS]])<0.5,"",(Proj2018[[#This Row],[PROJ TOTAL PTS]]-Proj2018[[#This Row],[LastProj]])/16) | W3: K | Y3: =IF(Proj2018[[#This Row],[POS]]="K",-100,Proj2018[[#This Row],[VAR/G]]+1.5) -> 4.0925 | Z3: =ROUND(MAX(Proj2018[[#This Row],[VAWG]],0)*$AC$9,0)+1 -> 471
A4: 2018 | B4: Cam Newton | C4: Car | D4: QB | E4: 313 | F4: 530 | G4: 3761 | H4: 22 | I4: 14 | J4: 128 | K4: 627 | L4: 6 | M4: 0 | N4: 0 | O4: 0 | P4: 309.14 | Q4: 278.68 | R4: 30.46 | S4: 1.90375 | U4: 309.14 | V4: =IF(ABS(Proj2018[[#This Row],[LastProj]]-Proj2018[[#This Row],[PROJ TOTAL PTS]])<0.5,"",(Proj2018[[#This Row],[PROJ TOTAL PTS]]-Proj2018[[#This Row],[LastProj]])/16) | W4: K | Y4: =IF(Proj2018[[#This Row],[POS]]="K",-100,Proj2018[[#This Row],[VAR/G]]+1.5) -> 3.40375 | Z4: =ROUND(MAX(Proj2018[[#This Row],[VAWG]],0)*$AC$9,0)+1 -> 392 | AB4: Optimal $/VARG | AC4: 12.194044
A5: 2018 | B5: Carson Wentz | C5: Phi | D5: QB | E5: 358 | F5: 578 | G5: 4148 | H5: 30 | I5: 12 | J5: 70 | K5: 272 | L5: 3 | M5: 0 | N5: 0 | O5: 0 | P5: 307.12 | Q5: 278.68 | R5: 28.44 | S5: 1.7775 | U5: 307.12 | V5: =IF(ABS(Proj2018[[#This Row],[LastProj]]-Proj2018[[#This Row],[PROJ TOTAL PTS]])<0.5,"",(Proj2018[[#This Row],[PROJ TOTAL PTS]]-Proj2018[[#This Row],[LastProj]])/16) | W5: K | Y5: =IF(Proj2018[[#This Row],[POS]]="K",-100,Proj2018[[#This Row],[VAR/G]]+1.5) -> 3.2775 | Z5: =ROUND(MAX(Proj2018[[#This Row],[VAWG]],0)*$AC$9,0)+1 -> 377
A6: 2018 | B6: Russell Wilson | C6: Sea | D6: QB | E6: 322 | F6: 521 | G6: 3826 | H6: 27 | I6: 11 | J6: 92 | K6: 484 | L6: 2 | M6: 0 | N6: 0 | O6: 0 | P6: 299.44 | Q6: 278.68 | R6: 20.76 | S6: 1.2975 | U6: 299.44 | V6: =IF(ABS(Proj2018[[#This Row],[LastProj]]-Proj2018[[#This Row],[PROJ TOTAL PTS]])<0.5,"",(Proj2018[[#This Row],[PROJ TOTAL PTS]]-Proj2018[[#This Row],[LastProj]])/16) | W6: K | Y6: =IF(Proj2018[[#This Row],[POS]]="K",-100,Proj2018[[#This Row],[VAR/G]]+1.5) -> 2.7975 | Z6: =ROUND(MAX(Proj2018[[#This Row],[VAWG]],0)*$AC$9,0)+1 -> 322 | AB6: Balance Point VARG | AC6: =AC1/AC4 -> 226.34
A7: 2018 | B7: Andrew Luck | C7: Ind | D7: QB | E7: 366 | F7: 585 | G7: 4294 | H7: 29 | I7: 16 | J7: 60 | K7: 285 | L7: 2 | M7: 0 | N7: 0 | O7: 0 | P7: 296.26 | Q7: 278.68 | R7: 17.58 | S7: 1.09875 | U7: 296.26 | V7: =IF(ABS(Proj2018[[#This Row],[LastProj]]-Proj2018[[#This Row],[PROJ TOTAL PTS]])<0.5,"",(Proj2018[[#This Row],[PROJ TOTAL PTS]]-Proj2018[[#This Row],[LastProj]])/16) | W7: K | Y7: =IF(Proj2018[[#This Row],[POS]]="K",-100,Proj2018[[#This Row],[VAR/G]]+1.5) -> 2.59875 | Z7: =ROUND(MAX(Proj2018[[#This Row],[VAWG]],0)*$AC$9,0)+1 -> 299 | AB7: Total VARG | AC7: =SUMIFS(Proj2018[VAWG],Proj2018[VAWG],">0",Proj2018[Keeper?],"") -> 24.04375
A8: 2018 | B8: Alex Smith | C8: Was | D8: QB | E8: 359 | F8: 557 | G8: 4142 | H8: 24 | I8: 8 | J8: 57 | K8: 300 | L8: 2 | M8: 0 | N8: 0 | O8: 0 | P8: 287.68 | Q8: 278.68 | R8: 9 | S8: 0.5625 | U8: 287.68 | V8: =IF(ABS(Proj2018[[#This Row],[LastProj]]-Proj2018[[#This Row],[PROJ TOTAL PTS]])<0.5,"",(Proj2018[[#This Row],[PROJ TOTAL PTS]]-Proj2018[[#This Row],[LastProj]])/16) | W8: K | Y8: =IF(Proj2018[[#This Row],[POS]]="K",-100,Proj2018[[#This Row],[VAR/G]]+1.5) -> 2.0625 | Z8: =ROUND(MAX(Proj2018[[#This Row],[VAWG]],0)*$AC$9,0)+1 -> 238
A9: 2018 | B9: Deshaun Watson | C9: Hou | D9: QB | E9: 309 | F9: 514 | G9: 3722 | H9: 27 | I9: 17 | J9: 87 | K9: 444 | L9: 3 | M9: 0 | N9: 0 | O9: 0 | P9: 285.28 | Q9: 278.68 | R9: 6.6 | S9: 0.4125 | U9: 285.28 | V9: =IF(ABS(Proj2018[[#This Row],[LastProj]]-Proj2018[[#This Row],[PROJ TOTAL PTS]])<0.5,"",(Proj2018[[#This Row],[PROJ TOTAL PTS]]-Proj2018[[#This Row],[LastProj]])/16) | W9: K | Y9: =IF(Proj2018[[#This Row],[POS]]="K",-100,Proj2018[[#This Row],[VAR/G]]+1.5) -> 1.9125 | Z9: =ROUND(MAX(Proj2018[[#This Row],[VAWG]],0)*$AC$9,0)+1 -> 221 | AB9: $/VAWG | AC9: =AC1/AC7 -> 114.79075
A10: 2018 | B10: Matthew Stafford | C10: Det | D10: QB | E10: 373 | F10: 575 | G10: 4392 | H10: 28 | I10: 11 | J10: 31 | K10: 104 | L10: 1 | M10: 0 | N10: 0 | O10: 0 | P10: 282.08 | Q10: 278.68 | R10: 3.4 | S10: 0.2125 | U10: 282.08 | V10: =IF(ABS(Proj2018[[#This Row],[LastProj]]-Proj2018[[#This Row],[PROJ TOTAL PTS]])<0.5,"",(Proj2018[[#This Row],[PROJ TOTAL PTS]]-Proj2018[[#This Row],[LastProj]])/16) | W10: K | Y10: =IF(Proj2018[[#This Row],[POS]]="K",-100,Proj2018[[#This Row],[VAR/G]]+1.5) -> 1.7125 | Z10: =ROUND(MAX(Proj2018[[#This Row],[VAWG]],0)*$AC$9,0)+1 -> 198
A11: 2018 | B11: Drew Brees | C11: NO | D11: QB | E11: 386 | F11: 569 | G11: 4405 | H11: 28 | I11: 12 | J11: 27 | K11: 31 | L11: 2 | M11: 0 | N11: 0 | O11: 0 | P11: 279.3 | Q11: 278.68 | R11: 0.62 | S11: 0.03875 | U11: 279.3 | V11: =IF(ABS(Proj2018[[#This Row],[LastProj]]-Proj2018[[#This Row],[PROJ TOTAL PTS]])<0.5,"",(Proj2018[[#This Row],[PROJ TOTAL PTS]]-Proj2018[[#This Row],[LastProj]])/16) | W11: K | Y11: =IF(Proj2018[[#This Row],[POS]]="K",-100,Proj2018[[#This Row],[VAR/G]]+1.5) -> 1.53875 | Z11: =ROUND(MAX(Proj2018[[#This Row],[VAWG]],0)*$AC$9,0)+1 -> 178
A12: 2018 | B12: Ben Roethlisberger | C12: Pit | D12: QB | E12: 376 | F12: 584 | G12: 4534 | H12: 29 | I12: 15 | J12: 28 | K12: 58 | L12: 1 | M12: 0 | N12: 0 | O12: 0 | P12: 279.16 | Q12: 278.68 | R12: 0.48 | S12: 0.03 | U12: 279.16 | V12: =IF(ABS(Proj2018[[#This Row],[LastProj]]-Proj2018[[#This Row],[PROJ TOTAL PTS]])<0.5,"",(Proj2018[[#This Row],[PROJ TOTAL PTS]]-Proj2018[[#This Row],[LastProj]])/16) | W12: K | Y12: =IF(Proj2018[[#This Row],[POS]]="K",-100,Proj2018[[#This Row],[VAR/G]]+1.5) -> 1.53 | Z12: =ROUND(MAX(Proj2018[[#This Row],[VAWG]],0)*$AC$9,0)+1 -> 177
A13: 2018 | B13: Kirk Cousins | C13: Min | D13: QB | E13: 373 | F13: 572 | G13: 4328 | H13: 27 | I13: 14 | J13: 47 | K13: 136 | L13: 2 | M13: 0 | N13: 0 | O13: 0 | P13: 278.72 | Q13: 278.68 | R13: 0.04 | S13: 0.0025 | U13: 278.72 | V13: =IF(ABS(Proj2018[[#This Row],[LastProj]]-Proj2018[[#This Row],[PROJ TOTAL PTS]])<0.5,"",(Proj2018[[#This Row],[PROJ TOTAL PTS]]-Proj2018[[#This Row],[LastProj]])/16) | W13: K | Y13: =IF(Proj2018[[#This Row],[POS]]="K",-100,Proj2018[[#This Row],[VAR/G]]+1.5) -> 1.5025 | Z13: =ROUND(MAX(Proj2018[[#This Row],[VAWG]],0)*$AC$9,0)+1 -> 173
A14: 2018 | B14: Marcus Mariota | C14: Ten | D14: QB | E14: 326 | F14: 529 | G14: 3777 | H14: 24 | I14: 13 | J14: 67 | K14: 366 | L14: 3 | M14: 0 | N14: 0 | O14: 0 | P14: 275.68 | Q14: 278.68 | R14: -3 | S14: -0.1875 | U14: 275.68 | V14: =IF(ABS(Proj2018[[#This Row],[LastProj]]-Proj2018[[#This Row],[PROJ TOTAL PTS]])<0.5,"",(Proj2018[[#This Row],[PROJ TOTAL PTS]]-Proj2018[[#This Row],[LastProj]])/16) | W14: K | Y14: =IF(Proj2018[[#This Row],[POS]]="K",-100,Proj2018[[#This Row],[VAR/G]]+1.5) -> 1.3125 | Z14: =ROUND(MAX(Proj2018[[#This Row],[VAWG]],0)*$AC$9,0)+1 -> 152
A15: 2018 | B15: Patrick Mahomes | C15: KC | D15: QB | E15: 344 | F15: 548 | G15: 4118 | H15: 22 | I15: 15 | J15: 66 | K15: 344 | L15: 3 | M15: 0 | N15: 0 | O15: 0 | P15: 275.12 | Q15: 278.68 | R15: -3.56 | S15: -0.2225 | U15: 275.12 | V15: =IF(ABS(Proj2018[[#This Row],[LastProj]]-Proj2018[[#This Row],[PROJ TOTAL PTS]])<0.5,"",(Proj2018[[#This Row],[PROJ TOTAL PTS]]-Proj2018[[#This Row],[LastProj]])/16) | W15: K | Y15: =IF(Proj2018[[#This Row],[POS]]="K",-100,Proj2018[[#This Row],[VAR/G]]+1.5) -> 1.2775 | Z15: =ROUND(MAX(Proj2018[[#This Row],[VAWG]],0)*$AC$9,0)+1 -> 148
A16: 2018 | B16: Le'Veon Bell | C16: Pit | D16: RB | E16: 0 | F16: 0 | G16: 0 | H16: 0 | I16: 0 | J16: 307 | K16: 1319 | L16: 10 | M16: 79 | N16: 635 | O16: 3 | P16: 273.4 | Q16: 118.8 | R16: 154.6 | S16: 9.6625 | U16: 273.4 | V16: =IF(ABS(Proj2018[[#This Row],[LastProj]]-Proj2018[[#This Row],[PROJ TOTAL PTS]])<0.5,"",(Proj2018[[#This Row],[PROJ TOTAL PTS]]-Proj2018[[#This Row],[LastProj]])/16) | W16: K | Y16: =IF(Proj2018[[#This Row],[POS]]="K",-100,Proj2018[[#This Row],[VAR/G]]+1.5) -> 11.1625 | Z16: =ROUND(MAX(Proj2018[[#This Row],[VAWG]],0)*$AC$9,0)+1 -> 1282
A17: 2018 | B17: Matt Ryan | C17: Atl | D17: QB | E17: 357 | F17: 550 | G17: 4307 | H17: 26 | I17: 10 | J17: 33 | K17: 108 | L17: 1 | M17: 0 | N17: 0 | O17: 0 | P17: 273.08 | Q17: 278.68 | R17: -5.6 | S17: -0.35 | U17: 273.08 | V17: =IF(ABS(Proj2018[[#This Row],[LastProj]]-Proj2018[[#This Row],[PROJ TOTAL PTS]])<0.5,"",(Proj2018[[#This Row],[PROJ TOTAL PTS]]-Proj2018[[#This Row],[LastProj]])/16) | W17: K | Y17: =IF(Proj2018[[#This Row],[POS]]="K",-100,Proj2018[[#This Row],[VAR/G]]+1.5) -> 1.15 | Z17: =ROUND(MAX(Proj2018[[#This Row],[VAWG]],0)*$AC$9,0)+1 -> 133
A18: 2018 | B18: Jimmy Garoppolo | C18: SF | D18: QB | E18: 377 | F18: 591 | G18: 4354 | H18: 24 | I18: 13 | J18: 43 | K18: 107 | L18: 2 | M18: 0 | N18: 0 | O18: 0 | P18: 266.86 | Q18: 278.68 | R18: -11.82 | S18: -0.73875 | U18: 266.86 | V18: =IF(ABS(Proj2018[[#This Row],[LastProj]]-Proj2018[[#This Row],[PROJ TOTAL PTS]])<0.5,"",(Proj2018[[#This Row],[PROJ TOTAL PTS]]-Proj2018[[#This Row],[LastProj]])/16) | W18: K | Y18: =IF(Proj2018[[#This Row],[POS]]="K",-100,Proj2018[[#This Row],[VAR/G]]+1.5) -> 0.76125 | Z18: =ROUND(MAX(Proj2018[[#This Row],[VAWG]],0)*$AC$9,0)+1 -> 88
A19: 2018 | B19: Philip Rivers | C19: LAC | D19: QB | E19: 362 | F19: 576 | G19: 4336 | H19: 28 | I19: 12 | J19: 24 | K19: 49 | L19: 0 | M19: 0 | N19: 0 | O19: 0 | P19: 266.34 | Q19: 278.68 | R19: -12.34 | S19: -0.77125 | U19: 266.34 | V19: =IF(ABS(Proj2018[[#This Row],[LastProj]]-Proj2018[[#This Row],[PROJ TOTAL PTS]])<0.5,"",(Proj2018[[#This Row],[PROJ TOTAL PTS]]-Proj2018[[#This Row],[LastProj]])/16) | W19: K | Y19: =IF(Proj2018[[#This Row],[POS]]="K",-100,Proj2018[[#This Row],[VAR/G]]+1.5) -> 0.72875 | Z19: =ROUND(MAX(Proj2018[[#This Row],[VAWG]],0)*$AC$9,0)+1 -> 85
A20: 2018 | B20: Todd Gurley II | C20: LAR | D20: RB | E20: 0 | F20: 0 | G20: 0 | H20: 0 | I20: 0 | J20: 284 | K20: 1274 | L20: 10 | M20: 67 | N20: 595 | O20: 3 | P20: 264.9 | Q20: 118.8 | R20: 146.1 | S20: 9.13125 | U20: 264.9 | V20: =IF(ABS(Proj2018[[#This Row],[LastProj]]-Proj2018[[#This Row],[PROJ TOTAL PTS]])<0.5,"",(Proj2018[[#This Row],[PROJ TOTAL PTS]]-Proj2018[[#This Row],[LastProj]])/16) | W20: K | Y20: =IF(Proj2018[[#This Row],[POS]]="K",-100,Proj2018[[#This Row],[VAR/G]]+1.5) -> 10.63125 | Z20: =ROUND(MAX(Proj2018[[#This Row],[VAWG]],0)*$AC$9,0)+1 -> 1221
A21: 2018 | B21: Mitchell Trubisky | C21: Chi | D21: QB | E21: 347 | F21: 567 | G21: 3949 | H21: 23 | I21: 13 | J21: 63 | K21: 280 | L21: 2 | M21: 0 | N21: 0 | O21: 0 | P21: 263.96 | Q21: 278.68 | R21: -14.72 | S21: -0.92 | U21: 263.96 | V21: =IF(ABS(Proj2018[[#This Row],[LastProj]]-Proj2018[[#This Row],[PROJ TOTAL PTS]])<0.5,"",(Proj2018[[#This Row],[PROJ TOTAL PTS]]-Proj2018[[#This Row],[LastProj]])/16) | W21: K | Y21: =IF(Proj2018[[#This Row],[POS]]="K",-100,Proj2018[[#This Row],[VAR/G]]+1.5) -> 0.58 | Z21: =ROUND(MAX(Proj2018[[#This Row],[VAWG]],0)*$AC$9,0)+1 -> 68
... A23: 2018 | B23: Andy Dalton | C23: Cin | D23: QB | E23: 344 | F23: 558 | G23: 4009 | H23: 24 | I23: 11 | J23: 44 | K23: 154 | L23: 1 | M23: 0 | N23: 0 | O23: 0 | P23: 255.76 | Q23: 278.68 | R23: -22.92 | S23: -1.4325 | U23: 255.76 | V23: =IF(ABS(Proj2018[[#This Row],[LastProj]]-Proj2018[[#This Row],[PROJ TOTAL PTS]])<0.5,"",(Proj2018[[#This Row],[PROJ TOTAL PTS]]-Proj2018[[#This Row],[LastProj]])/16) | W23: K | Y23: =IF(Proj2018[[#This Row],[POS]]="K",-100,Proj2018[[#This Row],[VAR/G]]+1.5) -> 0.0675 | Z23: =ROUND(MAX(Proj2018[[#This Row],[VAWG]],0)*$AC$9,0)+1 -> 9
A24: 2018 | B24: Ryan Tannehill | C24: Mia | D24: QB | E24: 364 | F24: 571 | G24: 4150 | H24: 23 | I24: 14 | J24: 41 | K24: 186 | L24: 1 | M24: 0 | N24: 0 | O24: 0 | P24: 254.6 | Q24: 278.68 | R24: -24.08 | S24: -1.505 | U24: 254.6 | V24: =IF(ABS(Proj2018[[#This Row],[LastProj]]-Proj2018[[#This Row],[PROJ TOTAL PTS]])<0.5,"",(Proj2018[[#This Row],[PROJ TOTAL PTS]]-Proj2018[[#This Row],[LastProj]])/16) | Y24: =IF(Proj2018[[#This Row],[POS]]="K",-100,Proj2018[[#This Row],[VAR/G]]+1.5) -> -0.005 | Z24: =ROUND(MAX(Proj2018[[#This Row],[VAWG]],0)*$AC$9,0)+1 -> 1
A25: 2018 | B25: Dak Prescott | C25: Dal | D25: QB | E25: 325 | F25: 515 | G25: 3697 | H25: 21 | I25: 13 | J25: 56 | K25: 306 | L25: 3 | M25: 0 | N25: 0 | O25: 0 | P25: 254.48 | Q25: 278.68 | R25: -24.2 | S25: -1.5125 | U25: 254.48 | V25: =IF(ABS(Proj2018[[#This Row],[LastProj]]-Proj2018[[#This Row],[PROJ TOTAL PTS]])<0.5,"",(Proj2018[[#This Row],[PROJ TOTAL PTS]]-Proj2018[[#This Row],[LastProj]])/16) | W25: K | Y25: =IF(Proj2018[[#This Row],[POS]]="K",-100,Proj2018[[#This Row],[VAR/G]]+1.5) -> -0.0125 | Z25: =ROUND(MAX(Proj2018[[#This Row],[VAWG]],0)*$AC$9,0)+1 -> 1
A26: 2018 | B26: Blake Bortles | C26: Jax | D26: QB | E26: 324 | F26: 533 | G26: 3725 | H26: 20 | I26: 12 | J26: 58 | K26: 333 | L26: 2 | M26: 0 | N26: 0 | O26: 0 | P26: 250.3 | Q26: 278.68 | R26: -28.38 | S26: -1.77375 | U26: 250.3 | V26: =IF(ABS(Proj2018[[#This Row],[LastProj]]-Proj2018[[#This Row],[PROJ TOTAL PTS]])<0.5,"",(Proj2018[[#This Row],[PROJ TOTAL PTS]]-Proj2018[[#This Row],[LastProj]])/16) | Y26: =IF(Proj2018[[#This Row],[POS]]="K",-100,Proj2018[[#This Row],[VAR/G]]+1.5) -> -0.27375 | Z26: =ROUND(MAX(Proj2018[[#This Row],[VAWG]],0)*$AC$9,0)+1 -> 1
A27: 2018 | B27: Ezekiel Elliott | C27: Dal | D27: RB | E27: 0 | F27: 0 | G27: 0 | H27: 0 | I27: 0 | J27: 324 | K27: 1404 | L27: 11 | M27: 44 | N27: 370 | O27: 1 | P27: 249.4 | Q27: 118.8 | R27: 130.6 | S27: 8.1625 | U27: 249.4 | V27: =IF(ABS(Proj2018[[#This Row],[LastProj]]-Proj2018[[#This Row],[PROJ TOTAL PTS]])<0.5,"",(Proj2018[[#This Row],[PROJ TOTAL PTS]]-Proj2018[[#This Row],[LastProj]])/16) | W27: K | Y27: =IF(Proj2018[[#This Row],[POS]]="K",-100,Proj2018[[#This Row],[VAR/G]]+1.5) -> 9.6625 | Z27: =ROUND(MAX(Proj2018[[#This Row],[VAWG]],0)*$AC$9,0)+1 -> 1110
A28: 2018 | B28: David Johnson | C28: Ari | D28: RB | E28: 0 | F28: 0 | G28: 0 | H28: 0 | I28: 0 | J28: 266 | K28: 1087 | L28: 8 | M28: 77 | N28: 739 | O28: 3 | P28: 248.6 | Q28: 118.8 | R28: 129.8 | S28: 8.1125 | U28: 248.6 | V28: =IF(ABS(Proj2018[[#This Row],[LastProj]]-Proj2018[[#This Row],[PROJ TOTAL PTS]])<0.5,"",(Proj2018[[#This Row],[PROJ TOTAL PTS]]-Proj2018[[#This Row],[LastProj]])/16) | W28: K | Y28: =IF(Proj2018[[#This Row],[POS]]="K",-100,Proj2018[[#This Row],[VAR/G]]+1.5) -> 9.6125 | Z28: =ROUND(MAX(Proj2018[[#This Row],[VAWG]],0)*$AC$9,0)+1 -> 1104
A29: 2018 | B29: Case Keenum | C29: Den | D29: QB | E29: 368 | F29: 588 | G29: 4092 | H29: 22 | I29: 12 | J29: 40 | K29: 144 | L29: 1 | M29: 0 | N29: 0 | O29: 0 | P29: 248.08 | Q29: 278.68 | R29: -30.6 | S29: -1.9125 | U29: 248.08 | V29: =IF(ABS(Proj2018[[#This Row],[LastProj]]-Proj2018[[#This Row],[PROJ TOTAL PTS]])<0.5,"",(Proj2018[[#This Row],[PROJ TOTAL PTS]]-Proj2018[[#This Row],[LastProj]])/16) | Y29: =IF(Proj2018[[#This Row],[POS]]="K",-100,Proj2018[[#This Row],[VAR/G]]+1.5) -> -0.4125 | Z29: =ROUND(MAX(Proj2018[[#This Row],[VAWG]],0)*$AC$9,0)+1 -> 1
A30: 2018 | B30: Derek Carr | C30: Oak | D30: QB | E30: 352 | F30: 574 | G30: 3963 | H30: 24 | I30: 12 | J30: 32 | K30: 89 | L30: 1 | M30: 0 | N30: 0 | O30: 0 | P30: 245.42 | Q30: 278.68 | R30: -33.26 | S30: -2.07875 | U30: 245.42 | V30: =IF(ABS(Proj2018[[#This Row],[LastProj]]-Proj2018[[#This Row],[PROJ TOTAL PTS]])<0.5,"",(Proj2018[[#This Row],[PROJ TOTAL PTS]]-Proj2018[[#This Row],[LastProj]])/16) | W30: K | Y30: =IF(Proj2018[[#This Row],[POS]]="K",-100,Proj2018[[#This Row],[VAR/G]]+1.5) -> -0.57875 | Z30: =ROUND(MAX(Proj2018[[#This Row],[VAWG]],0)*$AC$9,0)+1 -> 1
A31: 2018 | B31: Eli Manning | C31: NYG | D31: QB | E31: 369 | F31: 598 | G31: 4107 | H31: 26 | I31: 15 | J31: 18 | K31: 27 | L31: 0 | M31: 0 | N31: 0 | O31: 0 | P31: 240.98 | Q31: 278.68 | R31: -37.7 | S31: -2.35625 | U31: 240.98 | V31: =IF(ABS(Proj2018[[#This Row],[LastProj]]-Proj2018[[#This Row],[PROJ TOTAL PTS]])<0.5,"",(Proj2018[[#This Row],[PROJ TOTAL PTS]]-Proj2018[[#This Row],[LastProj]])/16) | Y31: =IF(Proj2018[[#This Row],[POS]]="K",-100,Proj2018[[#This Row],[VAR/G]]+1.5) -> -0.85625 | Z31: =ROUND(MAX(Proj2018[[#This Row],[VAWG]],0)*$AC$9,0)+1 -> 1
A32: 2018 | B32: Jameis Winston | C32: TB | D32: QB | E32: 290 | F32: 468 | G32: 3595 | H32: 23 | I32: 12 | J32: 38 | K32: 161 | L32: 1 | M32: 0 | N32: 0 | O32: 0 | P32: 233.9 | Q32: 278.68 | R32: -44.78 | S32: -2.79875 | U32: 233.9 | V32: =IF(ABS(Proj2018[[#This Row],[LastProj]]-Proj2018[[#This Row],[PROJ TOTAL PTS]])<0.5,"",(Proj2018[[#This Row],[PROJ TOTAL PTS]]-Proj2018[[#This Row],[LastProj]])/16) | Y32: =IF(Proj2018[[#This Row],[POS]]="K",-100,Proj2018[[#This Row],[VAR/G]]+1.5) -> -1.29875 | Z32: =ROUND(MAX(Proj2018[[#This Row],[VAWG]],0)*$AC$9,0)+1 -> 1
A33: 2018 | B33: Tyrod Taylor | C33: Cle | D33: QB | E33: 244 | F33: 395 | G33: 2764 | H33: 18 | I33: 6 | J33: 67 | K33: 384 | L33: 3 | M33: 0 | N33: 0 | O33: 0 | P33: 226.96 | Q33: 278.68 | R33: -51.72 | S33: -3.2325 | U33: 226.96 | V33: =IF(ABS(Proj2018[[#This Row],[LastProj]]-Proj2018[[#This Row],[PROJ TOTAL PTS]])<0.5,"",(Proj2018[[#This Row],[PROJ TOTAL PTS]]-Proj2018[[#This Row],[LastProj]])/16) | Y33: =IF(Proj2018[[#This Row],[POS]]="K",-100,Proj2018[[#This Row],[VAR/G]]+1.5) -> -1.7325 | Z33: =ROUND(MAX(Proj2018[[#This Row],[VAWG]],0)*$AC$9,0)+1 -> 1
A34: 2018 | B34: Saquon Barkley | C34: NYG | D34: RB | E34: 0 | F34: 0 | G34: 0 | H34: 0 | I34: 0 | J34: 258 | K34: 1133 | L34: 7 | M34: 60 | N34: 533 | O34: 3 | P34: 226.6 | Q34: 118.8 | R34: 107.8 | S34: 6.7375 | T34: Rookie | U34: 226.6 | V34: =IF(ABS(Proj2018[[#This Row],[LastProj]]-Proj2018[[#This Row],[PROJ TOTAL PTS]])<0.5,"",(Proj2018[[#This Row],[PROJ TOTAL PTS]]-Proj2018[[#This Row],[LastProj]])/16) | W34: K | Y34: =IF(Proj2018[[#This Row],[POS]]="K",-100,Proj2018[[#This Row],[VAR/G]]+1.5) -> 8.2375 | Z34: =ROUND(MAX(Proj2018[[#This Row],[VAWG]],0)*$AC$9,0)+1 -> 947
A35: 2018 | B35: Alvin Kamara | C35: NO | D35: RB | E35: 0 | F35: 0 | G35: 0 | H35: 0 | I35: 0 | J35: 186 | K35: 843 | L35: 8 | M35: 74 | N35: 716 | O35: 3 | P35: 221.9 | Q35: 118.8 | R35: 103.1 | S35: 6.44375 | U35: 221.9 | V35: =IF(ABS(Proj2018[[#This Row],[LastProj]]-Proj2018[[#This Row],[PROJ TOTAL PTS]])<0.5,"",(Proj2018[[#This Row],[PROJ TOTAL PTS]]-Proj2018[[#This Row],[LastProj]])/16) | W35: K | Y35: =IF(Proj2018[[#This Row],[POS]]="K",-100,Proj2018[[#This Row],[VAR/G]]+1.5) -> 7.94375 | Z35: =ROUND(MAX(Proj2018[[#This Row],[VAWG]],0)*$AC$9,0)+1 -> 913
A36: 2018 | B36: Leonard Fournette | C36: Jax | D36: RB | E36: 0 | F36: 0 | G36: 0 | H36: 0 | I36: 0 | J36: 310 | K36: 1202 | L36: 10 | M36: 40 | N36: 329 | O36: 1 | P36: 219.1 | Q36: 118.8 | R36: 100.3 | S36: 6.26875 | U36: 219.1 | V36: =IF(ABS(Proj2018[[#This Row],[LastProj]]-Proj2018[[#This Row],[PROJ TOTAL PTS]])<0.5,"",(Proj2018[[#This Row],[PROJ TOTAL PTS]]-Proj2018[[#This Row],[LastProj]])/16) | W36: K | Y36: =IF(Proj2018[[#This Row],[POS]]="K",-100,Proj2018[[#This Row],[VAR/G]]+1.5) -> 7.76875 | Z36: =ROUND(MAX(Proj2018[[#This Row],[VAWG]],0)*$AC$9,0)+1 -> 893
A37: 2018 | B37: Dalvin Cook | C37: Min | D37: RB | E37: 0 | F37: 0 | G37: 0 | H37: 0 | I37: 0 | J37: 261 | K37: 1108 | L37: 7 | M37: 54 | N37: 500 | O37: 2 | P37: 214.8 | Q37: 118.8 | R37: 96 | S37: 6 | U37: 214.8 | V37: =IF(ABS(Proj2018[[#This Row],[LastProj]]-Proj2018[[#This Row],[PROJ TOTAL PTS]])<0.5,"",(Proj2018[[#This Row],[PROJ TOTAL PTS]]-Proj2018[[#This Row],[LastProj]])/16) | W37: K | Y37: =IF(Proj2018[[#This Row],[POS]]="K",-100,Proj2018[[#This Row],[VAR/G]]+1.5) -> 7.5 | Z37: =ROUND(MAX(Proj2018[[#This Row],[VAWG]],0)*$AC$9,0)+1 -> 862
A38: 2018 | B38: Antonio Brown | C38: Pit | D38: WR | E38: 0 | F38: 0 | G38: 0 | H38: 0 | I38: 0 | J38: 0 | K38: 0 | L38: 0 | M38: 110 | N38: 1576 | O38: 9 | P38: 211.6 | Q38: 117.7 | R38: 93.9 | S38: 5.86875 | U38: 211.6 | V38: =IF(ABS(Proj2018[[#This Row],[LastProj]]-Proj2018[[#This Row],[PROJ TOTAL PTS]])<0.5,"",(Proj2018[[#This Row],[PROJ TOTAL PTS]]-Proj2018[[#This Row],[LastProj]])/16) | W38: K | Y38: =IF(Proj2018[[#This Row],[POS]]="K",-100,Proj2018[[#This Row],[VAR/G]]+1.5) -> 7.36875 | Z38: =ROUND(MAX(Proj2018[[#This Row],[VAWG]],0)*$AC$9,0)+1 -> 847
A39: 2018 | B39: Kareem Hunt | C39: KC | D39: RB | E39: 0 | F39: 0 | G39: 0 | H39: 0 | I39: 0 | J39: 236 | K39: 999 | L39: 8 | M39: 56 | N39: 450 | O39: 2 | P39: 204.9 | Q39: 118.8 | R39: 86.1 | S39: 5.38125 | U39: 204.9 | V39: =IF(ABS(Proj2018[[#This Row],[LastProj]]-Proj2018[[#This Row],[PROJ TOTAL PTS]])<0.5,"",(Proj2018[[#This Row],[PROJ TOTAL PTS]]-Proj2018[[#This Row],[LastProj]])/16) | W39: K | Y39: =IF(Proj2018[[#This Row],[POS]]="K",-100,Proj2018[[#This Row],[VAR/G]]+1.5) -> 6.88125 | Z39: =ROUND(MAX(Proj2018[[#This Row],[VAWG]],0)*$AC$9,0)+1 -> 791
A40: 2018 | B40: Joe Flacco | C40: Bal | D40: QB | E40: 343 | F40: 546 | G40: 3528 | H40: 18 | I40: 11 | J40: 25 | K40: 46 | L40: 1 | M40: 0 | N40: 0 | O40: 0 | P40: 201.72 | Q40: 278.68 | R40: -76.96 | S40: -4.81 | U40: 201.72 | V40: =IF(ABS(Proj2018[[#This Row],[LastProj]]-Proj2018[[#This Row],[PROJ TOTAL PTS]])<0.5,"",(Proj2018[[#This Row],[PROJ TOTAL PTS]]-Proj2018[[#This Row],[LastProj]])/16) | Y40: =IF(Proj2018[[#This Row],[POS]]="K",-100,Proj2018[[#This Row],[VAR/G]]+1.5) -> -3.31 | Z40: =ROUND(MAX(Proj2018[[#This Row],[VAWG]],0)*$AC$9,0)+1 -> 1
A41: 2018 | B41: LeSean McCoy | C41: Buf | D41: RB | E41: 0 | F41: 0 | G41: 0 | H41: 0 | I41: 0 | J41: 244 | K41: 1098 | L41: 6 | M41: 57 | N41: 437 | O41: 2 | P41: 201.5 | Q41: 118.8 | R41: 82.7 | S41: 5.16875 | U41: 201.5 | V41: =IF(ABS(Proj2018[[#This Row],[LastProj]]-Proj2018[[#This Row],[PROJ TOTAL PTS]])<0.5,"",(Proj2018[[#This Row],[PROJ TOTAL PTS]]-Proj2018[[#This Row],[LastProj]])/16) | W41: K | X41: RFA | Y41: =IF(Proj2018[[#This Row],[POS]]="K",-100,Proj2018[[#This Row],[VAR/G]]+1.5) -> 6.66875 | Z41: =ROUND(MAX(Proj2018[[#This Row],[VAWG]],0)*$AC$9,0)+1 -> 767
A42: 2018 | B42: Melvin Gordon | C42: LAC | D42: RB | E42: 0 | F42: 0 | G42: 0 | H42: 0 | I42: 0 | J42: 264 | K42: 1024 | L42: 6 | M42: 60 | N42: 502 | O42: 2 | P42: 200.6 | Q42: 118.8 | R42: 81.8 | S42: 5.1125 | U42: 200.6 | V42: =IF(ABS(Proj2018[[#This Row],[LastProj]]-Proj2018[[#This Row],[PROJ TOTAL PTS]])<0.5,"",(Proj2018[[#This Row],[PROJ TOTAL PTS]]-Proj2018[[#This Row],[LastProj]])/16) | W42: K | Y42: =IF(Proj2018[[#This Row],[POS]]="K",-100,Proj2018[[#This Row],[VAR/G]]+1.5) -> 6.6125 | Z42: =ROUND(MAX(Proj2018[[#This Row],[VAWG]],0)*$AC$9,0)+1 -> 760
A43: 2018 | B43: Julio Jones | C43: Atl | D43: WR | E43: 0 | F43: 0 | G43: 0 | H43: 0 | I43: 0 | J43: 2 | K43: 12 | L43: 0 | M43: 94 | N43: 1486 | O43: 8 | P43: 197.8 | Q43: 117.7 | R43: 80.1 | S43: 5.00625 | U43: 197.8 | V43: =IF(ABS(Proj2018[[#This Row],[LastProj]]-Proj2018[[#This Row],[PROJ TOTAL PTS]])<0.5,"",(Proj2018[[#This Row],[PROJ TOTAL PTS]]-Proj2018[[#This Row],[LastProj]])/16) | W43: K | X43: RFA | Y43: =IF(Proj2018[[#This Row],[POS]]="K",-100,Proj2018[[#This Row],[VAR/G]]+1.5) -> 6.50625 | Z43: =ROUND(MAX(Proj2018[[#This Row],[VAWG]],0)*$AC$9,0)+1 -> 748
A44: 2018 | B44: DeAndre Hopkins | C44: Hou | D44: WR | E44: 0 | F44: 0 | G44: 0 | H44: 0 | I44: 0 | J44: 0 | K44: 0 | L44: 0 | M44: 94 | N44: 1326 | O44: 10 | P44: 192.6 | Q44: 117.7 | R44: 74.9 | S44: 4.68125 | U44: 192.6 | V44: =IF(ABS(Proj2018[[#This Row],[LastProj]]-Proj2018[[#This Row],[PROJ TOTAL PTS]])<0.5,"",(Proj2018[[#This Row],[PROJ TOTAL PTS]]-Proj2018[[#This Row],[LastProj]])/16) | W44: K | Y44: =IF(Proj2018[[#This Row],[POS]]="K",-100,Proj2018[[#This Row],[VAR/G]]+1.5) -> 6.18125 | Z44: =ROUND(MAX(Proj2018[[#This Row],[VAWG]],0)*$AC$9,0)+1 -> 711
A45: 2018 | B45: Devonta Freeman | C45: Atl | D45: RB | E45: 0 | F45: 0 | G45: 0 | H45: 0 | I45: 0 | J45: 223 | K45: 939 | L45: 8 | M45: 42 | N45: 360 | O45: 2 | P45: 189.9 | Q45: 118.8 | R45: 71.1 | S45: 4.44375 | U45: 189.9 | V45: =IF(ABS(Proj2018[[#This Row],[LastProj]]-Proj2018[[#This Row],[PROJ TOTAL PTS]])<0.5,"",(Proj2018[[#This Row],[PROJ TOTAL PTS]]-Proj2018[[#This Row],[LastProj]])/16) | W45: K | Y45: =IF(Proj2018[[#This Row],[POS]]="K",-100,Proj2018[[#This Row],[VAR/G]]+1.5) -> 5.94375 | Z45: =ROUND(MAX(Proj2018[[#This Row],[VAWG]],0)*$AC$9,0)+1 -> 683
A46: 2018 | B46: Odell Beckham Jr. | C46: NYG | D46: WR | E46: 0 | F46: 0 | G46: 0 | H46: 0 | I46: 0 | J46: 4 | K46: 21 | L46: 0 | M46: 99 | N46: 1300 | O46: 8 | P46: 180.1 | Q46: 117.7 | R46: 62.4 | S46: 3.9 | U46: 180.1 | V46: =IF(ABS(Proj2018[[#This Row],[LastProj]]-Proj2018[[#This Row],[PROJ TOTAL PTS]])<0.5,"",(Proj2018[[#This Row],[PROJ TOTAL PTS]]-Proj2018[[#This Row],[LastProj]])/16) | W46: K | Y46: =IF(Proj2018[[#This Row],[POS]]="K",-100,Proj2018[[#This Row],[VAR/G]]+1.5) -> 5.4 | Z46: =ROUND(MAX(Proj2018[[#This Row],[VAWG]],0)*$AC$9,0)+1 -> 621
A47: 2018 | B47: Keenan Allen | C47: LAC | D47: WR | E47: 0 | F47: 0 | G47: 0 | H47: 0 | I47: 0 | J47: 2 | K47: 13 | L47: 0 | M47: 101 | N47: 1307 | O47: 8 | P47: 180 | Q47: 117.7 | R47: 62.3 | S47: 3.89375 | U47: 180 | V47: =IF(ABS(Proj2018[[#This Row],[LastProj]]-Proj2018[[#This Row],[PROJ TOTAL PTS]])<0.5,"",(Proj2018[[#This Row],[PROJ TOTAL PTS]]-Proj2018[[#This Row],[LastProj]])/16) | W47: K | Y47: =IF(Proj2018[[#This Row],[POS]]="K",-100,Proj2018[[#This Row],[VAR/G]]+1.5) -> 5.39375 | Z47: =ROUND(MAX(Proj2018[[#This Row],[VAWG]],0)*$AC$9,0)+1 -> 620
A48: 2018 | B48: A.J. Green | C48: Cin | D48: WR | E48: 0 | F48: 0 | G48: 0 | H48: 0 | I48: 0 | J48: 0 | K48: 0 | L48: 0 | M48: 90 | N48: 1297 | O48: 8 | P48: 177.7 | Q48: 117.7 | R48: 60 | S48: 3.75 | U48: 177.7 | V48: =IF(ABS(Proj2018[[#This Row],[LastProj]]-Proj2018[[#This Row],[PROJ TOTAL PTS]])<0.5,"",(Proj2018[[#This Row],[PROJ TOTAL PTS]]-Proj2018[[#This Row],[LastProj]])/16) | W48: K | Y48: =IF(Proj2018[[#This Row],[POS]]="K",-100,Proj2018[[#This Row],[VAR/G]]+1.5) -> 5.25 | Z48: =ROUND(MAX(Proj2018[[#This Row],[VAWG]],0)*$AC$9,0)+1 -> 604
A49: 2018 | B49: Jerick McKinnon | C49: SF | D49: RB | E49: 0 | F49: 0 | G49: 0 | H49: 0 | I49: 0 | J49: 217 | K49: 876 | L49: 7 | M49: 54 | N49: 407 | O49: 1 | P49: 176.3 | Q49: 118.8 | R49: 57.5 | S49: 3.59375 | U49: 176.3 | V49: =IF(ABS(Proj2018[[#This Row],[LastProj]]-Proj2018[[#This Row],[PROJ TOTAL PTS]])<0.5,"",(Proj2018[[#This Row],[PROJ TOTAL PTS]]-Proj2018[[#This Row],[LastProj]])/16) | W49: K | Y49: =IF(Proj2018[[#This Row],[POS]]="K",-100,Proj2018[[#This Row],[VAR/G]]+1.5) -> 5.09375 | Z49: =ROUND(MAX(Proj2018[[#This Row],[VAWG]],0)*$AC$9,0)+1 -> 586
A50: 2018 | B50: Derrius Guice | C50: Was | D50: RB | E50: 0 | F50: 0 | G50: 0 | H50: 0 | I50: 0 | J50: 236 | K50: 998 | L50: 8 | M50: 25 | N50: 208 | O50: 1 | P50: 174.6 | Q50: 118.8 | R50: 55.8 | S50: 3.4875 | T50: Rookie | U50: 174.6 | V50: =IF(ABS(Proj2018[[#This Row],[LastProj]]-Proj2018[[#This Row],[PROJ TOTAL PTS]])<0.5,"",(Proj2018[[#This Row],[PROJ TOTAL PTS]]-Proj2018[[#This Row],[LastProj]])/16) | W50: K | Y50: =IF(Proj2018[[#This Row],[POS]]="K",-100,Proj2018[[#This Row],[VAR/G]]+1.5) -> 4.9875 | Z50: =ROUND(MAX(Proj2018[[#This Row],[VAWG]],0)*$AC$9,0)+1 -> 574
A51: 2018 | B51: Michael Thomas | C51: NO | D51: WR | E51: 0 | F51: 0 | G51: 0 | H51: 0 | I51: 0 | J51: 0 | K51: 0 | L51: 0 | M51: 100 | N51: 1263 | O51: 8 | P51: 174.3 | Q51: 117.7 | R51: 56.6 | S51: 3.5375 | U51: 174.3 | V51: =IF(ABS(Proj2018[[#This Row],[LastProj]]-Proj2018[[#This Row],[PROJ TOTAL PTS]])<0.5,"",(Proj2018[[#This Row],[PROJ TOTAL PTS]]-Proj2018[[#This Row],[LastProj]])/16) | W51: K | Y51: =IF(Proj2018[[#This Row],[POS]]="K",-100,Proj2018[[#This Row],[VAR/G]]+1.5) -> 5.0375 | Z51: =ROUND(MAX(Proj2018[[#This Row],[VAWG]],0)*$AC$9,0)+1 -> 579
A52: 2018 | B52: Christian McCaffrey | C52: Car | D52: RB | E52: 0 | F52: 0 | G52: 0 | H52: 0 | I52: 0 | J52: 159 | K52: 635 | L52: 4 | M52: 78 | N52: 687 | O52: 3 | P52: 174.2 | Q52: 118.8 | R52: 55.4 | S52: 3.4625 | U52: 174.2 | V52: =IF(ABS(Proj2018[[#This Row],[LastProj]]-Proj2018[[#This Row],[PROJ TOTAL PTS]])<0.5,"",(Proj2018[[#This Row],[PROJ TOTAL PTS]]-Proj2018[[#This Row],[LastProj]])/16) | W52: K | Y52: =IF(Proj2018[[#This Row],[POS]]="K",-100,Proj2018[[#This Row],[VAR/G]]+1.5) -> 4.9625 | Z52: =ROUND(MAX(Proj2018[[#This Row],[VAWG]],0)*$AC$9,0)+1 -> 571
A53: 2018 | B53: Jordan Howard | C53: Chi | D53: RB | E53: 0 | F53: 0 | G53: 0 | H53: 0 | I53: 0 | J53: 239 | K53: 1023 | L53: 7 | M53: 29 | N53: 231 | O53: 1 | P53: 173.4 | Q53: 118.8 | R53: 54.6 | S53: 3.4125 | U53: 173.4 | V53: =IF(ABS(Proj2018[[#This Row],[LastProj]]-Proj2018[[#This Row],[PROJ TOTAL PTS]])<0.5,"",(Proj2018[[#This Row],[PROJ TOTAL PTS]]-Proj2018[[#This Row],[LastProj]])/16) | W53: K | Y53: =IF(Proj2018[[#This Row],[POS]]="K",-100,Proj2018[[#This Row],[VAR/G]]+1.5) -> 4.9125 | Z53: =ROUND(MAX(Proj2018[[#This Row],[VAWG]],0)*$AC$9,0)+1 -> 565
A54: 2018 | B54: Marshawn Lynch | C54: Oak | D54: RB | E54: 0 | F54: 0 | G54: 0 | H54: 0 | I54: 0 | J54: 220 | K54: 957 | L54: 8 | M54: 29 | N54: 229 | O54: 1 | P54: 172.6 | Q54: 118.8 | R54: 53.8 | S54: 3.3625 | U54: 172.6 | V54: =IF(ABS(Proj2018[[#This Row],[LastProj]]-Proj2018[[#This Row],[PROJ TOTAL PTS]])<0.5,"",(Proj2018[[#This Row],[PROJ TOTAL PTS]]-Proj2018[[#This Row],[LastProj]])/16) | W54: K | Y54: =IF(Proj2018[[#This Row],[POS]]="K",-100,Proj2018[[#This Row],[VAR/G]]+1.5) -> 4.8625 | Z54: =ROUND(MAX(Proj2018[[#This Row],[VAWG]],0)*$AC$9,0)+1 -> 559
A55: 2018 | B55: Davante Adams | C55: GB | D55: WR | E55: 0 | F55: 0 | G55: 0 | H55: 0 | I55: 0 | J55: 0 | K55: 0 | L55: 0 | M55: 86 | N55: 1087 | O55: 10 | P55: 168.7 | Q55: 117.7 | R55: 51 | S55: 3.1875 | U55: 168.7 | V55: =IF(ABS(Proj2018[[#This Row],[LastProj]]-Proj2018[[#This Row],[PROJ TOTAL PTS]])<0.5,"",(Proj2018[[#This Row],[PROJ TOTAL PTS]]-Proj2018[[#This Row],[LastProj]])/16) | W55: K | Y55: =IF(Proj2018[[#This Row],[POS]]="K",-100,Proj2018[[#This Row],[VAR/G]]+1.5) -> 4.6875 | Z55: =ROUND(MAX(Proj2018[[#This Row],[VAWG]],0)*$AC$9,0)+1 -> 539
A56: 2018 | B56: T.Y. Hilton | C56: Ind | D56: WR | E56: 0 | F56: 0 | G56: 0 | H56: 0 | I56: 0 | J56: 0 | K56: 0 | L56: 0 | M56: 75 | N56: 1249 | O56: 7 | P56: 166.9 | Q56: 117.7 | R56: 49.2 | S56: 3.075 | U56: 166.9 | V56: =IF(ABS(Proj2018[[#This Row],[LastProj]]-Proj2018[[#This Row],[PROJ TOTAL PTS]])<0.5,"",(Proj2018[[#This Row],[PROJ TOTAL PTS]]-Proj2018[[#This Row],[LastProj]])/16) | W56: K | Y56: =IF(Proj2018[[#This Row],[POS]]="K",-100,Proj2018[[#This Row],[VAR/G]]+1.5) -> 4.575 | Z56: =ROUND(MAX(Proj2018[[#This Row],[VAWG]],0)*$AC$9,0)+1 -> 526
A57: 2018 | B57: Joe Mixon | C57: Cin | D57: RB | E57: 0 | F57: 0 | G57: 0 | H57: 0 | I57: 0 | J57: 227 | K57: 892 | L57: 6 | M57: 43 | N57: 353 | O57: 1 | P57: 166.5 | Q57: 118.8 | R57: 47.7 | S57: 2.98125 | U57: 166.5 | V57: =IF(ABS(Proj2018[[#This Row],[LastProj]]-Proj2018[[#This Row],[PROJ TOTAL PTS]])<0.5,"",(Proj2018[[#This Row],[PROJ TOTAL PTS]]-Proj2018[[#This Row],[LastProj]])/16) | W57: K | Y57: =IF(Proj2018[[#This Row],[POS]]="K",-100,Proj2018[[#This Row],[VAR/G]]+1.5) -> 4.48125 | Z57: =ROUND(MAX(Proj2018[[#This Row],[VAWG]],0)*$AC$9,0)+1 -> 515
A58: 2018 | B58: Rob Gronkowski | C58: NE | D58: TE | E58: 0 | F58: 0 | G58: 0 | H58: 0 | I58: 0 | J58: 0 | K58: 0 | L58: 0 | M58: 72 | N58: 1124 | O58: 9 | P58: 166.4 | Q58: 81.6 | R58: 84.8 | S58: 5.3 | U58: 166.4 | V58: =IF(ABS(Proj2018[[#This Row],[LastProj]]-Proj2018[[#This Row],[PROJ TOTAL PTS]])<0.5,"",(Proj2018[[#This Row],[PROJ TOTAL PTS]]-Proj2018[[#This Row],[LastProj]])/16) | W58: K | Y58: =IF(Proj2018[[#This Row],[POS]]="K",-100,Proj2018[[#This Row],[VAR/G]]+1.5) -> 6.8 | Z58: =ROUND(MAX(Proj2018[[#This Row],[VAWG]],0)*$AC$9,0)+1 -> 782
A59: 2018 | B59: Sony Michel | C59: NE | D59: RB | E59: 0 | F59: 0 | G59: 0 | H59: 0 | I59: 0 | J59: 208 | K59: 897 | L59: 8 | M59: 27 | N59: 219 | O59: 1 | P59: 165.6 | Q59: 118.8 | R59: 46.8 | S59: 2.925 | T59: Rookie | U59: 165.6 | V59: =IF(ABS(Proj2018[[#This Row],[LastProj]]-Proj2018[[#This Row],[PROJ TOTAL PTS]])<0.5,"",(Proj2018[[#This Row],[PROJ TOTAL PTS]]-Proj2018[[#This Row],[LastProj]])/16) | W59: K | Y59: =IF(Proj2018[[#This Row],[POS]]="K",-100,Proj2018[[#This Row],[VAR/G]]+1.5) -> 4.425 | Z59: =ROUND(MAX(Proj2018[[#This Row],[VAWG]],0)*$AC$9,0)+1 -> 509
A60: 2018 | B60: Alex Collins | C60: Bal | D60: RB | E60: 0 | F60: 0 | G60: 0 | H60: 0 | I60: 0 | J60: 231 | K60: 988 | L60: 6 | M60: 30 | N60: 235 | O60: 1 | P60: 164.3 | Q60: 118.8 | R60: 45.5 | S60: 2.84375 | U60: 164.3 | V60: =IF(ABS(Proj2018[[#This Row],[LastProj]]-Proj2018[[#This Row],[PROJ TOTAL PTS]])<0.5,"",(Proj2018[[#This Row],[PROJ TOTAL PTS]]-Proj2018[[#This Row],[LastProj]])/16) | W60: K | Y60: =IF(Proj2018[[#This Row],[POS]]="K",-100,Proj2018[[#This Row],[VAR/G]]+1.5) -> 4.34375 | Z60: =ROUND(MAX(Proj2018[[#This Row],[VAWG]],0)*$AC$9,0)+1 -> 500
A61: 2018 | B61: Derrick Henry | C61: Ten | D61: RB | E61: 0 | F61: 0 | G61: 0 | H61: 0 | I61: 0 | J61: 223 | K61: 939 | L61: 7 | M61: 24 | N61: 213 | O61: 1 | P61: 163.2 | Q61: 118.8 | R61: 44.4 | S61: 2.775 | U61: 163.2 | V61: =IF(ABS(Proj2018[[#This Row],[LastProj]]-Proj2018[[#This Row],[PROJ TOTAL PTS]])<0.5,"",(Proj2018[[#This Row],[PROJ TOTAL PTS]]-Proj2018[[#This Row],[LastProj]])/16) | W61: K | Y61: =IF(Proj2018[[#This Row],[POS]]="K",-100,Proj2018[[#This Row],[VAR/G]]+1.5) -> 4.275 | Z61: =ROUND(MAX(Proj2018[[#This Row],[VAWG]],0)*$AC$9,0)+1 -> 492
A62: 2018 | B62: Adam Thielen | C62: Min | D62: WR | E62: 0 | F62: 0 | G62: 0 | H62: 0 | I62: 0 | J62: 2 | K62: 13 | L62: 0 | M62: 85 | N62: 1192 | O62: 7 | P62: 162.5 | Q62: 117.7 | R62: 44.8 | S62: 2.8 | U62: 162.5 | V62: =IF(ABS(Proj2018[[#This Row],[LastProj]]-Proj2018[[#This Row],[PROJ TOTAL PTS]])<0.5,"",(Proj2018[[#This Row],[PROJ TOTAL PTS]]-Proj2018[[#This Row],[LastProj]])/16) | W62: K | Y62: =IF(Proj2018[[#This Row],[POS]]="K",-100,Proj2018[[#This Row],[VAR/G]]+1.5) -> 4.3 | Z62: =ROUND(MAX(Proj2018[[#This Row],[VAWG]],0)*$AC$9,0)+1 -> 495
A63: 2018 | B63: Rashaad Penny | C63: Sea | D63: RB | E63: 0 | F63: 0 | G63: 0 | H63: 0 | I63: 0 | J63: 222 | K63: 948 | L63: 6 | M63: 30 | N63: 247 | O63: 1 | P63: 161.5 | Q63: 118.8 | R63: 42.7 | S63: 2.66875 | T63: Rookie | U63: 161.5 | V63: =IF(ABS(Proj2018[[#This Row],[LastProj]]-Proj2018[[#This Row],[PROJ TOTAL PTS]])<0.5,"",(Proj2018[[#This Row],[PROJ TOTAL PTS]]-Proj2018[[#This Row],[LastProj]])/16) | W63: K | Y63: =IF(Proj2018[[#This Row],[POS]]="K",-100,Proj2018[[#This Row],[VAR/G]]+1.5) -> 4.16875 | Z63: =ROUND(MAX(Proj2018[[#This Row],[VAWG]],0)*$AC$9,0)+1 -> 480
A64: 2018 | B64: Royce Freeman | C64: Den | D64: RB | E64: 0 | F64: 0 | G64: 0 | H64: 0 | I64: 0 | J64: 223 | K64: 942 | L64: 6 | M64: 31 | N64: 247 | O64: 1 | P64: 160.9 | Q64: 118.8 | R64: 42.1 | S64: 2.63125 | T64: Rookie | U64: 160.9 | V64: =IF(ABS(Proj2018[[#This Row],[LastProj]]-Proj2018[[#This Row],[PROJ TOTAL PTS]])<0.5,"",(Proj2018[[#This Row],[PROJ TOTAL PTS]]-Proj2018[[#This Row],[LastProj]])/16) | W64: K | Y64: =IF(Proj2018[[#This Row],[POS]]="K",-100,Proj2018[[#This Row],[VAR/G]]+1.5) -> 4.13125 | Z64: =ROUND(MAX(Proj2018[[#This Row],[VAWG]],0)*$AC$9,0)+1 -> 475
A65: 2018 | B65: Kenyan Drake | C65: Mia | D65: RB | E65: 0 | F65: 0 | G65: 0 | H65: 0 | I65: 0 | J65: 194 | K65: 848 | L65: 6 | M65: 43 | N65: 323 | O65: 1 | P65: 159.1 | Q65: 118.8 | R65: 40.3 | S65: 2.51875 | U65: 159.1 | V65: =IF(ABS(Proj2018[[#This Row],[LastProj]]-Proj2018[[#This Row],[PROJ TOTAL PTS]])<0.5,"",(Proj2018[[#This Row],[PROJ TOTAL PTS]]-Proj2018[[#This Row],[LastProj]])/16) | W65: K | Y65: =IF(Proj2018[[#This Row],[POS]]="K",-100,Proj2018[[#This Row],[VAR/G]]+1.5) -> 4.01875 | Z65: =ROUND(MAX(Proj2018[[#This Row],[VAWG]],0)*$AC$9,0)+1 -> 462
A66: 2018 | B66: Mike Evans | C66: TB | D66: WR | E66: 0 | F66: 0 | G66: 0 | H66: 0 | I66: 0 | J66: 0 | K66: 0 | L66: 0 | M66: 76 | N66: 1058 | O66: 8 | P66: 153.8 | Q66: 117.7 | R66: 36.1 | S66: 2.25625 | U66: 153.8 | V66: =IF(ABS(Proj2018[[#This Row],[LastProj]]-Proj2018[[#This Row],[PROJ TOTAL PTS]])<0.5,"",(Proj2018[[#This Row],[PROJ TOTAL PTS]]-Proj2018[[#This Row],[LastProj]])/16) | W66: K | X66: RFA | Y66: =IF(Proj2018[[#This Row],[POS]]="K",-100,Proj2018[[#This Row],[VAR/G]]+1.5) -> 3.75625 | Z66: =ROUND(MAX(Proj2018[[#This Row],[VAWG]],0)*$AC$9,0)+1 -> 432
A67: 2018 | B67: Ronald Jones II | C67: TB | D67: RB | E67: 0 | F67: 0 | G67: 0 | H67: 0 | I67: 0 | J67: 228 | K67: 956 | L67: 4 | M67: 35 | N67: 279 | O67: 1 | P67: 153.5 | Q67: 118.8 | R67: 34.7 | S67: 2.16875 | T67: Rookie | U67: 153.5 | V67: =IF(ABS(Proj2018[[#This Row],[LastProj]]-Proj2018[[#This Row],[PROJ TOTAL PTS]])<0.5,"",(Proj2018[[#This Row],[PROJ TOTAL PTS]]-Proj2018[[#This Row],[LastProj]])/16) | Y67: =IF(Proj2018[[#This Row],[POS]]="K",-100,Proj2018[[#This Row],[VAR/G]]+1.5) -> 3.66875 | Z67: =ROUND(MAX(Proj2018[[#This Row],[VAWG]],0)*$AC$9,0)+1 -> 422
A68: 2018 | B68: Tyreek Hill | C68: KC | D68: WR | E68: 0 | F68: 0 | G68: 0 | H68: 0 | I68: 0 | J68: 18 | K68: 123 | L68: 1 | M68: 80 | N68: 1034 | O68: 5 | P68: 151.7 | Q68: 117.7 | R68: 34 | S68: 2.125 | U68: 151.7 | V68: =IF(ABS(Proj2018[[#This Row],[LastProj]]-Proj2018[[#This Row],[PROJ TOTAL PTS]])<0.5,"",(Proj2018[[#This Row],[PROJ TOTAL PTS]]-Proj2018[[#This Row],[LastProj]])/16) | W68: K | Y68: =IF(Proj2018[[#This Row],[POS]]="K",-100,Proj2018[[#This Row],[VAR/G]]+1.5) -> 3.625 | Z68: =ROUND(MAX(Proj2018[[#This Row],[VAWG]],0)*$AC$9,0)+1 -> 417
A69: 2018 | B69: Josh Gordon | C69: Cle | D69: WR | E69: 0 | F69: 0 | G69: 0 | H69: 0 | I69: 0 | J69: 2 | K69: 12 | L69: 0 | M69: 69 | N69: 1084 | O69: 7 | P69: 151.6 | Q69: 117.7 | R69: 33.9 | S69: 2.11875 | U69: 151.6 | V69: =IF(ABS(Proj2018[[#This Row],[LastProj]]-Proj2018[[#This Row],[PROJ TOTAL PTS]])<0.5,"",(Proj2018[[#This Row],[PROJ TOTAL PTS]]-Proj2018[[#This Row],[LastProj]])/16) | W69: K | Y69: =IF(Proj2018[[#This Row],[POS]]="K",-100,Proj2018[[#This Row],[VAR/G]]+1.5) -> 3.61875 | Z69: =ROUND(MAX(Proj2018[[#This Row],[VAWG]],0)*$AC$9,0)+1 -> 416
A70: 2018 | B70: Doug Baldwin | C70: Sea | D70: WR | E70: 0 | F70: 0 | G70: 0 | H70: 0 | I70: 0 | J70: 4 | K70: 21 | L70: 0 | M70: 83 | N70: 1067 | O70: 7 | P70: 150.8 | Q70: 117.7 | R70: 33.1 | S70: 2.06875 | U70: 150.8 | V70: =IF(ABS(Proj2018[[#This Row],[LastProj]]-Proj2018[[#This Row],[PROJ TOTAL PTS]])<0.5,"",(Proj2018[[#This Row],[PROJ TOTAL PTS]]-Proj2018[[#This Row],[LastProj]])/16) | W70: K | Y70: =IF(Proj2018[[#This Row],[POS]]="K",-100,Proj2018[[#This Row],[VAR/G]]+1.5) -> 3.56875 | Z70: =ROUND(MAX(Proj2018[[#This Row],[VAWG]],0)*$AC$9,0)+1 -> 411
A71: 2018 | B71: Allen Robinson | C71: Chi | D71: WR | E71: 0 | F71: 0 | G71: 0 | H71: 0 | I71: 0 | J71: 0 | K71: 0 | L71: 0 | M71: 73 | N71: 1048 | O71: 7 | P71: 146.8 | Q71: 117.7 | R71: 29.1 | S71: 1.81875 | U71: 146.8 | V71: =IF(ABS(Proj2018[[#This Row],[LastProj]]-Proj2018[[#This Row],[PROJ TOTAL PTS]])<0.5,"",(Proj2018[[#This Row],[PROJ TOTAL PTS]]-Proj2018[[#This Row],[LastProj]])/16) | W71: K | Y71: =IF(Proj2018[[#This Row],[POS]]="K",-100,Proj2018[[#This Row],[VAR/G]]+1.5) -> 3.31875 | Z71: =ROUND(MAX(Proj2018[[#This Row],[VAWG]],0)*$AC$9,0)+1 -> 382
A72: 2018 | B72: Jay Ajayi | C72: Phi | D72: RB | E72: 0 | F72: 0 | G72: 0 | H72: 0 | I72: 0 | J72: 220 | K72: 939 | L72: 5 | M72: 21 | N72: 164 | O72: 1 | P72: 146.3 | Q72: 118.8 | R72: 27.5 | S72: 1.71875 | U72: 146.3 | V72: =IF(ABS(Proj2018[[#This Row],[LastProj]]-Proj2018[[#This Row],[PROJ TOTAL PTS]])<0.5,"",(Proj2018[[#This Row],[PROJ TOTAL PTS]]-Proj2018[[#This Row],[LastProj]])/16) | Y72: =IF(Proj2018[[#This Row],[POS]]="K",-100,Proj2018[[#This Row],[VAR/G]]+1.5) -> 3.21875 | Z72: =ROUND(MAX(Proj2018[[#This Row],[VAWG]],0)*$AC$9,0)+1 -> 370
A73: 2018 | B73: Stefon Diggs | C73: Min | D73: WR | E73: 0 | F73: 0 | G73: 0 | H73: 0 | I73: 0 | J73: 8 | K73: 47 | L73: 0 | M73: 82 | N73: 1045 | O73: 6 | P73: 145.2 | Q73: 117.7 | R73: 27.5 | S73: 1.71875 | U73: 145.2 | V73: =IF(ABS(Proj2018[[#This Row],[LastProj]]-Proj2018[[#This Row],[PROJ TOTAL PTS]])<0.5,"",(Proj2018[[#This Row],[PROJ TOTAL PTS]]-Proj2018[[#This Row],[LastProj]])/16) | W73: K | Y73: =IF(Proj2018[[#This Row],[POS]]="K",-100,Proj2018[[#This Row],[VAR/G]]+1.5) -> 3.21875 | Z73: =ROUND(MAX(Proj2018[[#This Row],[VAWG]],0)*$AC$9,0)+1 -> 370
A74: 2018 | B74: Alshon Jeffery | C74: Phi | D74: WR | E74: 0 | F74: 0 | G74: 0 | H74: 0 | I74: 0 | J74: 0 | K74: 0 | L74: 0 | M74: 66 | N74: 971 | O74: 8 | P74: 145.1 | Q74: 117.7 | R74: 27.4 | S74: 1.7125 | U74: 145.1 | V74: =IF(ABS(Proj2018[[#This Row],[LastProj]]-Proj2018[[#This Row],[PROJ TOTAL PTS]])<0.5,"",(Proj2018[[#This Row],[PROJ TOTAL PTS]]-Proj2018[[#This Row],[LastProj]])/16) | W74: K | Y74: =IF(Proj2018[[#This Row],[POS]]="K",-100,Proj2018[[#This Row],[VAR/G]]+1.5) -> 3.2125 | Z74: =ROUND(MAX(Proj2018[[#This Row],[VAWG]],0)*$AC$9,0)+1 -> 370
A75: 2018 | B75: Demaryius Thomas | C75: Den | D75: WR | E75: 0 | F75: 0 | G75: 0 | H75: 0 | I75: 0 | J75: 0 | K75: 0 | L75: 0 | M75: 91 | N75: 1064 | O75: 6 | P75: 142.4 | Q75: 117.7 | R75: 24.7 | S75: 1.54375 | U75: 142.4 | V75: =IF(ABS(Proj2018[[#This Row],[LastProj]]-Proj2018[[#This Row],[PROJ TOTAL PTS]])<0.5,"",(Proj2018[[#This Row],[PROJ TOTAL PTS]]-Proj2018[[#This Row],[LastProj]])/16) | W75: K | Y75: =IF(Proj2018[[#This Row],[POS]]="K",-100,Proj2018[[#This Row],[VAR/G]]+1.5) -> 3.04375 | Z75: =ROUND(MAX(Proj2018[[#This Row],[VAWG]],0)*$AC$9,0)+1 -> 350
A76: 2018 | B76: Amari Cooper | C76: Oak | D76: WR | E76: 0 | F76: 0 | G76: 0 | H76: 0 | I76: 0 | J76: 2 | K76: 12 | L76: 0 | M76: 76 | N76: 1007 | O76: 6 | P76: 137.9 | Q76: 117.7 | R76: 20.2 | S76: 1.2625 | U76: 137.9 | V76: =IF(ABS(Proj2018[[#This Row],[LastProj]]-Proj2018[[#This Row],[PROJ TOTAL PTS]])<0.5,"",(Proj2018[[#This Row],[PROJ TOTAL PTS]]-Proj2018[[#This Row],[LastProj]])/16) | W76: K | Y76: =IF(Proj2018[[#This Row],[POS]]="K",-100,Proj2018[[#This Row],[VAR/G]]+1.5) -> 2.7625 | Z76: =ROUND(MAX(Proj2018[[#This Row],[VAWG]],0)*$AC$9,0)+1 -> 318
A77: 2018 | B77: Mark Ingram II | C77: NO | D77: RB | E77: 0 | F77: 0 | G77: 0 | H77: 0 | I77: 0 | J77: 153 | K77: 696 | L77: 6 | M77: 36 | N77: 261 | O77: 1 | P77: 137.7 | Q77: 118.8 | R77: 18.9 | S77: 1.18125 | U77: 137.7 | V77: =IF(ABS(Proj2018[[#This Row],[LastProj]]-Proj2018[[#This Row],[PROJ TOTAL PTS]])<0.5,"",(Proj2018[[#This Row],[PROJ TOTAL PTS]]-Proj2018[[#This Row],[LastProj]])/16) | W77: K | Y77: =IF(Proj2018[[#This Row],[POS]]="K",-100,Proj2018[[#This Row],[VAR/G]]+1.5) -> 2.68125 | Z77: =ROUND(MAX(Proj2018[[#This Row],[VAWG]],0)*$AC$9,0)+1 -> 309
A78: 2018 | B78: Travis Kelce | C78: KC | D78: TE | E78: 0 | F78: 0 | G78: 0 | H78: 0 | I78: 0 | J78: 2 | K78: 7 | L78: 0 | M78: 81 | N78: 1006 | O78: 6 | P78: 137.3 | Q78: 81.6 | R78: 55.7 | S78: 3.48125 | U78: 137.3 | V78: =IF(ABS(Proj2018[[#This Row],[LastProj]]-Proj2018[[#This Row],[PROJ TOTAL PTS]])<0.5,"",(Proj2018[[#This Row],[PROJ TOTAL PTS]]-Proj2018[[#This Row],[LastProj]])/16) | W78: K | Y78: =IF(Proj2018[[#This Row],[POS]]="K",-100,Proj2018[[#This Row],[VAR/G]]+1.5) -> 4.98125 | Z78: =ROUND(MAX(Proj2018[[#This Row],[VAWG]],0)*$AC$9,0)+1 -> 573
A79: 2018 | B79: Chris Hogan | C79: NE | D79: WR | E79: 0 | F79: 0 | G79: 0 | H79: 0 | I79: 0 | J79: 5 | K79: 32 | L79: 0 | M79: 61 | N79: 910 | O79: 7 | P79: 136.2 | Q79: 117.7 | R79: 18.5 | S79: 1.15625 | U79: 136.2 | V79: =IF(ABS(Proj2018[[#This Row],[LastProj]]-Proj2018[[#This Row],[PROJ TOTAL PTS]])<0.5,"",(Proj2018[[#This Row],[PROJ TOTAL PTS]]-Proj2018[[#This Row],[LastProj]])/16) | W79: K | Y79: =IF(Proj2018[[#This Row],[POS]]="K",-100,Proj2018[[#This Row],[VAR/G]]+1.5) -> 2.65625 | Z79: =ROUND(MAX(Proj2018[[#This Row],[VAWG]],0)*$AC$9,0)+1 -> 306
A80: 2018 | B80: JuJu Smith-Schuster | C80: Pit | D80: WR | E80: 0 | F80: 0 | G80: 0 | H80: 0 | I80: 0 | J80: 0 | K80: 0 | L80: 0 | M80: 76 | N80: 996 | O80: 6 | P80: 135.6 | Q80: 117.7 | R80: 17.9 | S80: 1.11875 | U80: 135.6 | V80: =IF(ABS(Proj2018[[#This Row],[LastProj]]-Proj2018[[#This Row],[PROJ TOTAL PTS]])<0.5,"",(Proj2018[[#This Row],[PROJ TOTAL PTS]]-Proj2018[[#This Row],[LastProj]])/16) | W80: K | Y80: =IF(Proj2018[[#This Row],[POS]]="K",-100,Proj2018[[#This Row],[VAR/G]]+1.5) -> 2.61875 | Z80: =ROUND(MAX(Proj2018[[#This Row],[VAWG]],0)*$AC$9,0)+1 -> 302
A81: 2018 | B81: Marvin Jones Jr. | C81: Det | D81: WR | E81: 0 | F81: 0 | G81: 0 | H81: 0 | I81: 0 | J81: 0 | K81: 0 | L81: 0 | M81: 59 | N81: 935 | O81: 7 | P81: 135.5 | Q81: 117.7 | R81: 17.8 | S81: 1.1125 | U81: 135.5 | V81: =IF(ABS(Proj2018[[#This Row],[LastProj]]-Proj2018[[#This Row],[PROJ TOTAL PTS]])<0.5,"",(Proj2018[[#This Row],[PROJ TOTAL PTS]]-Proj2018[[#This Row],[LastProj]])/16) | W81: K | Y81: =IF(Proj2018[[#This Row],[POS]]="K",-100,Proj2018[[#This Row],[VAR/G]]+1.5) -> 2.6125 | Z81: =ROUND(MAX(Proj2018[[#This Row],[VAWG]],0)*$AC$9,0)+1 -> 301
A82: 2018 | B82: Larry Fitzgerald | C82: Ari | D82: WR | E82: 0 | F82: 0 | G82: 0 | H82: 0 | I82: 0 | J82: 0 | K82: 0 | L82: 0 | M82: 105 | N82: 1054 | O82: 5 | P82: 135.4 | Q82: 117.7 | R82: 17.7 | S82: 1.10625 | U82: 135.4 | V82: =IF(ABS(Proj2018[[#This Row],[LastProj]]-Proj2018[[#This Row],[PROJ TOTAL PTS]])<0.5,"",(Proj2018[[#This Row],[PROJ TOTAL PTS]]-Proj2018[[#This Row],[LastProj]])/16) | W82: K | Y82: =IF(Proj2018[[#This Row],[POS]]="K",-100,Proj2018[[#This Row],[VAR/G]]+1.5) -> 2.60625 | Z82: =ROUND(MAX(Proj2018[[#This Row],[VAWG]],0)*$AC$9,0)+1 -> 300
A83: 2018 | B83: AJ McCarron | C83: Buf | D83: QB | E83: 207 | F83: 340 | G83: 2247 | H83: 10 | I83: 7 | J83: 28 | K83: 112 | L83: 1 | M83: 0 | N83: 0 | O83: 0 | P83: 133.08 | Q83: 278.68 | R83: -145.6 | S83: -9.1 | U83: 133.08 | V83: =IF(ABS(Proj2018[[#This Row],[LastProj]]-Proj2018[[#This Row],[PROJ TOTAL PTS]])<0.5,"",(Proj2018[[#This Row],[PROJ TOTAL PTS]]-Proj2018[[#This Row],[LastProj]])/16) | Y83: =IF(Proj2018[[#This Row],[POS]]="K",-100,Proj2018[[#This Row],[VAR/G]]+1.5) -> -7.6 | Z83: =ROUND(MAX(Proj2018[[#This Row],[VAWG]],0)*$AC$9,0)+1 -> 1
A84: 2018 | B84: Marlon Mack | C84: Ind | D84: RB | E84: 0 | F84: 0 | G84: 0 | H84: 0 | I84: 0 | J84: 174 | K84: 699 | L84: 5 | M84: 31 | N84: 270 | O84: 1 | P84: 132.9 | Q84: 118.8 | R84: 14.1 | S84: 0.88125 | U84: 132.9 | V84: =IF(ABS(Proj2018[[#This Row],[LastProj]]-Proj2018[[#This Row],[PROJ TOTAL PTS]])<0.5,"",(Proj2018[[#This Row],[PROJ TOTAL PTS]]-Proj2018[[#This Row],[LastProj]])/16) | W84: K | Y84: =IF(Proj2018[[#This Row],[POS]]="K",-100,Proj2018[[#This Row],[VAR/G]]+1.5) -> 2.38125 | Z84: =ROUND(MAX(Proj2018[[#This Row],[VAWG]],0)*$AC$9,0)+1 -> 274
A85: 2018 | B85: Dion Lewis | C85: Ten | D85: RB | E85: 0 | F85: 0 | G85: 0 | H85: 0 | I85: 0 | J85: 132 | K85: 574 | L85: 4 | M85: 46 | N85: 372 | O85: 2 | P85: 130.6 | Q85: 118.8 | R85: 11.8 | S85: 0.7375 | U85: 130.6 | V85: =IF(ABS(Proj2018[[#This Row],[LastProj]]-Proj2018[[#This Row],[PROJ TOTAL PTS]])<0.5,"",(Proj2018[[#This Row],[PROJ TOTAL PTS]]-Proj2018[[#This Row],[LastProj]])/16) | W85: K | Y85: =IF(Proj2018[[#This Row],[POS]]="K",-100,Proj2018[[#This Row],[VAR/G]]+1.5) -> 2.2375 | Z85: =ROUND(MAX(Proj2018[[#This Row],[VAWG]],0)*$AC$9,0)+1 -> 258
A86: 2018 | B86: Zach Ertz | C86: Phi | D86: TE | E86: 0 | F86: 0 | G86: 0 | H86: 0 | I86: 0 | J86: 0 | K86: 0 | L86: 0 | M86: 82 | N86: 884 | O86: 7 | P86: 130.4 | Q86: 81.6 | R86: 48.8 | S86: 3.05 | U86: 130.4 | V86: =IF(ABS(Proj2018[[#This Row],[LastProj]]-Proj2018[[#This Row],[PROJ TOTAL PTS]])<0.5,"",(Proj2018[[#This Row],[PROJ TOTAL PTS]]-Proj2018[[#This Row],[LastProj]])/16) | W86: K | Y86: =IF(Proj2018[[#This Row],[POS]]="K",-100,Proj2018[[#This Row],[VAR/G]]+1.5) -> 4.55 | Z86: =ROUND(MAX(Proj2018[[#This Row],[VAWG]],0)*$AC$9,0)+1 -> 523
A87: 2018 | B87: Tevin Coleman | C87: Atl | D87: RB | E87: 0 | F87: 0 | G87: 0 | H87: 0 | I87: 0 | J87: 142 | K87: 590 | L87: 4 | M87: 36 | N87: 342 | O87: 2 | P87: 129.2 | Q87: 118.8 | R87: 10.4 | S87: 0.65 | U87: 129.2 | V87: =IF(ABS(Proj2018[[#This Row],[LastProj]]-Proj2018[[#This Row],[PROJ TOTAL PTS]])<0.5,"",(Proj2018[[#This Row],[PROJ TOTAL PTS]]-Proj2018[[#This Row],[LastProj]])/16) | W87: K | Y87: =IF(Proj2018[[#This Row],[POS]]="K",-100,Proj2018[[#This Row],[VAR/G]]+1.5) -> 2.15 | Z87: =ROUND(MAX(Proj2018[[#This Row],[VAWG]],0)*$AC$9,0)+1 -> 248
A88: 2018 | B88: Greg Olsen | C88: Car | D88: TE | E88: 0 | F88: 0 | G88: 0 | H88: 0 | I88: 0 | J88: 0 | K88: 0 | L88: 0 | M88: 69 | N88: 914 | O88: 6 | P88: 127.4 | Q88: 81.6 | R88: 45.8 | S88: 2.8625 | U88: 127.4 | V88: =IF(ABS(Proj2018[[#This Row],[LastProj]]-Proj2018[[#This Row],[PROJ TOTAL PTS]])<0.5,"",(Proj2018[[#This Row],[PROJ TOTAL PTS]]-Proj2018[[#This Row],[LastProj]])/16) | W88: K | Y88: =IF(Proj2018[[#This Row],[POS]]="K",-100,Proj2018[[#This Row],[VAR/G]]+1.5) -> 4.3625 | Z88: =ROUND(MAX(Proj2018[[#This Row],[VAWG]],0)*$AC$9,0)+1 -> 502
A89: 2018 | B89: Golden Tate | C89: Det | D89: WR | E89: 0 | F89: 0 | G89: 0 | H89: 0 | I89: 0 | J89: 5 | K89: 28 | L89: 0 | M89: 89 | N89: 990 | O89: 4 | P89: 125.8 | Q89: 117.7 | R89: 8.1 | S89: 0.50625 | U89: 125.8 | V89: =IF(ABS(Proj2018[[#This Row],[LastProj]]-Proj2018[[#This Row],[PROJ TOTAL PTS]])<0.5,"",(Proj2018[[#This Row],[PROJ TOTAL PTS]]-Proj2018[[#This Row],[LastProj]])/16) | W89: K | Y89: =IF(Proj2018[[#This Row],[POS]]="K",-100,Proj2018[[#This Row],[VAR/G]]+1.5) -> 2.00625 | Z89: =ROUND(MAX(Proj2018[[#This Row],[VAWG]],0)*$AC$9,0)+1 -> 231
A90: 2018 | B90: Josh McCown | C90: NYJ | D90: QB | E90: 186 | F90: 302 | G90: 2142 | H90: 10 | I90: 8 | J90: 23 | K90: 101 | L90: 1 | M90: 0 | N90: 0 | O90: 0 | P90: 125.78 | Q90: 278.68 | R90: -152.9 | S90: -9.55625 | U90: 125.78 | V90: =IF(ABS(Proj2018[[#This Row],[LastProj]]-Proj2018[[#This Row],[PROJ TOTAL PTS]])<0.5,"",(Proj2018[[#This Row],[PROJ TOTAL PTS]]-Proj2018[[#This Row],[LastProj]])/16) | Y90: =IF(Proj2018[[#This Row],[POS]]="K",-100,Proj2018[[#This Row],[VAR/G]]+1.5) -> -8.05625 | Z90: =ROUND(MAX(Proj2018[[#This Row],[VAWG]],0)*$AC$9,0)+1 -> 1
A91: 2018 | B91: Sammy Watkins | C91: KC | D91: WR | E91: 0 | F91: 0 | G91: 0 | H91: 0 | I91: 0 | J91: 0 | K91: 0 | L91: 0 | M91: 60 | N91: 952 | O91: 5 | P91: 125.2 | Q91: 117.7 | R91: 7.5 | S91: 0.46875 | U91: 125.2 | V91: =IF(ABS(Proj2018[[#This Row],[LastProj]]-Proj2018[[#This Row],[PROJ TOTAL PTS]])<0.5,"",(Proj2018[[#This Row],[PROJ TOTAL PTS]]-Proj2018[[#This Row],[LastProj]])/16) | W91: K | Y91: =IF(Proj2018[[#This Row],[POS]]="K",-100,Proj2018[[#This Row],[VAR/G]]+1.5) -> 1.96875 | Z91: =ROUND(MAX(Proj2018[[#This Row],[VAWG]],0)*$AC$9,0)+1 -> 227
A92: 2018 | B92: Emmanuel Sanders | C92: Den | D92: WR | E92: 0 | F92: 0 | G92: 0 | H92: 0 | I92: 0 | J92: 0 | K92: 0 | L92: 0 | M92: 73 | N92: 950 | O92: 5 | P92: 125 | Q92: 117.7 | R92: 7.3 | S92: 0.45625 | U92: 125 | V92: =IF(ABS(Proj2018[[#This Row],[LastProj]]-Proj2018[[#This Row],[PROJ TOTAL PTS]])<0.5,"",(Proj2018[[#This Row],[PROJ TOTAL PTS]]-Proj2018[[#This Row],[LastProj]])/16) | W92: K | Y92: =IF(Proj2018[[#This Row],[POS]]="K",-100,Proj2018[[#This Row],[VAR/G]]+1.5) -> 1.95625 | Z92: =ROUND(MAX(Proj2018[[#This Row],[VAWG]],0)*$AC$9,0)+1 -> 226
A93: 2018 | B93: Brandin Cooks | C93: LAR | D93: WR | E93: 0 | F93: 0 | G93: 0 | H93: 0 | I93: 0 | J93: 8 | K93: 47 | L93: 0 | M93: 61 | N93: 901 | O93: 5 | P93: 124.8 | Q93: 117.7 | R93: 7.1 | S93: 0.44375 | U93: 124.8 | V93: =IF(ABS(Proj2018[[#This Row],[LastProj]]-Proj2018[[#This Row],[PROJ TOTAL PTS]])<0.5,"",(Proj2018[[#This Row],[PROJ TOTAL PTS]]-Proj2018[[#This Row],[LastProj]])/16) | W93: K | X93: RFA | Y93: =IF(Proj2018[[#This Row],[POS]]="K",-100,Proj2018[[#This Row],[VAR/G]]+1.5) -> 1.94375 | Z93: =ROUND(MAX(Proj2018[[#This Row],[VAWG]],0)*$AC$9,0)+1 -> 224
A94: 2018 | B94: Devin Funchess | C94: Car | D94: WR | E94: 0 | F94: 0 | G94: 0 | H94: 0 | I94: 0 | J94: 0 | K94: 0 | L94: 0 | M94: 61 | N94: 884 | O94: 6 | P94: 124.4 | Q94: 117.7 | R94: 6.7 | S94: 0.41875 | U94: 124.4 | V94: =IF(ABS(Proj2018[[#This Row],[LastProj]]-Proj2018[[#This Row],[PROJ TOTAL PTS]])<0.5,"",(Proj2018[[#This Row],[PROJ TOTAL PTS]]-Proj2018[[#This Row],[LastProj]])/16) | W94: K | Y94: =IF(Proj2018[[#This Row],[POS]]="K",-100,Proj2018[[#This Row],[VAR/G]]+1.5) -> 1.91875 | Z94: =ROUND(MAX(Proj2018[[#This Row],[VAWG]],0)*$AC$9,0)+1 -> 221
A95: 2018 | B95: Lamar Miller | C95: Hou | D95: RB | E95: 0 | F95: 0 | G95: 0 | H95: 0 | I95: 0 | J95: 186 | K95: 722 | L95: 4 | M95: 28 | N95: 220 | O95: 1 | P95: 124.2 | Q95: 118.8 | R95: 5.4 | S95: 0.3375 | U95: 124.2 | V95: =IF(ABS(Proj2018[[#This Row],[LastProj]]-Proj2018[[#This Row],[PROJ TOTAL PTS]])<0.5,"",(Proj2018[[#This Row],[PROJ TOTAL PTS]]-Proj2018[[#This Row],[LastProj]])/16) | W95: K | X95: RFA | Y95: =IF(Proj2018[[#This Row],[POS]]="K",-100,Proj2018[[#This Row],[VAR/G]]+1.5) -> 1.8375 | Z95: =ROUND(MAX(Proj2018[[#This Row],[VAWG]],0)*$AC$9,0)+1 -> 212
A96: 2018 | B96: Delanie Walker | C96: Ten | D96: TE | E96: 0 | F96: 0 | G96: 0 | H96: 0 | I96: 0 | J96: 0 | K96: 0 | L96: 0 | M96: 71 | N96: 820 | O96: 7 | P96: 124 | Q96: 81.6 | R96: 42.4 | S96: 2.65 | U96: 124 | V96: =IF(ABS(Proj2018[[#This Row],[LastProj]]-Proj2018[[#This Row],[PROJ TOTAL PTS]])<0.5,"",(Proj2018[[#This Row],[PROJ TOTAL PTS]]-Proj2018[[#This Row],[LastProj]])/16) | Y96: =IF(Proj2018[[#This Row],[POS]]="K",-100,Proj2018[[#This Row],[VAR/G]]+1.5) -> 4.15 | Z96: =ROUND(MAX(Proj2018[[#This Row],[VAWG]],0)*$AC$9,0)+1 -> 477
A97: 2018 | B97: Sam Bradford | C97: Ari | D97: QB | E97: 195 | F97: 302 | G97: 2104 | H97: 11 | I97: 4 | J97: 14 | K97: 32 | L97: 0 | M97: 0 | N97: 0 | O97: 0 | P97: 123.36 | Q97: 278.68 | R97: -155.32 | S97: -9.7075 | U97: 123.36 | V97: =IF(ABS(Proj2018[[#This Row],[LastProj]]-Proj2018[[#This Row],[PROJ TOTAL PTS]])<0.5,"",(Proj2018[[#This Row],[PROJ TOTAL PTS]]-Proj2018[[#This Row],[LastProj]])/16) | Y97: =IF(Proj2018[[#This Row],[POS]]="K",-100,Proj2018[[#This Row],[VAR/G]]+1.5) -> -8.2075 | Z97: =ROUND(MAX(Proj2018[[#This Row],[VAWG]],0)*$AC$9,0)+1 -> 1
A98: 2018 | B98: Pierre Garcon | C98: SF | D98: WR | E98: 0 | F98: 0 | G98: 0 | H98: 0 | I98: 0 | J98: 0 | K98: 0 | L98: 0 | M98: 76 | N98: 980 | O98: 4 | P98: 122 | Q98: 117.7 | R98: 4.3 | S98: 0.26875 | U98: 122 | V98: =IF(ABS(Proj2018[[#This Row],[LastProj]]-Proj2018[[#This Row],[PROJ TOTAL PTS]])<0.5,"",(Proj2018[[#This Row],[PROJ TOTAL PTS]]-Proj2018[[#This Row],[LastProj]])/16) | W98: K | Y98: =IF(Proj2018[[#This Row],[POS]]="K",-100,Proj2018[[#This Row],[VAR/G]]+1.5) -> 1.76875 | Z98: =ROUND(MAX(Proj2018[[#This Row],[VAWG]],0)*$AC$9,0)+1 -> 204
A99: 2018 | B99: Jarvis Landry | C99: Cle | D99: WR | E99: 0 | F99: 0 | G99: 0 | H99: 0 | I99: 0 | J99: 2 | K99: 10 | L99: 0 | M99: 90 | N99: 897 | O99: 5 | P99: 120.7 | Q99: 117.7 | R99: 3 | S99: 0.1875 | U99: 120.7 | V99: =IF(ABS(Proj2018[[#This Row],[LastProj]]-Proj2018[[#This Row],[PROJ TOTAL PTS]])<0.5,"",(Proj2018[[#This Row],[PROJ TOTAL PTS]]-Proj2018[[#This Row],[LastProj]])/16) | W99: K | Y99: =IF(Proj2018[[#This Row],[POS]]="K",-100,Proj2018[[#This Row],[VAR/G]]+1.5) -> 1.6875 | Z99: =ROUND(MAX(Proj2018[[#This Row],[VAWG]],0)*$AC$9,0)+1 -> 195
A100: 2018 | B100: Corey Davis | C100: Ten | D100: WR | E100: 0 | F100: 0 | G100: 0 | H100: 0 | I100: 0 | J100: 0 | K100: 0 | L100: 0 | M100: 68 | N100: 847 | O100: 6 | P100: 120.7 | Q100: 117.7 | R100: 3 | S100: 0.1875 | U100: 120.7 | V100: =IF(ABS(Proj2018[[#This Row],[LastProj]]-Proj2018[[#This Row],[PROJ TOTAL PTS]])<0.5,"",(Proj2018[[#This Row],[PROJ TOTAL PTS]]-Proj2018[[#This Row],[LastProj]])/16) | W100: K | Y100: =IF(Proj2018[[#This Row],[POS]]="K",-100,Proj2018[[#This Row],[VAR/G]]+1.5) -> 1.6875 | Z100: =ROUND(MAX(Proj2018[[#This Row],[VAWG]],0)*$AC$9,0)+1 -> 195
A101: 2018 | B101: Cooper Kupp | C101: LAR | D101: WR | E101: 0 | F101: 0 | G101: 0 | H101: 0 | I101: 0 | J101: 0 | K101: 0 | L101: 0 | M101: 67 | N101: 847 | O101: 6 | P101: 120.7 | Q101: 117.7 | R101: 3 | S101: 0.1875 | U101: 120.7 | V101: =IF(ABS(Proj2018[[#This Row],[LastProj]]-Proj2018[[#This Row],[PROJ TOTAL PTS]])<0.5,"",(Proj2018[[#This Row],[PROJ TOTAL PTS]]-Proj2018[[#This Row],[LastProj]])/16) | W101: K | Y101: =IF(Proj2018[[#This Row],[POS]]="K",-100,Proj2018[[#This Row],[VAR/G]]+1.5) -> 1.6875 | Z101: =ROUND(MAX(Proj2018[[#This Row],[VAWG]],0)*$AC$9,0)+1 -> 195
...

Sheet ESPNTeams
A1: Team ID | B1: Team | C1: Owner
A2: 4 | B2: R E L A X | C2: Sean Christopherson
A3: 5 | B3: House of Romanov | C3: David Tabachnick
A4: 6 | B4: Scrote Squad | C4: Jonny Max
A5: 7 | B5: Baldrick's Cunning Plan | C5: Gregory Germano
A6: 10 | B6: Strange Brew | C6: Josh Hellstrom
A7: 1 | B7: The Meme Team | C7: Adam Pranger
A8: 9 | B8: GawdDamn Trash Pandas | C8: Joe Nienalt
A9: 3 | B9: Nino and The Twerks | C9: David Opp
A10: 2 | B10: We Are All Doomed! | C10: Robert Noradki
A11: 8 | B11: Read Option Illiteracy | C11: SKYE BURLINGAME

Sheet Owners
A1: user_id | B1: team_name | C1: league_id | D1: display_name
A2: 78938523440660480 | B2: Baldrick's Cunning Plan | C2: 1313750925990465536 | D2: gregdg82
A3: 297161941346963456 | B3: The Replacements | C3: 1313750925990465536 | D3: GentlemanBrewer
A4: 342475185162694656 | B4: BILL BILL BILL BILL BILL | C4: 1313750925990465536 | D4: hellj85
A5: 342745172225974272 | C5: 1313750925990465536 | D5: demboys26
A6: 342747602523004928 | B6: Love Machines | C6: 1313750925990465536 | D6: BobbyBaby
A7: 342909084795711488 | B7: Los Pollos Hermanos | C7: 1313750925990465536 | D7: joe9alt
A8: 410283082055172096 | B8: Gettin Some Strange | C8: 1313750925990465536 | D8: Jonnymaxed
A9: 413095484094160896 | B9: Damar's Revenge | C9: 1313750925990465536 | D9: zombull
A10: 452206609343442944 | C10: 1313750925990465536 | D10: docopp
A11: 454379832487178240 | B11: Tin Plate Dengerate | C11: 1313750925990465536 | D11: cthultu
A12: 563130086871535616 | C12: 1313750925990465536 | D12: mcmahanwich

Sheet Full Roster
A1: player_id | B1: OWNER | C1: PLAYER | D1: RosterIndex | E1: DraftIndex | F1: TEAM | G1: POS | H1: SOURCE | I1: $ PREV | J1: Contract | K1: Contract Year | L1: RFA Eligible? | M1: FFA Year | N1: $↑ VAR | O1: $ CURR | P1: VAR/G | Q1: GoodVARG | R1: ManualVARG | S1: KEEPER / RFA | T1: Net Keeper Count | U1: RFA $ | V1: Optimal $ | W1: Opt Value | X1: VAW/G | Y1: VAWG Market $ | Z1: VAWG Value | AA1: Pure Inflated $ | AB1: Inflated Value | AC1: Age | AE1: FA Draft $ | AF1: OWNER | AG1: Keeper $ | AH1: Keeper + RFA | AI1: Roster Size | AJ1: Keepers # | AK1: RFA # | AL1: Penalty | AM1: Min Salary | AN1: VARG (K) | AO1: VARG (RFA) | AP1: VARG (non K) | AQ1: $ to VARG | AR1: Total VARG | AS1: Value
A2: 11603 | B2: BobbyBaby | C2: AJ Barner | D2: =_xlfn.IFNA(MATCH(RosterPlan25[[#This Row],[player_id]],CompositeRoster[sleeper_id],0), MATCH(RosterPlan25[[#This Row],[PLAYER]],CompositeRoster[full_name],0)) -> 1 | E2: =MATCH(RosterPlan25[[#This Row],[player_id]],Draft2025[sleeper_id],0) -> #N/A | F2: =INDEX(CompositeRoster[team],RosterPlan25[[#This Row],[RosterIndex]])&"" -> SEA | G2: =INDEX(CompositeRoster[position],RosterPlan25[[#This Row],[RosterIndex]])&"" -> TE | H2: =INDEX(CompositeRoster[source],RosterPlan25[[#This Row],[RosterIndex]]) -> Roster | I2: =_xlfn.IFNA(INDEX(Draft2025[PRICE],RosterPlan25[[#This Row],[DraftIndex]]),0) -> 0 | J2: =IF(RosterPlan25[[#This Row],[SOURCE]]="Rookie","Rookie",_xlfn.IFNA(INDEX(Draft2025[Current Contract],RosterPlan25[[#This Row],[DraftIndex]]),"Undrafted")) -> Undrafted | K2: {=IF(OR(ISBLANK(RosterPlan25[[#This Row],[player_id]]),NOT(ISNA(MATCH(RosterPlan25[[#This Row],[player_id]],INDIRECT("Rookies" & SEASON &"[player_id]"),0)))), SEASON, _xlfn.IFNA(INDEX(Draft2025[Contract Year],RosterPlan25[[#This Row],[DraftIndex]]),IF(IN_SEASON,SEASON,SEASON-1)))} -> 2025 | L2: =IF(_xlfn.IFNA(INDEX(Draft2025[KEEPER],RosterPlan25[[#This Row],[DraftIndex]]),"")="K","Yes","") | M2: {=IF(RosterPlan25[[#This Row],[Contract]]="Rookie", "", IF(_xlfn.IFNA(INDEX(Draft2025[Contract Year],RosterPlan25[[#This Row],[DraftIndex]]),IF(IN_SEASON,SEASON,SEASON-1))+3<SEASON, SEASON, _xlfn.IFNA(INDEX(Draft2025[Contract Year],RosterPlan25[[#This Row],[DraftIndex]]),IF(IN_SEASON,SEASON,SEASON-1))+3))} -> 2028 | N2: =ROUNDDOWN(RosterPlan25[[#This Row],[Optimal $]]*IF(RosterPlan25[[#This Row],[Contract]]="Rookie",0.3,0.15),0) -> 0 | O2: =IF(RosterPlan25[[#This Row],[SOURCE]]="Rookie", INDEX(INDIRECT("Rookies" & SEASON & "[salary]"),MATCH(RosterPlan25[[#This Row],[PLAYER]],INDIRECT("Rookies"& SEASON & "[full_name]"),0)), MAX(RosterPlan25[[#This Row],[$ PREV]] + IF(RAISES_ENABLED,RosterPlan25[[#This Row],[$↑ VAR]],0),1)) -> 1 | P2: =IF(VARG="MANUAL",RosterPlan25[[#This Row],[ManualVARG]],IF(VARG="GOOD",RosterPlan25[[#This Row],[GoodVARG]],"ERR")) -> -1.4633912 | Q2: =_xlfn.IFNA(IF(RosterPlan25[[#This Row],[POS]]="K",0,INDEX(GoodSheets[MG VARG],MATCH(TEXT(RosterPlan25[[#This Row],[player_id]],"0"),GoodSheets[sleeper_id],0))), IF(RosterPlan25[[#This Row],[POS]]="QB",-12,IF(RosterPlan25[[#This Row],[POS]]="RB",-8,IF(RosterPlan25[[#This Row],[POS]]="WR",-8,-5)))) -> -1.4633912 | R2: =_xlfn.IFNA(INDEX(ALL_Athletic[VARG], MATCH(RosterPlan25[[#This Row],[player_id]],ALL_Athletic[SleeperID],0)), IF(RosterPlan25[[#This Row],[POS]]="QB",-12,IF(RosterPlan25[[#This Row],[POS]]="RB",-8,IF(RosterPlan25[[#This Row],[POS]]="WR",-8,-5)))) -> -5 | S2: K | T2: =_xlfn.IFNA(INDEX(Draft2025[Net Keeper Count],RosterPlan25[[#This Row],[DraftIndex]]),0)+IF(RosterPlan25[[#This Row],[KEEPER / RFA]]="K",1,0) -> 1 | U2: =IF(RosterPlan25[[#This Row],[KEEPER / RFA]]="RFA",RosterPlan25[[#This Row],[Pure Inflated $]],"") | V2: =IF(RosterPlan25[[#This Row],[VAR/G]]>0, ROUND(IF(VARG="GOOD",$AG$29,IF(VARG="ATHLETIC",$AH$29,99999999999))*RosterPlan25[[#This Row],[VAR/G]],0), 0) + 1 -> 1 | W2: =RosterPlan25[[#This Row],[Optimal $]]-RosterPlan25[[#This Row],[$ CURR]] -> 0 | X2: =IF(OR(RosterPlan25[[#This Row],[SOURCE]]="Rookie",RosterPlan25[[#This Row],[POS]]="K"),0,RosterPlan25[[#This Row],[VAR/G]]+3.3) -> 1.8366088 | Y2: =IF(RosterPlan25[[#This Row],[VAW/G]]>0,ROUND(RosterPlan25[[#This Row],[VAW/G]]*$AG$56,0)+1,1) -> 31 | Z2: =RosterPlan25[[#This Row],[VAWG Market $]]-_xlfn.IFNA(RosterPlan25[[#This Row],[$ CURR]],1) -> 30 | AA2: =IF(RosterPlan25[[#This Row],[VAR/G]]>0,1+ROUND(RosterPlan25[[#This Row],[VAR/G]]*IF(RosterPlan25[[#This Row],[KEEPER / RFA]]="K",($AG$34+RosterPlan25[[#This Row],[$ CURR]]-1)/($AG$23+RosterPlan25[[#This Row],[VAR/G]]),$AG$35),0),1) -> 1 | AB2: =RosterPlan25[[#This Row],[Pure Inflated $]]-RosterPlan25[[#This Row],[$ CURR]] -> 0 | AC2: =INDEX(players[age],MATCH(RosterPlan25[[#This Row],[player_id]],players[sleeper_id],0)) -> 24 | AE2: =300-AG2+AI2+$AE$15-24-AL2 -> 215 | AF2: cthultu | AG2: =SUMIFS(RosterPlan25[[$ CURR]:[$ CURR]],RosterPlan25[[OWNER]:[OWNER]],"="&$AF2,RosterPlan25[[KEEPER / RFA]:[KEEPER / RFA]],"K") -> 89 | AH2: =SUMIFS(RosterPlan25[[$ CURR]:[$ CURR]],RosterPlan25[[OWNER]:[OWNER]],"="&$AF2,RosterPlan25[[KEEPER / RFA]:[KEEPER / RFA]],"K")+ SUMIFS(RosterPlan25[[RFA $]:[RFA $]],RosterPlan25[[OWNER]:[OWNER]],"="&$AF2,RosterPlan25[[KEEPER / RFA]:[KEEPER / RFA]],"RFA") -> 89 | AI2: =COUNTIFS(RosterPlan25[OWNER],"="&$AF2) -> 20 | AJ2: =COUNTIFS(RosterPlan25[OWNER],"="&$AF2,RosterPlan25[KEEPER / RFA],"K") -> 20 | AK2: =COUNTIFS(RosterPlan25[OWNER],"="&$AF2,RosterPlan25[KEEPER / RFA],"RFA") -> 0 | AM2: =AH2+24+AL2-MIN(AJ2+AK2,24) -> 93 | AN2: =SUMIFS(RosterPlan25[[VAR/G]:[VAR/G]],RosterPlan25[[OWNER]:[OWNER]],"="&$AF2,RosterPlan25[[KEEPER / RFA]:[KEEPER / RFA]],"K",RosterPlan25[[VAR/G]:[VAR/G]],">0") -> 4.799523 | AO2: =SUMIFS(RosterPlan25[[VAR/G]:[VAR/G]],RosterPlan25[[OWNER]:[OWNER]],"="&$AF2,RosterPlan25[[KEEPER / RFA]:[KEEPER / RFA]],"RFA",RosterPlan25[[VAR/G]:[VAR/G]],">0") -> 0 | AP2: =SUMIFS(RosterPlan25[[VAR/G]:[VAR/G]],RosterPlan25[[OWNER]:[OWNER]],"="&$AF2,RosterPlan25[[KEEPER / RFA]:[KEEPER / RFA]],"<>K",RosterPlan25[[VAR/G]:[VAR/G]],">0") -> 0 | AQ2: =(300-AM2)/IF(VARG="ATHLETIC",$AH$35,IF(VARG="GOOD",$AG$35,0)) -> 12.597641 | AR2: =AN2+AQ2+AO2 -> 17.397164 | AS2: 19.522489 | AT2: =AR2-AS2 -> -2.1253257 | AU2: =AR2/$AR$12 -> 0.074324076
A3: 11631 | B3: BobbyBaby | C3: Brian Thomas | D3: =_xlfn.IFNA(MATCH(RosterPlan25[[#This Row],[player_id]],CompositeRoster[sleeper_id],0), MATCH(RosterPlan25[[#This Row],[PLAYER]],CompositeRoster[full_name],0)) -> 2 | E3: =MATCH(RosterPlan25[[#This Row],[player_id]],Draft2025[sleeper_id],0) -> 7 | F3: =INDEX(CompositeRoster[team],RosterPlan25[[#This Row],[RosterIndex]])&"" -> JAX | G3: =INDEX(CompositeRoster[position],RosterPlan25[[#This Row],[RosterIndex]])&"" -> WR | H3: =INDEX(CompositeRoster[source],RosterPlan25[[#This Row],[RosterIndex]]) -> Roster | I3: =_xlfn.IFNA(INDEX(Draft2025[PRICE],RosterPlan25[[#This Row],[DraftIndex]]),0) -> 18 | J3: =IF(RosterPlan25[[#This Row],[SOURCE]]="Rookie","Rookie",_xlfn.IFNA(INDEX(Draft2025[Current Contract],RosterPlan25[[#This Row],[DraftIndex]]),"Undrafted")) -> Rookie | K3: {=IF(OR(ISBLANK(RosterPlan25[[#This Row],[player_id]]),NOT(ISNA(MATCH(RosterPlan25[[#This Row],[player_id]],INDIRECT("Rookies" & SEASON &"[player_id]"),0)))), SEASON, _xlfn.IFNA(INDEX(Draft2025[Contract Year],RosterPlan25[[#This Row],[DraftIndex]]),IF(IN_SEASON,SEASON,SEASON-1)))} -> 2024 | L3: =IF(_xlfn.IFNA(INDEX(Draft2025[KEEPER],RosterPlan25[[#This Row],[DraftIndex]]),"")="K","Yes","") -> Yes | M3: {=IF(RosterPlan25[[#This Row],[Contract]]="Rookie", "", IF(_xlfn.IFNA(INDEX(Draft2025[Contract Year],RosterPlan25[[#This Row],[DraftIndex]]),IF(IN_SEASON,SEASON,SEASON-1))+3<SEASON, SEASON, _xlfn.IFNA(INDEX(Draft2025[Contract Year],RosterPlan25[[#This Row],[DraftIndex]]),IF(IN_SEASON,SEASON,SEASON-1))+3))} | N3: =ROUNDDOWN(RosterPlan25[[#This Row],[Optimal $]]*IF(RosterPlan25[[#This Row],[Contract]]="Rookie",0.3,0.15),0) -> 2 | O3: =IF(RosterPlan25[[#This Row],[SOURCE]]="Rookie", INDEX(INDIRECT("Rookies" & SEASON & "[salary]"),MATCH(RosterPlan25[[#This Row],[PLAYER]],INDIRECT("Rookies"& SEASON & "[full_name]"),0)), MAX(RosterPlan25[[#This Row],[$ PREV]] + IF(RAISES_ENABLED,RosterPlan25[[#This Row],[$↑ VAR]],0),1)) -> 20 | P3: =IF(VARG="MANUAL",RosterPlan25[[#This Row],[ManualVARG]],IF(VARG="GOOD",RosterPlan25[[#This Row],[GoodVARG]],"ERR")) -> 0.47162003 | Q3: =_xlfn.IFNA(IF(RosterPlan25[[#This Row],[POS]]="K",0,INDEX(GoodSheets[MG VARG],MATCH(TEXT(RosterPlan25[[#This Row],[player_id]],"0"),GoodSheets[sleeper_id],0))), IF(RosterPlan25[[#This Row],[POS]]="QB",-12,IF(RosterPlan25[[#This Row],[POS]]="RB",-8,IF(RosterPlan25[[#This Row],[POS]]="WR",-8,-5)))) -> 0.47162003 | R3: =_xlfn.IFNA(INDEX(ALL_Athletic[VARG], MATCH(RosterPlan25[[#This Row],[player_id]],ALL_Athletic[SleeperID],0)), IF(RosterPlan25[[#This Row],[POS]]="QB",-12,IF(RosterPlan25[[#This Row],[POS]]="RB",-8,IF(RosterPlan25[[#This Row],[POS]]="WR",-8,-5)))) -> -8 | S3: K | T3: =_xlfn.IFNA(INDEX(Draft2025[Net Keeper Count],RosterPlan25[[#This Row],[DraftIndex]]),0)+IF(RosterPlan25[[#This Row],[KEEPER / RFA]]="K",1,0) -> 2 | U3: =IF(RosterPlan25[[#This Row],[KEEPER / RFA]]="RFA",RosterPlan25[[#This Row],[Pure Inflated $]],"") | V3: =IF(RosterPlan25[[#This Row],[VAR/G]]>0, ROUND(IF(VARG="GOOD",$AG$29,IF(VARG="ATHLETIC",$AH$29,99999999999))*RosterPlan25[[#This Row],[VAR/G]],0), 0) + 1 -> 7 | W3: =RosterPlan25[[#This Row],[Optimal $]]-RosterPlan25[[#This Row],[$ CURR]] -> -13 | X3: =IF(OR(RosterPlan25[[#This Row],[SOURCE]]="Rookie",RosterPlan25[[#This Row],[POS]]="K"),0,RosterPlan25[[#This Row],[VAR/G]]+3.3) -> 3.77162 | Y3: =IF(RosterPlan25[[#This Row],[VAW/G]]>0,ROUND(RosterPlan25[[#This Row],[VAW/G]]*$AG$56,0)+1,1) -> 63 | Z3: =RosterPlan25[[#This Row],[VAWG Market $]]-_xlfn.IFNA(RosterPlan25[[#This Row],[$ CURR]],1) -> 43 | AA3: =IF(RosterPlan25[[#This Row],[VAR/G]]>0,1+ROUND(RosterPlan25[[#This Row],[VAR/G]]*IF(RosterPlan25[[#This Row],[KEEPER / RFA]]="K",($AG$34+RosterPlan25[[#This Row],[$ CURR]]-1)/($AG$23+RosterPlan25[[#This Row],[VAR/G]]),$AG$35),0),1) -> 9 | AB3: =RosterPlan25[[#This Row],[Pure Inflated $]]-RosterPlan25[[#This Row],[$ CURR]] -> -11 | AC3: =INDEX(players[age],MATCH(RosterPlan25[[#This Row],[player_id]],players[sleeper_id],0)) -> 23 | AE3: =300-AG3+AI3+$AE$15-24-AL3 -> 133 | AF3: mcmahanwich | AG3: =SUMIFS(RosterPlan25[[$ CURR]:[$ CURR]],RosterPlan25[[OWNER]:[OWNER]],"="&$AF3,RosterPlan25[[KEEPER / RFA]:[KEEPER / RFA]],"K") -> 175 | AH3: =SUMIFS(RosterPlan25[[$ CURR]:[$ CURR]],RosterPlan25[[OWNER]:[OWNER]],"="&$AF3,RosterPlan25[[KEEPER / RFA]:[KEEPER / RFA]],"K")+ SUMIFS(RosterPlan25[[RFA $]:[RFA $]],RosterPlan25[[OWNER]:[OWNER]],"="&$AF3,RosterPlan25[[KEEPER / RFA]:[KEEPER / RFA]],"RFA") -> 175 | AI3: =COUNTIFS(RosterPlan25[OWNER],"="&$AF3) -> 24 | AJ3: =COUNTIFS(RosterPlan25[OWNER],"="&$AF3,RosterPlan25[KEEPER / RFA],"K") -> 24 | AK3: =COUNTIFS(RosterPlan25[OWNER],"="&$AF3,RosterPlan25[KEEPER / RFA],"RFA") -> 0 | AM3: =AH3+24+AL3-MIN(AJ3+AK3,24) -> 175 | AN3: =SUMIFS(RosterPlan25[[VAR/G]:[VAR/G]],RosterPlan25[[OWNER]:[OWNER]],"="&$AF3,RosterPlan25[[KEEPER / RFA]:[KEEPER / RFA]],"K",RosterPlan25[[VAR/G]:[VAR/G]],">0") -> 13.728754 | AO3: =SUMIFS(RosterPlan25[[VAR/G]:[VAR/G]],RosterPlan25[[OWNER]:[OWNER]],"="&$AF3,RosterPlan25[[KEEPER / RFA]:[KEEPER / RFA]],"RFA",RosterPlan25[[VAR/G]:[VAR/G]],">0") -> 0 | AP3: =SUMIFS(RosterPlan25[[VAR/G]:[VAR/G]],RosterPlan25[[OWNER]:[OWNER]],"="&$AF3,RosterPlan25[[KEEPER / RFA]:[KEEPER / RFA]],"<>K",RosterPlan25[[VAR/G]:[VAR/G]],">0") -> 0 | AQ3: =(300-AM3)/IF(VARG="ATHLETIC",$AH$35,IF(VARG="GOOD",$AG$35,0)) -> 7.6072709 | AR3: =AN3+AQ3+AO3 -> 21.336025 | AS3: 19.527714 | AT3: =AR3-AS3 -> 1.8083116 | AU3: =AR3/$AR$12 -> 0.091151661
A4: 10236 | B4: BobbyBaby | C4: Dalton Kincaid | D4: =_xlfn.IFNA(MATCH(RosterPlan25[[#This Row],[player_id]],CompositeRoster[sleeper_id],0), MATCH(RosterPlan25[[#This Row],[PLAYER]],CompositeRoster[full_name],0)) -> 3 | E4: =MATCH(RosterPlan25[[#This Row],[player_id]],Draft2025[sleeper_id],0) -> 8 | F4: =INDEX(CompositeRoster[team],RosterPlan25[[#This Row],[RosterIndex]])&"" -> BUF | G4: =INDEX(CompositeRoster[position],RosterPlan25[[#This Row],[RosterIndex]])&"" -> TE | H4: =INDEX(CompositeRoster[source],RosterPlan25[[#This Row],[RosterIndex]]) -> Roster | I4: =_xlfn.IFNA(INDEX(Draft2025[PRICE],RosterPlan25[[#This Row],[DraftIndex]]),0) -> 13 | J4: =IF(RosterPlan25[[#This Row],[SOURCE]]="Rookie","Rookie",_xlfn.IFNA(INDEX(Draft2025[Current Contract],RosterPlan25[[#This Row],[DraftIndex]]),"Undrafted")) -> Rookie | K4: {=IF(OR(ISBLANK(RosterPlan25[[#This Row],[player_id]]),NOT(ISNA(MATCH(RosterPlan25[[#This Row],[player_id]],INDIRECT("Rookies" & SEASON &"[player_id]"),0)))), SEASON, _xlfn.IFNA(INDEX(Draft2025[Contract Year],RosterPlan25[[#This Row],[DraftIndex]]),IF(IN_SEASON,SEASON,SEASON-1)))} -> 2023 | L4: =IF(_xlfn.IFNA(INDEX(Draft2025[KEEPER],RosterPlan25[[#This Row],[DraftIndex]]),"")="K","Yes","") -> Yes | M4: {=IF(RosterPlan25[[#This Row],[Contract]]="Rookie", "", IF(_xlfn.IFNA(INDEX(Draft2025[Contract Year],RosterPlan25[[#This Row],[DraftIndex]]),IF(IN_SEASON,SEASON,SEASON-1))+3<SEASON, SEASON, _xlfn.IFNA(INDEX(Draft2025[Contract Year],RosterPlan25[[#This Row],[DraftIndex]]),IF(IN_SEASON,SEASON,SEASON-1))+3))} | N4: =ROUNDDOWN(RosterPlan25[[#This Row],[Optimal $]]*IF(RosterPlan25[[#This Row],[Contract]]="Rookie",0.3,0.15),0) -> 2 | O4: =IF(RosterPlan25[[#This Row],[SOURCE]]="Rookie", INDEX(INDIRECT("Rookies" & SEASON & "[salary]"),MATCH(RosterPlan25[[#This Row],[PLAYER]],INDIRECT("Rookies"& SEASON & "[full_name]"),0)), MAX(RosterPlan25[[#This Row],[$ PREV]] + IF(RAISES_ENABLED,RosterPlan25[[#This Row],[$↑ VAR]],0),1)) -> 15 | P4: =IF(VARG="MANUAL",RosterPlan25[[#This Row],[ManualVARG]],IF(VARG="GOOD",RosterPlan25[[#This Row],[GoodVARG]],"ERR")) -> 0.63336655 | Q4: =_xlfn.IFNA(IF(RosterPlan25[[#This Row],[POS]]="K",0,INDEX(GoodSheets[MG VARG],MATCH(TEXT(RosterPlan25[[#This Row],[player_id]],"0"),GoodSheets[sleeper_id],0))), IF(RosterPlan25[[#This Row],[POS]]="QB",-12,IF(RosterPlan25[[#This Row],[POS]]="RB",-8,IF(RosterPlan25[[#This Row],[POS]]="WR",-8,-5)))) -> 0.63336655 | R4: =_xlfn.IFNA(INDEX(ALL_Athletic[VARG], MATCH(RosterPlan25[[#This Row],[player_id]],ALL_Athletic[SleeperID],0)), IF(RosterPlan25[[#This Row],[POS]]="QB",-12,IF(RosterPlan25[[#This Row],[POS]]="RB",-8,IF(RosterPlan25[[#This Row],[POS]]="WR",-8,-5)))) -> -0.46649975 | S4: K | T4: =_xlfn.IFNA(INDEX(Draft2025[Net Keeper Count],RosterPlan25[[#This Row],[DraftIndex]]),0)+IF(RosterPlan25[[#This Row],[KEEPER / RFA]]="K",1,0) -> 3 | U4: =IF(RosterPlan25[[#This Row],[KEEPER / RFA]]="RFA",RosterPlan25[[#This Row],[Pure Inflated $]],"") | V4: =IF(RosterPlan25[[#This Row],[VAR/G]]>0, ROUND(IF(VARG="GOOD",$AG$29,IF(VARG="ATHLETIC",$AH$29,99999999999))*RosterPlan25[[#This Row],[VAR/G]],0), 0) + 1 -> 8 | W4: =RosterPlan25[[#This Row],[Optimal $]]-RosterPlan25[[#This Row],[$ CURR]] -> -7 | X4: =IF(OR(RosterPlan25[[#This Row],[SOURCE]]="Rookie",RosterPlan25[[#This Row],[POS]]="K"),0,RosterPlan25[[#This Row],[VAR/G]]+3.3) -> 3.9333666 | Y4: =IF(RosterPlan25[[#This Row],[VAW/G]]>0,ROUND(RosterPlan25[[#This Row],[VAW/G]]*$AG$56,0)+1,1) -> 66 | Z4: =RosterPlan25[[#This Row],[VAWG Market $]]-_xlfn.IFNA(RosterPlan25[[#This Row],[$ CURR]],1) -> 51 | AA4: =IF(RosterPlan25[[#This Row],[VAR/G]]>0,1+ROUND(RosterPlan25[[#This Row],[VAR/G]]*IF(RosterPlan25[[#This Row],[KEEPER / RFA]]="K",($AG$34+RosterPlan25[[#This Row],[$ CURR]]-1)/($AG$23+RosterPlan25[[#This Row],[VAR/G]]),$AG$35),0),1) -> 11 | AB4: =RosterPlan25[[#This Row],[Pure Inflated $]]-RosterPlan25[[#This Row],[$ CURR]] -> -4 | AC4: =INDEX(players[age],MATCH(RosterPlan25[[#This Row],[player_id]],players[sleeper_id],0)) -> 26 | AE4: =300-AG4+AI4+$AE$15-24-AL4 -> 61 | AF4: GentlemanBrewer | AG4: =SUMIFS(RosterPlan25[[$ CURR]:[$ CURR]],RosterPlan25[[OWNER]:[OWNER]],"="&$AF4,RosterPlan25[[KEEPER / RFA]:[KEEPER / RFA]],"K") -> 241 | AH4: =SUMIFS(RosterPlan25[[$ CURR]:[$ CURR]],RosterPlan25[[OWNER]:[OWNER]],"="&$AF4,RosterPlan25[[KEEPER / RFA]:[KEEPER / RFA]],"K")+ SUMIFS(RosterPlan25[[RFA $]:[RFA $]],RosterPlan25[[OWNER]:[OWNER]],"="&$AF4,RosterPlan25[[KEEPER / RFA]:[KEEPER / RFA]],"RFA") -> 241 | AI4: =COUNTIFS(RosterPlan25[OWNER],"="&$AF4) -> 18 | AJ4: =COUNTIFS(RosterPlan25[OWNER],"="&$AF4,RosterPlan25[KEEPER / RFA],"K") -> 18 | AK4: =COUNTIFS(RosterPlan25[OWNER],"="&$AF4,RosterPlan25[KEEPER / RFA],"RFA") -> 0 | AM4: =AH4+24+AL4-MIN(AJ4+AK4,24) -> 247 | AN4: =SUMIFS(RosterPlan25[[VAR/G]:[VAR/G]],RosterPlan25[[OWNER]:[OWNER]],"="&$AF4,RosterPlan25[[KEEPER / RFA]:[KEEPER / RFA]],"K",RosterPlan25[[VAR/G]:[VAR/G]],">0") -> 20.105512 | AO4: =SUMIFS(RosterPlan25[[VAR/G]:[VAR/G]],RosterPlan25[[OWNER]:[OWNER]],"="&$AF4,RosterPlan25[[KEEPER / RFA]:[KEEPER / RFA]],"RFA",RosterPlan25[[VAR/G]:[VAR/G]],">0") -> 0 | AP4: =SUMIFS(RosterPlan25[[VAR/G]:[VAR/G]],RosterPlan25[[OWNER]:[OWNER]],"="&$AF4,RosterPlan25[[KEEPER / RFA]:[KEEPER / RFA]],"<>K",RosterPlan25[[VAR/G]:[VAR/G]],">0") -> 0 | AQ4: =(300-AM4)/IF(VARG="ATHLETIC",$AH$35,IF(VARG="GOOD",$AG$35,0)) -> 3.2254829 | AR4: =AN4+AQ4+AO4 -> 23.330995 | AS4: 24.008323 | AT4: =AR4-AS4 -> -0.67732798 | AU4: =AR4/$AR$12 -> 0.09967456
A5: 5870 | B5: BobbyBaby | C5: Daniel Jones | D5: =_xlfn.IFNA(MATCH(RosterPlan25[[#This Row],[player_id]],CompositeRoster[sleeper_id],0), MATCH(RosterPlan25[[#This Row],[PLAYER]],CompositeRoster[full_name],0)) -> 4 | E5: =MATCH(RosterPlan25[[#This Row],[player_id]],Draft2025[sleeper_id],0) -> 9 | F5: =INDEX(CompositeRoster[team],RosterPlan25[[#This Row],[RosterIndex]])&"" -> IND | G5: =INDEX(CompositeRoster[position],RosterPlan25[[#This Row],[RosterIndex]])&"" -> QB | H5: =INDEX(CompositeRoster[source],RosterPlan25[[#This Row],[RosterIndex]]) -> Roster | I5: =_xlfn.IFNA(INDEX(Draft2025[PRICE],RosterPlan25[[#This Row],[DraftIndex]]),0) -> 3 | J5: =IF(RosterPlan25[[#This Row],[SOURCE]]="Rookie","Rookie",_xlfn.IFNA(INDEX(Draft2025[Current Contract],RosterPlan25[[#This Row],[DraftIndex]]),"Undrafted")) -> Rookie | K5: {=IF(OR(ISBLANK(RosterPlan25[[#This Row],[player_id]]),NOT(ISNA(MATCH(RosterPlan25[[#This Row],[player_id]],INDIRECT("Rookies" & SEASON &"[player_id]"),0)))), SEASON, _xlfn.IFNA(INDEX(Draft2025[Contract Year],RosterPlan25[[#This Row],[DraftIndex]]),IF(IN_SEASON,SEASON,SEASON-1)))} -> 2019 | L5: =IF(_xlfn.IFNA(INDEX(Draft2025[KEEPER],RosterPlan25[[#This Row],[DraftIndex]]),"")="K","Yes","") -> Yes | M5: {=IF(RosterPlan25[[#This Row],[Contract]]="Rookie", "", IF(_xlfn.IFNA(INDEX(Draft2025[Contract Year],RosterPlan25[[#This Row],[DraftIndex]]),IF(IN_SEASON,SEASON,SEASON-1))+3<SEASON, SEASON, _xlfn.IFNA(INDEX(Draft2025[Contract Year],RosterPlan25[[#This Row],[DraftIndex]]),IF(IN_SEASON,SEASON,SEASON-1))+3))} | N5: =ROUNDDOWN(RosterPlan25[[#This Row],[Optimal $]]*IF(RosterPlan25[[#This Row],[Contract]]="Rookie",0.3,0.15),0) -> 0 | O5: =IF(RosterPlan25[[#This Row],[SOURCE]]="Rookie", INDEX(INDIRECT("Rookies" & SEASON & "[salary]"),MATCH(RosterPlan25[[#This Row],[PLAYER]],INDIRECT("Rookies"& SEASON & "[full_name]"),0)), MAX(RosterPlan25[[#This Row],[$ PREV]] + IF(RAISES_ENABLED,RosterPlan25[[#This Row],[$↑ VAR]],0),1)) -> 3 | P5: =IF(VARG="MANUAL",RosterPlan25[[#This Row],[ManualVARG]],IF(VARG="GOOD",RosterPlan25[[#This Row],[GoodVARG]],"ERR")) -> -2.9186835 | Q5: =_xlfn.IFNA(IF(RosterPlan25[[#This Row],[POS]]="K",0,INDEX(GoodSheets[MG VARG],MATCH(TEXT(RosterPlan25[[#This Row],[player_id]],"0"),GoodSheets[sleeper_id],0))), IF(RosterPlan25[[#This Row],[POS]]="QB",-12,IF(RosterPlan25[[#This Row],[POS]]="RB",-8,IF(RosterPlan25[[#This Row],[POS]]="WR",-8,-5)))) -> -2.9186835 | R5: =_xlfn.IFNA(INDEX(ALL_Athletic[VARG], MATCH(RosterPlan25[[#This Row],[player_id]],ALL_Athletic[SleeperID],0)), IF(RosterPlan25[[#This Row],[POS]]="QB",-12,IF(RosterPlan25[[#This Row],[POS]]="RB",-8,IF(RosterPlan25[[#This Row],[POS]]="WR",-8,-5)))) -> 0.58442541 | S5: K | T5: =_xlfn.IFNA(INDEX(Draft2025[Net Keeper Count],RosterPlan25[[#This Row],[DraftIndex]]),0)+IF(RosterPlan25[[#This Row],[KEEPER / RFA]]="K",1,0) -> 7 | U5: =IF(RosterPlan25[[#This Row],[KEEPER / RFA]]="RFA",RosterPlan25[[#This Row],[Pure Inflated $]],"") | V5: =IF(RosterPlan25[[#This Row],[VAR/G]]>0, ROUND(IF(VARG="GOOD",$AG$29,IF(VARG="ATHLETIC",$AH$29,99999999999))*RosterPlan25[[#This Row],[VAR/G]],0), 0) + 1 -> 1 | W5: =RosterPlan25[[#This Row],[Optimal $]]-RosterPlan25[[#This Row],[$ CURR]] -> -2 | X5: =IF(OR(RosterPlan25[[#This Row],[SOURCE]]="Rookie",RosterPlan25[[#This Row],[POS]]="K"),0,RosterPlan25[[#This Row],[VAR/G]]+3.3) -> 0.38131648 | Y5: =IF(RosterPlan25[[#This Row],[VAW/G]]>0,ROUND(RosterPlan25[[#This Row],[VAW/G]]*$AG$56,0)+1,1) -> 7 | Z5: =RosterPlan25[[#This Row],[VAWG Market $]]-_xlfn.IFNA(RosterPlan25[[#This Row],[$ CURR]],1) -> 4 | AA5: =IF(RosterPlan25[[#This Row],[VAR/G]]>0,1+ROUND(RosterPlan25[[#This Row],[VAR/G]]*IF(RosterPlan25[[#This Row],[KEEPER / RFA]]="K",($AG$34+RosterPlan25[[#This Row],[$ CURR]]-1)/($AG$23+RosterPlan25[[#This Row],[VAR/G]]),$AG$35),0),1) -> 1 | AB5: =RosterPlan25[[#This Row],[Pure Inflated $]]-RosterPlan25[[#This Row],[$ CURR]] -> -2 | AC5: =INDEX(players[age],MATCH(RosterPlan25[[#This Row],[player_id]],players[sleeper_id],0)) -> 29 | AE5: =300-AG5+AI5+$AE$15-24-AL5 -> 25 | AF5: hellj85 | AG5: =SUMIFS(RosterPlan25[[$ CURR]:[$ CURR]],RosterPlan25[[OWNER]:[OWNER]],"="&$AF5,RosterPlan25[[KEEPER / RFA]:[KEEPER / RFA]],"K") -> 281 | AH5: =SUMIFS(RosterPlan25[[$ CURR]:[$ CURR]],RosterPlan25[[OWNER]:[OWNER]],"="&$AF5,RosterPlan25[[KEEPER / RFA]:[KEEPER / RFA]],"K")+ SUMIFS(RosterPlan25[[RFA $]:[RFA $]],RosterPlan25[[OWNER]:[OWNER]],"="&$AF5,RosterPlan25[[KEEPER / RFA]:[KEEPER / RFA]],"RFA") -> 281 | AI5: =COUNTIFS(RosterPlan25[OWNER],"="&$AF5) -> 22 | AJ5: =COUNTIFS(RosterPlan25[OWNER],"="&$AF5,RosterPlan25[KEEPER / RFA],"K") -> 22 | AK5: =COUNTIFS(RosterPlan25[OWNER],"="&$AF5,RosterPlan25[KEEPER / RFA],"RFA") -> 0 | AM5: =AH5+24+AL5-MIN(AJ5+AK5,24) -> 283 | AN5: =SUMIFS(RosterPlan25[[VAR/G]:[VAR/G]],RosterPlan25[[OWNER]:[OWNER]],"="&$AF5,RosterPlan25[[KEEPER / RFA]:[KEEPER / RFA]],"K",RosterPlan25[[VAR/G]:[VAR/G]],">0") -> 33.552718 | AO5: =SUMIFS(RosterPlan25[[VAR/G]:[VAR/G]],RosterPlan25[[OWNER]:[OWNER]],"="&$AF5,RosterPlan25[[KEEPER / RFA]:[KEEPER / RFA]],"RFA",RosterPlan25[[VAR/G]:[VAR/G]],">0") -> 0 | AP5: =SUMIFS(RosterPlan25[[VAR/G]:[VAR/G]],RosterPlan25[[OWNER]:[OWNER]],"="&$AF5,RosterPlan25[[KEEPER / RFA]:[KEEPER / RFA]],"<>K",RosterPlan25[[VAR/G]:[VAR/G]],">0") -> 0 | AQ5: =(300-AM5)/IF(VARG="ATHLETIC",$AH$35,IF(VARG="GOOD",$AG$35,0)) -> 1.0345888 | AR5: =AN5+AQ5+AO5 -> 34.587307 | AS5: 23.052842 | AT5: =AR5-AS5 -> 11.534465 | AU5: =AR5/$AR$12 -> 0.14776372
A6: 8698 | B6: BobbyBaby | C6: Jake Tonges | D6: =_xlfn.IFNA(MATCH(RosterPlan25[[#This Row],[player_id]],CompositeRoster[sleeper_id],0), MATCH(RosterPlan25[[#This Row],[PLAYER]],CompositeRoster[full_name],0)) -> 5 | E6: =MATCH(RosterPlan25[[#This Row],[player_id]],Draft2025[sleeper_id],0) -> #N/A | F6: =INDEX(CompositeRoster[team],RosterPlan25[[#This Row],[RosterIndex]])&"" -> SF | G6: =INDEX(CompositeRoster[position],RosterPlan25[[#This Row],[RosterIndex]])&"" -> TE | H6: =INDEX(CompositeRoster[source],RosterPlan25[[#This Row],[RosterIndex]]) -> Roster | I6: =_xlfn.IFNA(INDEX(Draft2025[PRICE],RosterPlan25[[#This Row],[DraftIndex]]),0) -> 0 | J6: =IF(RosterPlan25[[#This Row],[SOURCE]]="Rookie","Rookie",_xlfn.IFNA(INDEX(Draft2025[Current Contract],RosterPlan25[[#This Row],[DraftIndex]]),"Undrafted")) -> Undrafted | K6: {=IF(OR(ISBLANK(RosterPlan25[[#This Row],[player_id]]),NOT(ISNA(MATCH(RosterPlan25[[#This Row],[player_id]],INDIRECT("Rookies" & SEASON &"[player_id]"),0)))), SEASON, _xlfn.IFNA(INDEX(Draft2025[Contract Year],RosterPlan25[[#This Row],[DraftIndex]]),IF(IN_SEASON,SEASON,SEASON-1)))} -> 2025 | L6: =IF(_xlfn.IFNA(INDEX(Draft2025[KEEPER],RosterPlan25[[#This Row],[DraftIndex]]),"")="K","Yes","") | M6: {=IF(RosterPlan25[[#This Row],[Contract]]="Rookie", "", IF(_xlfn.IFNA(INDEX(Draft2025[Contract Year],RosterPlan25[[#This Row],[DraftIndex]]),IF(IN_SEASON,SEASON,SEASON-1))+3<SEASON, SEASON, _xlfn.IFNA(INDEX(Draft2025[Contract Year],RosterPlan25[[#This Row],[DraftIndex]]),IF(IN_SEASON,SEASON,SEASON-1))+3))} -> 2028 | N6: =ROUNDDOWN(RosterPlan25[[#This Row],[Optimal $]]*IF(RosterPlan25[[#This Row],[Contract]]="Rookie",0.3,0.15),0) -> 0 | O6: =IF(RosterPlan25[[#This Row],[SOURCE]]="Rookie", INDEX(INDIRECT("Rookies" & SEASON & "[salary]"),MATCH(RosterPlan25[[#This Row],[PLAYER]],INDIRECT("Rookies"& SEASON & "[full_name]"),0)), MAX(RosterPlan25[[#This Row],[$ PREV]] + IF(RAISES_ENABLED,RosterPlan25[[#This Row],[$↑ VAR]],0),1)) -> 1 | P6: =IF(VARG="MANUAL",RosterPlan25[[#This Row],[ManualVARG]],IF(VARG="GOOD",RosterPlan25[[#This Row],[GoodVARG]],"ERR")) -> -4.5165313 | Q6: =_xlfn.IFNA(IF(RosterPlan25[[#This Row],[POS]]="K",0,INDEX(GoodSheets[MG VARG],MATCH(TEXT(RosterPlan25[[#This Row],[player_id]],"0"),GoodSheets[sleeper_id],0))), IF(RosterPlan25[[#This Row],[POS]]="QB",-12,IF(RosterPlan25[[#This Row],[POS]]="RB",-8,IF(RosterPlan25[[#This Row],[POS]]="WR",-8,-5)))) -> -4.5165313 | R6: =_xlfn.IFNA(INDEX(ALL_Athletic[VARG], MATCH(RosterPlan25[[#This Row],[player_id]],ALL_Athletic[SleeperID],0)), IF(RosterPlan25[[#This Row],[POS]]="QB",-12,IF(RosterPlan25[[#This Row],[POS]]="RB",-8,IF(RosterPlan25[[#This Row],[POS]]="WR",-8,-5)))) -> -5 | S6: K | T6: =_xlfn.IFNA(INDEX(Draft2025[Net Keeper Count],RosterPlan25[[#This Row],[DraftIndex]]),0)+IF(RosterPlan25[[#This Row],[KEEPER / RFA]]="K",1,0) -> 1 | U6: =IF(RosterPlan25[[#This Row],[KEEPER / RFA]]="RFA",RosterPlan25[[#This Row],[Pure Inflated $]],"") | V6: =IF(RosterPlan25[[#This Row],[VAR/G]]>0, ROUND(IF(VARG="GOOD",$AG$29,IF(VARG="ATHLETIC",$AH$29,99999999999))*RosterPlan25[[#This Row],[VAR/G]],0), 0) + 1 -> 1 | W6: =RosterPlan25[[#This Row],[Optimal $]]-RosterPlan25[[#This Row],[$ CURR]] -> 0 | X6: =IF(OR(RosterPlan25[[#This Row],[SOURCE]]="Rookie",RosterPlan25[[#This Row],[POS]]="K"),0,RosterPlan25[[#This Row],[VAR/G]]+3.3) -> -1.2165313 | Y6: =IF(RosterPlan25[[#This Row],[VAW/G]]>0,ROUND(RosterPlan25[[#This Row],[VAW/G]]*$AG$56,0)+1,1) -> 1 | Z6: =RosterPlan25[[#This Row],[VAWG Market $]]-_xlfn.IFNA(RosterPlan25[[#This Row],[$ CURR]],1) -> 0 | AA6: =IF(RosterPlan25[[#This Row],[VAR/G]]>0,1+ROUND(RosterPlan25[[#This Row],[VAR/G]]*IF(RosterPlan25[[#This Row],[KEEPER / RFA]]="K",($AG$34+RosterPlan25[[#This Row],[$ CURR]]-1)/($AG$23+RosterPlan25[[#This Row],[VAR/G]]),$AG$35),0),1) -> 1 | AB6: =RosterPlan25[[#This Row],[Pure Inflated $]]-RosterPlan25[[#This Row],[$ CURR]] -> 0 | AC6: =INDEX(players[age],MATCH(RosterPlan25[[#This Row],[player_id]],players[sleeper_id],0)) -> 27 | AE6: =300-AG6+AI6+$AE$15-24-AL6 -> 149 | AF6: demboys26 | AG6: =SUMIFS(RosterPlan25[[$ CURR]:[$ CURR]],RosterPlan25[[OWNER]:[OWNER]],"="&$AF6,RosterPlan25[[KEEPER / RFA]:[KEEPER / RFA]],"K") -> 153 | AH6: =SUMIFS(RosterPlan25[[$ CURR]:[$ CURR]],RosterPlan25[[OWNER]:[OWNER]],"="&$AF6,RosterPlan25[[KEEPER / RFA]:[KEEPER / RFA]],"K")+ SUMIFS(RosterPlan25[[RFA $]:[RFA $]],RosterPlan25[[OWNER]:[OWNER]],"="&$AF6,RosterPlan25[[KEEPER / RFA]:[KEEPER / RFA]],"RFA") -> 153 | AI6: =COUNTIFS(RosterPlan25[OWNER],"="&$AF6) -> 18 | AJ6: =COUNTIFS(RosterPlan25[OWNER],"="&$AF6,RosterPlan25[KEEPER / RFA],"K") -> 18 | AK6: =COUNTIFS(RosterPlan25[OWNER],"="&$AF6,RosterPlan25[KEEPER / RFA],"RFA") -> 0 | AM6: =AH6+24+AL6-MIN(AJ6+AK6,24) -> 159 | AN6: =SUMIFS(RosterPlan25[[VAR/G]:[VAR/G]],RosterPlan25[[OWNER]:[OWNER]],"="&$AF6,RosterPlan25[[KEEPER / RFA]:[KEEPER / RFA]],"K",RosterPlan25[[VAR/G]:[VAR/G]],">0") -> 8.6664426 | AO6: =SUMIFS(RosterPlan25[[VAR/G]:[VAR/G]],RosterPlan25[[OWNER]:[OWNER]],"="&$AF6,RosterPlan25[[KEEPER / RFA]:[KEEPER / RFA]],"RFA",RosterPlan25[[VAR/G]:[VAR/G]],">0") -> 0 | AP6: =SUMIFS(RosterPlan25[[VAR/G]:[VAR/G]],RosterPlan25[[OWNER]:[OWNER]],"="&$AF6,RosterPlan25[[KEEPER / RFA]:[KEEPER / RFA]],"<>K",RosterPlan25[[VAR/G]:[VAR/G]],">0") -> 0 | AQ6: =(300-AM6)/IF(VARG="ATHLETIC",$AH$35,IF(VARG="GOOD",$AG$35,0)) -> 8.5810016 | AR6: =AN6+AQ6+AO6 -> 17.247444 | AS6: 27.344519 | AT6: =AR6-AS6 -> -10.097075 | AU6: =AR6/$AR$12 -> 0.073684445
A7: 5947 | B7: BobbyBaby | C7: Jakobi Meyers | D7: =_xlfn.IFNA(MATCH(RosterPlan25[[#This Row],[player_id]],CompositeRoster[sleeper_id],0), MATCH(RosterPlan25[[#This Row],[PLAYER]],CompositeRoster[full_name],0)) -> 6 | E7: =MATCH(RosterPlan25[[#This Row],[player_id]],Draft2025[sleeper_id],0) -> 174 | F7: =INDEX(CompositeRoster[team],RosterPlan25[[#This Row],[RosterIndex]])&"" -> JAX | G7: =INDEX(CompositeRoster[position],RosterPlan25[[#This Row],[RosterIndex]])&"" -> WR | H7: =INDEX(CompositeRoster[source],RosterPlan25[[#This Row],[RosterIndex]]) -> Roster | I7: =_xlfn.IFNA(INDEX(Draft2025[PRICE],RosterPlan25[[#This Row],[DraftIndex]]),0) -> 8 | J7: =IF(RosterPlan25[[#This Row],[SOURCE]]="Rookie","Rookie",_xlfn.IFNA(INDEX(Draft2025[Current Contract],RosterPlan25[[#This Row],[DraftIndex]]),"Undrafted")) -> Auction | K7: {=IF(OR(ISBLANK(RosterPlan25[[#This Row],[player_id]]),NOT(ISNA(MATCH(RosterPlan25[[#This Row],[player_id]],INDIRECT("Rookies" & SEASON &"[player_id]"),0)))), SEASON, _xlfn.IFNA(INDEX(Draft2025[Contract Year],RosterPlan25[[#This Row],[DraftIndex]]),IF(IN_SEASON,SEASON,SEASON-1)))} -> 2024 | L7: =IF(_xlfn.IFNA(INDEX(Draft2025[KEEPER],RosterPlan25[[#This Row],[DraftIndex]]),"")="K","Yes","") -> Yes | M7: {=IF(RosterPlan25[[#This Row],[Contract]]="Rookie", "", IF(_xlfn.IFNA(INDEX(Draft2025[Contract Year],RosterPlan25[[#This Row],[DraftIndex]]),IF(IN_SEASON,SEASON,SEASON-1))+3<SEASON, SEASON, _xlfn.IFNA(INDEX(Draft2025[Contract Year],RosterPlan25[[#This Row],[DraftIndex]]),IF(IN_SEASON,SEASON,SEASON-1))+3))} -> 2027 | N7: =ROUNDDOWN(RosterPlan25[[#This Row],[Optimal $]]*IF(RosterPlan25[[#This Row],[Contract]]="Rookie",0.3,0.15),0) -> 0 | O7: =IF(RosterPlan25[[#This Row],[SOURCE]]="Rookie", INDEX(INDIRECT("Rookies" & SEASON & "[salary]"),MATCH(RosterPlan25[[#This Row],[PLAYER]],INDIRECT("Rookies"& SEASON & "[full_name]"),0)), MAX(RosterPlan25[[#This Row],[$ PREV]] + IF(RAISES_ENABLED,RosterPlan25[[#This Row],[$↑ VAR]],0),1)) -> 8 | P7: =IF(VARG="MANUAL",RosterPlan25[[#This Row],[ManualVARG]],IF(VARG="GOOD",RosterPlan25[[#This Row],[GoodVARG]],"ERR")) -> -0.48171702 | Q7: =_xlfn.IFNA(IF(RosterPlan25[[#This Row],[POS]]="K",0,INDEX(GoodSheets[MG VARG],MATCH(TEXT(RosterPlan25[[#This Row],[player_id]],"0"),GoodSheets[sleeper_id],0))), IF(RosterPlan25[[#This Row],[POS]]="QB",-12,IF(RosterPlan25[[#This Row],[POS]]="RB",-8,IF(RosterPlan25[[#This Row],[POS]]="WR",-8,-5)))) -> -0.48171702 | R7: =_xlfn.IFNA(INDEX(ALL_Athletic[VARG], MATCH(RosterPlan25[[#This Row],[player_id]],ALL_Athletic[SleeperID],0)), IF(RosterPlan25[[#This Row],[POS]]="QB",-12,IF(RosterPlan25[[#This Row],[POS]]="RB",-8,IF(RosterPlan25[[#This Row],[POS]]="WR",-8,-5)))) -> -0.09253197 | S7: K | T7: =_xlfn.IFNA(INDEX(Draft2025[Net Keeper Count],RosterPlan25[[#This Row],[DraftIndex]]),0)+IF(RosterPlan25[[#This Row],[KEEPER / RFA]]="K",1,0) -> 2 | U7: =IF(RosterPlan25[[#This Row],[KEEPER / RFA]]="RFA",RosterPlan25[[#This Row],[Pure Inflated $]],"") | V7: =IF(RosterPlan25[[#This Row],[VAR/G]]>0, ROUND(IF(VARG="GOOD",$AG$29,IF(VARG="ATHLETIC",$AH$29,99999999999))*RosterPlan25[[#This Row],[VAR/G]],0), 0) + 1 -> 1 | W7: =RosterPlan25[[#This Row],[Optimal $]]-RosterPlan25[[#This Row],[$ CURR]] -> -7 | X7: =IF(OR(RosterPlan25[[#This Row],[SOURCE]]="Rookie",RosterPlan25[[#This Row],[POS]]="K"),0,RosterPlan25[[#This Row],[VAR/G]]+3.3) -> 2.818283 | Y7: =IF(RosterPlan25[[#This Row],[VAW/G]]>0,ROUND(RosterPlan25[[#This Row],[VAW/G]]*$AG$56,0)+1,1) -> 47 | Z7: =RosterPlan25[[#This Row],[VAWG Market $]]-_xlfn.IFNA(RosterPlan25[[#This Row],[$ CURR]],1) -> 39 | AA7: =IF(RosterPlan25[[#This Row],[VAR/G]]>0,1+ROUND(RosterPlan25[[#This Row],[VAR/G]]*IF(RosterPlan25[[#This Row],[KEEPER / RFA]]="K",($AG$34+RosterPlan25[[#This Row],[$ CURR]]-1)/($AG$23+RosterPlan25[[#This Row],[VAR/G]]),$AG$35),0),1) -> 1 | AB7: =RosterPlan25[[#This Row],[Pure Inflated $]]-RosterPlan25[[#This Row],[$ CURR]] -> -7 | AC7: =INDEX(players[age],MATCH(RosterPlan25[[#This Row],[player_id]],players[sleeper_id],0)) -> 29 | AE7: =300-AG7+AI7+$AE$15-24-AL7 -> 149 | AF7: BobbyBaby | AG7: =SUMIFS(RosterPlan25[[$ CURR]:[$ CURR]],RosterPlan25[[OWNER]:[OWNER]],"="&$AF7,RosterPlan25[[KEEPER / RFA]:[KEEPER / RFA]],"K") -> 156 | AH7: =SUMIFS(RosterPlan25[[$ CURR]:[$ CURR]],RosterPlan25[[OWNER]:[OWNER]],"="&$AF7,RosterPlan25[[KEEPER / RFA]:[KEEPER / RFA]],"K")+ SUMIFS(RosterPlan25[[RFA $]:[RFA $]],RosterPlan25[[OWNER]:[OWNER]],"="&$AF7,RosterPlan25[[KEEPER / RFA]:[KEEPER / RFA]],"RFA") -> 156 | AI7: =COUNTIFS(RosterPlan25[OWNER],"="&$AF7) -> 21 | AJ7: =COUNTIFS(RosterPlan25[OWNER],"="&$AF7,RosterPlan25[KEEPER / RFA],"K") -> 21 | AK7: =COUNTIFS(RosterPlan25[OWNER],"="&$AF7,RosterPlan25[KEEPER / RFA],"RFA") -> 0 | AM7: =AH7+24+AL7-MIN(AJ7+AK7,24) -> 159 | AN7: =SUMIFS(RosterPlan25[[VAR/G]:[VAR/G]],RosterPlan25[[OWNER]:[OWNER]],"="&$AF7,RosterPlan25[[KEEPER / RFA]:[KEEPER / RFA]],"K",RosterPlan25[[VAR/G]:[VAR/G]],">0") -> 8.8920078 | AO7: =SUMIFS(RosterPlan25[[VAR/G]:[VAR/G]],RosterPlan25[[OWNER]:[OWNER]],"="&$AF7,RosterPlan25[[KEEPER / RFA]:[KEEPER / RFA]],"RFA",RosterPlan25[[VAR/G]:[VAR/G]],">0") -> 0 | AP7: =SUMIFS(RosterPlan25[[VAR/G]:[VAR/G]],RosterPlan25[[OWNER]:[OWNER]],"="&$AF7,RosterPlan25[[KEEPER / RFA]:[KEEPER / RFA]],"<>K",RosterPlan25[[VAR/G]:[VAR/G]],">0") -> 0 | AQ7: =(300-AM7)/IF(VARG="ATHLETIC",$AH$35,IF(VARG="GOOD",$AG$35,0)) -> 8.5810016 | AR7: =AN7+AQ7+AO7 -> 17.473009 | AS7: 22.682308 | AT7: =AR7-AS7 -> -5.2092983 | AU7: =AR7/$AR$12 -> 0.074648104
A8: 12484 | B8: BobbyBaby | C8: Jayden Higgins | D8: =_xlfn.IFNA(MATCH(RosterPlan25[[#This Row],[player_id]],CompositeRoster[sleeper_id],0), MATCH(RosterPlan25[[#This Row],[PLAYER]],CompositeRoster[full_name],0)) -> 7 | E8: =MATCH(RosterPlan25[[#This Row],[player_id]],Draft2025[sleeper_id],0) -> 21 | F8: =INDEX(CompositeRoster[team],RosterPlan25[[#This Row],[RosterIndex]])&"" -> HOU | G8: =INDEX(CompositeRoster[position],RosterPlan25[[#This Row],[RosterIndex]])&"" -> WR | H8: =INDEX(CompositeRoster[source],RosterPlan25[[#This Row],[RosterIndex]]) -> Roster | I8: =_xlfn.IFNA(INDEX(Draft2025[PRICE],RosterPlan25[[#This Row],[DraftIndex]]),0) -> 4 | J8: =IF(RosterPlan25[[#This Row],[SOURCE]]="Rookie","Rookie",_xlfn.IFNA(INDEX(Draft2025[Current Contract],RosterPlan25[[#This Row],[DraftIndex]]),"Undrafted")) -> Rookie | K8: {=IF(OR(ISBLANK(RosterPlan25[[#This Row],[player_id]]),NOT(ISNA(MATCH(RosterPlan25[[#This Row],[player_id]],INDIRECT("Rookies" & SEASON &"[player_id]"),0)))), SEASON, _xlfn.IFNA(INDEX(Draft2025[Contract Year],RosterPlan25[[#This Row],[DraftIndex]]),IF(IN_SEASON,SEASON,SEASON-1)))} -> 2025 | L8: =IF(_xlfn.IFNA(INDEX(Draft2025[KEEPER],RosterPlan25[[#This Row],[DraftIndex]]),"")="K","Yes","") | M8: {=IF(RosterPlan25[[#This Row],[Contract]]="Rookie", "", IF(_xlfn.IFNA(INDEX(Draft2025[Contract Year],RosterPlan25[[#This Row],[DraftIndex]]),IF(IN_SEASON,SEASON,SEASON-1))+3<SEASON, SEASON, _xlfn.IFNA(INDEX(Draft2025[Contract Year],RosterPlan25[[#This Row],[DraftIndex]]),IF(IN_SEASON,SEASON,SEASON-1))+3))} | N8: =ROUNDDOWN(RosterPlan25[[#This Row],[Optimal $]]*IF(RosterPlan25[[#This Row],[Contract]]="Rookie",0.3,0.15),0) -> 0 | O8: =IF(RosterPlan25[[#This Row],[SOURCE]]="Rookie", INDEX(INDIRECT("Rookies" & SEASON & "[salary]"),MATCH(RosterPlan25[[#This Row],[PLAYER]],INDIRECT("Rookies"& SEASON & "[full_name]"),0)), MAX(RosterPlan25[[#This Row],[$ PREV]] + IF(RAISES_ENABLED,RosterPlan25[[#This Row],[$↑ VAR]],0),1)) -> 4 | P8: =IF(VARG="MANUAL",RosterPlan25[[#This Row],[ManualVARG]],IF(VARG="GOOD",RosterPlan25[[#This Row],[GoodVARG]],"ERR")) -> -1.2890294 | Q8: =_xlfn.IFNA(IF(RosterPlan25[[#This Row],[POS]]="K",0,INDEX(GoodSheets[MG VARG],MATCH(TEXT(RosterPlan25[[#This Row],[player_id]],"0"),GoodSheets[sleeper_id],0))), IF(RosterPlan25[[#This Row],[POS]]="QB",-12,IF(RosterPlan25[[#This Row],[POS]]="RB",-8,IF(RosterPlan25[[#This Row],[POS]]="WR",-8,-5)))) -> -1.2890294 | R8: =_xlfn.IFNA(INDEX(ALL_Athletic[VARG], MATCH(RosterPlan25[[#This Row],[player_id]],ALL_Athletic[SleeperID],0)), IF(RosterPlan25[[#This Row],[POS]]="QB",-12,IF(RosterPlan25[[#This Row],[POS]]="RB",-8,IF(RosterPlan25[[#This Row],[POS]]="WR",-8,-5)))) -> -8 | S8: K | T8: =_xlfn.IFNA(INDEX(Draft2025[Net Keeper Count],RosterPlan25[[#This Row],[DraftIndex]]),0)+IF(RosterPlan25[[#This Row],[KEEPER / RFA]]="K",1,0) -> 1 | U8: =IF(RosterPlan25[[#This Row],[KEEPER / RFA]]="RFA",RosterPlan25[[#This Row],[Pure Inflated $]],"") | V8: =IF(RosterPlan25[[#This Row],[VAR/G]]>0, ROUND(IF(VARG="GOOD",$AG$29,IF(VARG="ATHLETIC",$AH$29,99999999999))*RosterPlan25[[#This Row],[VAR/G]],0), 0) + 1 -> 1 | W8: =RosterPlan25[[#This Row],[Optimal $]]-RosterPlan25[[#This Row],[$ CURR]] -> -3 | X8: =IF(OR(RosterPlan25[[#This Row],[SOURCE]]="Rookie",RosterPlan25[[#This Row],[POS]]="K"),0,RosterPlan25[[#This Row],[VAR/G]]+3.3) -> 2.0109706 | Y8: =IF(RosterPlan25[[#This Row],[VAW/G]]>0,ROUND(RosterPlan25[[#This Row],[VAW/G]]*$AG$56,0)+1,1) -> 34 | Z8: =RosterPlan25[[#This Row],[VAWG Market $]]-_xlfn.IFNA(RosterPlan25[[#This Row],[$ CURR]],1) -> 30 | AA8: =IF(RosterPlan25[[#This Row],[VAR/G]]>0,1+ROUND(RosterPlan25[[#This Row],[VAR/G]]*IF(RosterPlan25[[#This Row],[KEEPER / RFA]]="K",($AG$34+RosterPlan25[[#This Row],[$ CURR]]-1)/($AG$23+RosterPlan25[[#This Row],[VAR/G]]),$AG$35),0),1) -> 1 | AB8: =RosterPlan25[[#This Row],[Pure Inflated $]]-RosterPlan25[[#This Row],[$ CURR]] -> -3 | AC8: =INDEX(players[age],MATCH(RosterPlan25[[#This Row],[player_id]],players[sleeper_id],0)) -> 23 | AE8: =300-AG8+AI8+$AE$15-24-AL8 -> 9 | AF8: joe9alt | AG8: =SUMIFS(RosterPlan25[[$ CURR]:[$ CURR]],RosterPlan25[[OWNER]:[OWNER]],"="&$AF8,RosterPlan25[[KEEPER / RFA]:[KEEPER / RFA]],"K") -> 298 | AH8: =SUMIFS(RosterPlan25[[$ CURR]:[$ CURR]],RosterPlan25[[OWNER]:[OWNER]],"="&$AF8,RosterPlan25[[KEEPER / RFA]:[KEEPER / RFA]],"K")+ SUMIFS(RosterPlan25[[RFA $]:[RFA $]],RosterPlan25[[OWNER]:[OWNER]],"="&$AF8,RosterPlan25[[KEEPER / RFA]:[KEEPER / RFA]],"RFA") -> 298 | AI8: =COUNTIFS(RosterPlan25[OWNER],"="&$AF8) -> 23 | AJ8: =COUNTIFS(RosterPlan25[OWNER],"="&$AF8,RosterPlan25[KEEPER / RFA],"K") -> 23 | AK8: =COUNTIFS(RosterPlan25[OWNER],"="&$AF8,RosterPlan25[KEEPER / RFA],"RFA") -> 0 | AM8: =AH8+24+AL8-MIN(AJ8+AK8,24) -> 299 | AN8: =SUMIFS(RosterPlan25[[VAR/G]:[VAR/G]],RosterPlan25[[OWNER]:[OWNER]],"="&$AF8,RosterPlan25[[KEEPER / RFA]:[KEEPER / RFA]],"K",RosterPlan25[[VAR/G]:[VAR/G]],">0") -> 22.779436 | AO8: =SUMIFS(RosterPlan25[[VAR/G]:[VAR/G]],RosterPlan25[[OWNER]:[OWNER]],"="&$AF8,RosterPlan25[[KEEPER / RFA]:[KEEPER / RFA]],"RFA",RosterPlan25[[VAR/G]:[VAR/G]],">0") -> 0 | AP8: =SUMIFS(RosterPlan25[[VAR/G]:[VAR/G]],RosterPlan25[[OWNER]:[OWNER]],"="&$AF8,RosterPlan25[[KEEPER / RFA]:[KEEPER / RFA]],"<>K",RosterPlan25[[VAR/G]:[VAR/G]],">0") -> 0 | AQ8: =(300-AM8)/IF(VARG="ATHLETIC",$AH$35,IF(VARG="GOOD",$AG$35,0)) -> 0.060858167 | AR8: =AN8+AQ8+AO8 -> 22.840294 | AS8: 20.371079 | AT8: =AR8-AS8 -> 2.4692148 | AU8: =AR8/$AR$12 -> 0.09757819
A9: 9504 | B9: BobbyBaby | C9: Kayshon Boutte | D9: =_xlfn.IFNA(MATCH(RosterPlan25[[#This Row],[player_id]],CompositeRoster[sleeper_id],0), MATCH(RosterPlan25[[#This Row],[PLAYER]],CompositeRoster[full_name],0)) -> 8 | E9: =MATCH(RosterPlan25[[#This Row],[player_id]],Draft2025[sleeper_id],0) -> #N/A | F9: =INDEX(CompositeRoster[team],RosterPlan25[[#This Row],[RosterIndex]])&"" -> NE | G9: =INDEX(CompositeRoster[position],RosterPlan25[[#This Row],[RosterIndex]])&"" -> WR | H9: =INDEX(CompositeRoster[source],RosterPlan25[[#This Row],[RosterIndex]]) -> Roster | I9: =_xlfn.IFNA(INDEX(Draft2025[PRICE],RosterPlan25[[#This Row],[DraftIndex]]),0) -> 0 | J9: =IF(RosterPlan25[[#This Row],[SOURCE]]="Rookie","Rookie",_xlfn.IFNA(INDEX(Draft2025[Current Contract],RosterPlan25[[#This Row],[DraftIndex]]),"Undrafted")) -> Undrafted | K9: {=IF(OR(ISBLANK(RosterPlan25[[#This Row],[player_id]]),NOT(ISNA(MATCH(RosterPlan25[[#This Row],[player_id]],INDIRECT("Rookies" & SEASON &"[player_id]"),0)))), SEASON, _xlfn.IFNA(INDEX(Draft2025[Contract Year],RosterPlan25[[#This Row],[DraftIndex]]),IF(IN_SEASON,SEASON,SEASON-1)))} -> 2025 | L9: =IF(_xlfn.IFNA(INDEX(Draft2025[KEEPER],RosterPlan25[[#This Row],[DraftIndex]]),"")="K","Yes","") | M9: {=IF(RosterPlan25[[#This Row],[Contract]]="Rookie", "", IF(_xlfn.IFNA(INDEX(Draft2025[Contract Year],RosterPlan25[[#This Row],[DraftIndex]]),IF(IN_SEASON,SEASON,SEASON-1))+3<SEASON, SEASON, _xlfn.IFNA(INDEX(Draft2025[Contract Year],RosterPlan25[[#This Row],[DraftIndex]]),IF(IN_SEASON,SEASON,SEASON-1))+3))} -> 2028 | N9: =ROUNDDOWN(RosterPlan25[[#This Row],[Optimal $]]*IF(RosterPlan25[[#This Row],[Contract]]="Rookie",0.3,0.15),0) -> 0 | O9: =IF(RosterPlan25[[#This Row],[SOURCE]]="Rookie", INDEX(INDIRECT("Rookies" & SEASON & "[salary]"),MATCH(RosterPlan25[[#This Row],[PLAYER]],INDIRECT("Rookies"& SEASON & "[full_name]"),0)), MAX(RosterPlan25[[#This Row],[$ PREV]] + IF(RAISES_ENABLED,RosterPlan25[[#This Row],[$↑ VAR]],0),1)) -> 1 | P9: =IF(VARG="MANUAL",RosterPlan25[[#This Row],[ManualVARG]],IF(VARG="GOOD",RosterPlan25[[#This Row],[GoodVARG]],"ERR")) -> -3.119594 | Q9: =_xlfn.IFNA(IF(RosterPlan25[[#This Row],[POS]]="K",0,INDEX(GoodSheets[MG VARG],MATCH(TEXT(RosterPlan25[[#This Row],[player_id]],"0"),GoodSheets[sleeper_id],0))), IF(RosterPlan25[[#This Row],[POS]]="QB",-12,IF(RosterPlan25[[#This Row],[POS]]="RB",-8,IF(RosterPlan25[[#This Row],[POS]]="WR",-8,-5)))) -> -3.119594 | R9: =_xlfn.IFNA(INDEX(ALL_Athletic[VARG], MATCH(RosterPlan25[[#This Row],[player_id]],ALL_Athletic[SleeperID],0)), IF(RosterPlan25[[#This Row],[POS]]="QB",-12,IF(RosterPlan25[[#This Row],[POS]]="RB",-8,IF(RosterPlan25[[#This Row],[POS]]="WR",-8,-5)))) -> -3.5875303 | S9: K | T9: =_xlfn.IFNA(INDEX(Draft2025[Net Keeper Count],RosterPlan25[[#This Row],[DraftIndex]]),0)+IF(RosterPlan25[[#This Row],[KEEPER / RFA]]="K",1,0) -> 1 | U9: =IF(RosterPlan25[[#This Row],[KEEPER / RFA]]="RFA",RosterPlan25[[#This Row],[Pure Inflated $]],"") | V9: =IF(RosterPlan25[[#This Row],[VAR/G]]>0, ROUND(IF(VARG="GOOD",$AG$29,IF(VARG="ATHLETIC",$AH$29,99999999999))*RosterPlan25[[#This Row],[VAR/G]],0), 0) + 1 -> 1 | W9: =RosterPlan25[[#This Row],[Optimal $]]-RosterPlan25[[#This Row],[$ CURR]] -> 0 | X9: =IF(OR(RosterPlan25[[#This Row],[SOURCE]]="Rookie",RosterPlan25[[#This Row],[POS]]="K"),0,RosterPlan25[[#This Row],[VAR/G]]+3.3) -> 0.18040604 | Y9: =IF(RosterPlan25[[#This Row],[VAW/G]]>0,ROUND(RosterPlan25[[#This Row],[VAW/G]]*$AG$56,0)+1,1) -> 4 | Z9: =RosterPlan25[[#This Row],[VAWG Market $]]-_xlfn.IFNA(RosterPlan25[[#This Row],[$ CURR]],1) -> 3 | AA9: =IF(RosterPlan25[[#This Row],[VAR/G]]>0,1+ROUND(RosterPlan25[[#This Row],[VAR/G]]*IF(RosterPlan25[[#This Row],[KEEPER / RFA]]="K",($AG$34+RosterPlan25[[#This Row],[$ CURR]]-1)/($AG$23+RosterPlan25[[#This Row],[VAR/G]]),$AG$35),0),1) -> 1 | AB9: =RosterPlan25[[#This Row],[Pure Inflated $]]-RosterPlan25[[#This Row],[$ CURR]] -> 0 | AC9: =INDEX(players[age],MATCH(RosterPlan25[[#This Row],[player_id]],players[sleeper_id],0)) -> 24 | AE9: =300-AG9+AI9+$AE$15-24-AL9 -> 148 | AF9: Jonnymaxed | AG9: =SUMIFS(RosterPlan25[[$ CURR]:[$ CURR]],RosterPlan25[[OWNER]:[OWNER]],"="&$AF9,RosterPlan25[[KEEPER / RFA]:[KEEPER / RFA]],"K") -> 156 | AH9: =SUMIFS(RosterPlan25[[$ CURR]:[$ CURR]],RosterPlan25[[OWNER]:[OWNER]],"="&$AF9,RosterPlan25[[KEEPER / RFA]:[KEEPER / RFA]],"K")+ SUMIFS(RosterPlan25[[RFA $]:[RFA $]],RosterPlan25[[OWNER]:[OWNER]],"="&$AF9,RosterPlan25[[KEEPER / RFA]:[KEEPER / RFA]],"RFA") -> 156 | AI9: =COUNTIFS(RosterPlan25[OWNER],"="&$AF9) -> 20 | AJ9: =COUNTIFS(RosterPlan25[OWNER],"="&$AF9,RosterPlan25[KEEPER / RFA],"K") -> 20 | AK9: =COUNTIFS(RosterPlan25[OWNER],"="&$AF9,RosterPlan25[KEEPER / RFA],"RFA") -> 0 | AM9: =AH9+24+AL9-MIN(AJ9+AK9,24) -> 160 | AN9: =SUMIFS(RosterPlan25[[VAR/G]:[VAR/G]],RosterPlan25[[OWNER]:[OWNER]],"="&$AF9,RosterPlan25[[KEEPER / RFA]:[KEEPER / RFA]],"K",RosterPlan25[[VAR/G]:[VAR/G]],">0") -> 14.775296 | AO9: =SUMIFS(RosterPlan25[[VAR/G]:[VAR/G]],RosterPlan25[[OWNER]:[OWNER]],"="&$AF9,RosterPlan25[[KEEPER / RFA]:[KEEPER / RFA]],"RFA",RosterPlan25[[VAR/G]:[VAR/G]],">0") -> 0 | AP9: =SUMIFS(RosterPlan25[[VAR/G]:[VAR/G]],RosterPlan25[[OWNER]:[OWNER]],"="&$AF9,RosterPlan25[[KEEPER / RFA]:[KEEPER / RFA]],"<>K",RosterPlan25[[VAR/G]:[VAR/G]],">0") -> 0 | AQ9: =(300-AM9)/IF(VARG="ATHLETIC",$AH$35,IF(VARG="GOOD",$AG$35,0)) -> 8.5201434 | AR9: =AN9+AQ9+AO9 -> 23.295439 | AS9: 23.789647 | AT9: =AR9-AS9 -> -0.49420802 | AU9: =AR9/$AR$12 -> 0.099522661
A10: 8151 | B10: BobbyBaby | C10: Kenneth Walker | D10: =_xlfn.IFNA(MATCH(RosterPlan25[[#This Row],[player_id]],CompositeRoster[sleeper_id],0), MATCH(RosterPlan25[[#This Row],[PLAYER]],CompositeRoster[full_name],0)) -> 9 | E10: =MATCH(RosterPlan25[[#This Row],[player_id]],Draft2025[sleeper_id],0) -> 12 | F10: =INDEX(CompositeRoster[team],RosterPlan25[[#This Row],[RosterIndex]])&"" -> KC | G10: =INDEX(CompositeRoster[position],RosterPlan25[[#This Row],[RosterIndex]])&"" -> RB | H10: =INDEX(CompositeRoster[source],RosterPlan25[[#This Row],[RosterIndex]]) -> Roster | I10: =_xlfn.IFNA(INDEX(Draft2025[PRICE],RosterPlan25[[#This Row],[DraftIndex]]),0) -> 39 | J10: =IF(RosterPlan25[[#This Row],[SOURCE]]="Rookie","Rookie",_xlfn.IFNA(INDEX(Draft2025[Current Contract],RosterPlan25[[#This Row],[DraftIndex]]),"Undrafted")) -> Rookie | K10: {=IF(OR(ISBLANK(RosterPlan25[[#This Row],[player_id]]),NOT(ISNA(MATCH(RosterPlan25[[#This Row],[player_id]],INDIRECT("Rookies" & SEASON &"[player_id]"),0)))), SEASON, _xlfn.IFNA(INDEX(Draft2025[Contract Year],RosterPlan25[[#This Row],[DraftIndex]]),IF(IN_SEASON,SEASON,SEASON-1)))} -> 2022 | L10: =IF(_xlfn.IFNA(INDEX(Draft2025[KEEPER],RosterPlan25[[#This Row],[DraftIndex]]),"")="K","Yes","") -> Yes | M10: {=IF(RosterPlan25[[#This Row],[Contract]]="Rookie", "", IF(_xlfn.IFNA(INDEX(Draft2025[Contract Year],RosterPlan25[[#This Row],[DraftIndex]]),IF(IN_SEASON,SEASON,SEASON-1))+3<SEASON, SEASON, _xlfn.IFNA(INDEX(Draft2025[Contract Year],RosterPlan25[[#This Row],[DraftIndex]]),IF(IN_SEASON,SEASON,SEASON-1))+3))} | N10: =ROUNDDOWN(RosterPlan25[[#This Row],[Optimal $]]*IF(RosterPlan25[[#This Row],[Contract]]="Rookie",0.3,0.15),0) -> 15 | O10: =IF(RosterPlan25[[#This Row],[SOURCE]]="Rookie", INDEX(INDIRECT("Rookies" & SEASON & "[salary]"),MATCH(RosterPlan25[[#This Row],[PLAYER]],INDIRECT("Rookies"& SEASON & "[full_name]"),0)), MAX(RosterPlan25[[#This Row],[$ PREV]] + IF(RAISES_ENABLED,RosterPlan25[[#This Row],[$↑ VAR]],0),1)) -> 54 | P10: =IF(VARG="MANUAL",RosterPlan25[[#This Row],[ManualVARG]],IF(VARG="GOOD",RosterPlan25[[#This Row],[GoodVARG]],"ERR")) -> 4.2886031 | Q10: =_xlfn.IFNA(IF(RosterPlan25[[#This Row],[POS]]="K",0,INDEX(GoodSheets[MG VARG],MATCH(TEXT(RosterPlan25[[#This Row],[player_id]],"0"),GoodSheets[sleeper_id],0))), IF(RosterPlan25[[#This Row],[POS]]="QB",-12,IF(RosterPlan25[[#This Row],[POS]]="RB",-8,IF(RosterPlan25[[#This Row],[POS]]="WR",-8,-5)))) -> 4.2886031 | R10: =_xlfn.IFNA(INDEX(ALL_Athletic[VARG], MATCH(RosterPlan25[[#This Row],[player_id]],ALL_Athletic[SleeperID],0)), IF(RosterPlan25[[#This Row],[POS]]="QB",-12,IF(RosterPlan25[[#This Row],[POS]]="RB",-8,IF(RosterPlan25[[#This Row],[POS]]="WR",-8,-5)))) -> -8 | S10: K | T10: =_xlfn.IFNA(INDEX(Draft2025[Net Keeper Count],RosterPlan25[[#This Row],[DraftIndex]]),0)+IF(RosterPlan25[[#This Row],[KEEPER / RFA]]="K",1,0) -> 4 | U10: =IF(RosterPlan25[[#This Row],[KEEPER / RFA]]="RFA",RosterPlan25[[#This Row],[Pure Inflated $]],"") | V10: =IF(RosterPlan25[[#This Row],[VAR/G]]>0, ROUND(IF(VARG="GOOD",$AG$29,IF(VARG="ATHLETIC",$AH$29,99999999999))*RosterPlan25[[#This Row],[VAR/G]],0), 0) + 1 -> 52 | W10: =RosterPlan25[[#This Row],[Optimal $]]-RosterPlan25[[#This Row],[$ CURR]] -> -2 | X10: =IF(OR(RosterPlan25[[#This Row],[SOURCE]]="Rookie",RosterPlan25[[#This Row],[POS]]="K"),0,RosterPlan25[[#This Row],[VAR/G]]+3.3) -> 7.5886031 | Y10: =IF(RosterPlan25[[#This Row],[VAW/G]]>0,ROUND(RosterPlan25[[#This Row],[VAW/G]]*$AG$56,0)+1,1) -> 126 | Z10: =RosterPlan25[[#This Row],[VAWG Market $]]-_xlfn.IFNA(RosterPlan25[[#This Row],[$ CURR]],1) -> 72 | AA10: =IF(RosterPlan25[[#This Row],[VAR/G]]>0,1+ROUND(RosterPlan25[[#This Row],[VAR/G]]*IF(RosterPlan25[[#This Row],[KEEPER / RFA]]="K",($AG$34+RosterPlan25[[#This Row],[$ CURR]]-1)/($AG$23+RosterPlan25[[#This Row],[VAR/G]]),$AG$35),0),1) -> 70 | AB10: =RosterPlan25[[#This Row],[Pure Inflated $]]-RosterPlan25[[#This Row],[$ CURR]] -> 16 | AC10: =INDEX(players[age],MATCH(RosterPlan25[[#This Row],[player_id]],players[sleeper_id],0)) -> 25 | AE10: =300-AG10+AI10+$AE$15-24-AL10 -> 8 | AF10: zombull | AG10: =SUMIFS(RosterPlan25[[$ CURR]:[$ CURR]],RosterPlan25[[OWNER]:[OWNER]],"="&$AF10,RosterPlan25[[KEEPER / RFA]:[KEEPER / RFA]],"K") -> 297 | AH10: =SUMIFS(RosterPlan25[[$ CURR]:[$ CURR]],RosterPlan25[[OWNER]:[OWNER]],"="&$AF10,RosterPlan25[[KEEPER / RFA]:[KEEPER / RFA]],"K")+ SUMIFS(RosterPlan25[[RFA $]:[RFA $]],RosterPlan25[[OWNER]:[OWNER]],"="&$AF10,RosterPlan25[[KEEPER / RFA]:[KEEPER / RFA]],"RFA") -> 297 | AI10: =COUNTIFS(RosterPlan25[OWNER],"="&$AF10) -> 21 | AJ10: =COUNTIFS(RosterPlan25[OWNER],"="&$AF10,RosterPlan25[KEEPER / RFA],"K") -> 21 | AK10: =COUNTIFS(RosterPlan25[OWNER],"="&$AF10,RosterPlan25[KEEPER / RFA],"RFA") -> 0 | AM10: =AH10+24+AL10-MIN(AJ10+AK10,24) -> 300 | AN10: =SUMIFS(RosterPlan25[[VAR/G]:[VAR/G]],RosterPlan25[[OWNER]:[OWNER]],"="&$AF10,RosterPlan25[[KEEPER / RFA]:[KEEPER / RFA]],"K",RosterPlan25[[VAR/G]:[VAR/G]],">0") -> 27.458358 | AO10: =SUMIFS(RosterPlan25[[VAR/G]:[VAR/G]],RosterPlan25[[OWNER]:[OWNER]],"="&$AF10,RosterPlan25[[KEEPER / RFA]:[KEEPER / RFA]],"RFA",RosterPlan25[[VAR/G]:[VAR/G]],">0") -> 0 | AP10: =SUMIFS(RosterPlan25[[VAR/G]:[VAR/G]],RosterPlan25[[OWNER]:[OWNER]],"="&$AF10,RosterPlan25[[KEEPER / RFA]:[KEEPER / RFA]],"<>K",RosterPlan25[[VAR/G]:[VAR/G]],">0") -> 0 | AQ10: =(300-AM10)/IF(VARG="ATHLETIC",$AH$35,IF(VARG="GOOD",$AG$35,0)) -> 0 | AR10: =AN10+AQ10+AO10 -> 27.458358 | AS10: 22.437788 | AT10: =AR10-AS10 -> 5.0205691 | AU10: =AR10/$AR$12 -> 0.11730746
A11: 1166 | B11: BobbyBaby | C11: Kirk Cousins | D11: =_xlfn.IFNA(MATCH(RosterPlan25[[#This Row],[player_id]],CompositeRoster[sleeper_id],0), MATCH(RosterPlan25[[#This Row],[PLAYER]],CompositeRoster[full_name],0)) -> 10 | E11: =MATCH(RosterPlan25[[#This Row],[player_id]],Draft2025[sleeper_id],0) -> #N/A | F11: =INDEX(CompositeRoster[team],RosterPlan25[[#This Row],[RosterIndex]])&"" -> LV | G11: =INDEX(CompositeRoster[position],RosterPlan25[[#This Row],[RosterIndex]])&"" -> QB | H11: =INDEX(CompositeRoster[source],RosterPlan25[[#This Row],[RosterIndex]]) -> Roster | I11: =_xlfn.IFNA(INDEX(Draft2025[PRICE],RosterPlan25[[#This Row],[DraftIndex]]),0) -> 0 | J11: =IF(RosterPlan25[[#This Row],[SOURCE]]="Rookie","Rookie",_xlfn.IFNA(INDEX(Draft2025[Current Contract],RosterPlan25[[#This Row],[DraftIndex]]),"Undrafted")) -> Undrafted | K11: {=IF(OR(ISBLANK(RosterPlan25[[#This Row],[player_id]]),NOT(ISNA(MATCH(RosterPlan25[[#This Row],[player_id]],INDIRECT("Rookies" & SEASON &"[player_id]"),0)))), SEASON, _xlfn.IFNA(INDEX(Draft2025[Contract Year],RosterPlan25[[#This Row],[DraftIndex]]),IF(IN_SEASON,SEASON,SEASON-1)))} -> 2025 | L11: =IF(_xlfn.IFNA(INDEX(Draft2025[KEEPER],RosterPlan25[[#This Row],[DraftIndex]]),"")="K","Yes","") | M11: {=IF(RosterPlan25[[#This Row],[Contract]]="Rookie", "", IF(_xlfn.IFNA(INDEX(Draft2025[Contract Year],RosterPlan25[[#This Row],[DraftIndex]]),IF(IN_SEASON,SEASON,SEASON-1))+3<SEASON, SEASON, _xlfn.IFNA(INDEX(Draft2025[Contract Year],RosterPlan25[[#This Row],[DraftIndex]]),IF(IN_SEASON,SEASON,SEASON-1))+3))} -> 2028 | N11: =ROUNDDOWN(RosterPlan25[[#This Row],[Optimal $]]*IF(RosterPlan25[[#This Row],[Contract]]="Rookie",0.3,0.15),0) -> 0 | O11: =IF(RosterPlan25[[#This Row],[SOURCE]]="Rookie", INDEX(INDIRECT("Rookies" & SEASON & "[salary]"),MATCH(RosterPlan25[[#This Row],[PLAYER]],INDIRECT("Rookies"& SEASON & "[full_name]"),0)), MAX(RosterPlan25[[#This Row],[$ PREV]] + IF(RAISES_ENABLED,RosterPlan25[[#This Row],[$↑ VAR]],0),1)) -> 1 | P11: =IF(VARG="MANUAL",RosterPlan25[[#This Row],[ManualVARG]],IF(VARG="GOOD",RosterPlan25[[#This Row],[GoodVARG]],"ERR")) -> -13.74038 | Q11: =_xlfn.IFNA(IF(RosterPlan25[[#This Row],[POS]]="K",0,INDEX(GoodSheets[MG VARG],MATCH(TEXT(RosterPlan25[[#This Row],[player_id]],"0"),GoodSheets[sleeper_id],0))), IF(RosterPlan25[[#This Row],[POS]]="QB",-12,IF(RosterPlan25[[#This Row],[POS]]="RB",-8,IF(RosterPlan25[[#This Row],[POS]]="WR",-8,-5)))) -> -13.74038 | R11: =_xlfn.IFNA(INDEX(ALL_Athletic[VARG], MATCH(RosterPlan25[[#This Row],[player_id]],ALL_Athletic[SleeperID],0)), IF(RosterPlan25[[#This Row],[POS]]="QB",-12,IF(RosterPlan25[[#This Row],[POS]]="RB",-8,IF(RosterPlan25[[#This Row],[POS]]="WR",-8,-5)))) -> 0.61542635 | S11: K | T11: =_xlfn.IFNA(INDEX(Draft2025[Net Keeper Count],RosterPlan25[[#This Row],[DraftIndex]]),0)+IF(RosterPlan25[[#This Row],[KEEPER / RFA]]="K",1,0) -> 1 | U11: =IF(RosterPlan25[[#This Row],[KEEPER / RFA]]="RFA",RosterPlan25[[#This Row],[Pure Inflated $]],"") | V11: =IF(RosterPlan25[[#This Row],[VAR/G]]>0, ROUND(IF(VARG="GOOD",$AG$29,IF(VARG="ATHLETIC",$AH$29,99999999999))*RosterPlan25[[#This Row],[VAR/G]],0), 0) + 1 -> 1 | W11: =RosterPlan25[[#This Row],[Optimal $]]-RosterPlan25[[#This Row],[$ CURR]] -> 0 | X11: =IF(OR(RosterPlan25[[#This Row],[SOURCE]]="Rookie",RosterPlan25[[#This Row],[POS]]="K"),0,RosterPlan25[[#This Row],[VAR/G]]+3.3) -> -10.44038 | Y11: =IF(RosterPlan25[[#This Row],[VAW/G]]>0,ROUND(RosterPlan25[[#This Row],[VAW/G]]*$AG$56,0)+1,1) -> 1 | Z11: =RosterPlan25[[#This Row],[VAWG Market $]]-_xlfn.IFNA(RosterPlan25[[#This Row],[$ CURR]],1) -> 0 | AA11: =IF(RosterPlan25[[#This Row],[VAR/G]]>0,1+ROUND(RosterPlan25[[#This Row],[VAR/G]]*IF(RosterPlan25[[#This Row],[KEEPER / RFA]]="K",($AG$34+RosterPlan25[[#This Row],[$ CURR]]-1)/($AG$23+RosterPlan25[[#This Row],[VAR/G]]),$AG$35),0),1) -> 1 | AB11: =RosterPlan25[[#This Row],[Pure Inflated $]]-RosterPlan25[[#This Row],[$ CURR]] -> 0 | AC11: =INDEX(players[age],MATCH(RosterPlan25[[#This Row],[player_id]],players[sleeper_id],0)) -> 37 | AE11: =300-AG11+AI11+$AE$15-24-AL11 -> 75 | AF11: docopp | AG11: =SUMIFS(RosterPlan25[[$ CURR]:[$ CURR]],RosterPlan25[[OWNER]:[OWNER]],"="&$AF11,RosterPlan25[[KEEPER / RFA]:[KEEPER / RFA]],"K") -> 227 | AH11: =SUMIFS(RosterPlan25[[$ CURR]:[$ CURR]],RosterPlan25[[OWNER]:[OWNER]],"="&$AF11,RosterPlan25[[KEEPER / RFA]:[KEEPER / RFA]],"K")+ SUMIFS(RosterPlan25[[RFA $]:[RFA $]],RosterPlan25[[OWNER]:[OWNER]],"="&$AF11,RosterPlan25[[KEEPER / RFA]:[KEEPER / RFA]],"RFA") -> 227 | AI11: =COUNTIFS(RosterPlan25[OWNER],"="&$AF11) -> 20 | AJ11: =COUNTIFS(RosterPlan25[OWNER],"="&$AF11,RosterPlan25[KEEPER / RFA],"K") -> 20 | AK11: =COUNTIFS(RosterPlan25[OWNER],"="&$AF11,RosterPlan25[KEEPER / RFA],"RFA") -> 0 | AL11: 2 | AM11: =AH11+24-MIN(AJ11+AK11,24) -> 231 | AN11: =SUMIFS(RosterPlan25[[VAR/G]:[VAR/G]],RosterPlan25[[OWNER]:[OWNER]],"="&$AF11,RosterPlan25[[KEEPER / RFA]:[KEEPER / RFA]],"K",RosterPlan25[[VAR/G]:[VAR/G]],">0") -> 24.906462 | AO11: =SUMIFS(RosterPlan25[[VAR/G]:[VAR/G]],RosterPlan25[[OWNER]:[OWNER]],"="&$AF11,RosterPlan25[[KEEPER / RFA]:[KEEPER / RFA]],"RFA",RosterPlan25[[VAR/G]:[VAR/G]],">0") -> 0 | AP11: =SUMIFS(RosterPlan25[[VAR/G]:[VAR/G]],RosterPlan25[[OWNER]:[OWNER]],"="&$AF11,RosterPlan25[[KEEPER / RFA]:[KEEPER / RFA]],"<>K",RosterPlan25[[VAR/G]:[VAR/G]],">0") -> 0 | AQ11: =(300-AM11)/IF(VARG="ATHLETIC",$AH$35,IF(VARG="GOOD",$AG$35,0)) -> 4.1992135 | AR11: =AN11+AQ11+AO11 -> 29.105675 | AS11: 15.203291 | AT11: =AR11-AS11 -> 13.902384 | AU11: =AR11/$AR$12 -> 0.12434512
A12: 12489 | B12: BobbyBaby | C12: RJ Harvey | D12: =_xlfn.IFNA(MATCH(RosterPlan25[[#This Row],[player_id]],CompositeRoster[sleeper_id],0), MATCH(RosterPlan25[[#This Row],[PLAYER]],CompositeRoster[full_name],0)) -> 11 | E12: =MATCH(RosterPlan25[[#This Row],[player_id]],Draft2025[sleeper_id],0) -> 22 | F12: =INDEX(CompositeRoster[team],RosterPlan25[[#This Row],[RosterIndex]])&"" -> DEN | G12: =INDEX(CompositeRoster[position],RosterPlan25[[#This Row],[RosterIndex]])&"" -> RB | H12: =INDEX(CompositeRoster[source],RosterPlan25[[#This Row],[RosterIndex]]) -> Roster | I12: =_xlfn.IFNA(INDEX(Draft2025[PRICE],RosterPlan25[[#This Row],[DraftIndex]]),0) -> 5 | J12: =IF(RosterPlan25[[#This Row],[SOURCE]]="Rookie","Rookie",_xlfn.IFNA(INDEX(Draft2025[Current Contract],RosterPlan25[[#This Row],[DraftIndex]]),"Undrafted")) -> Rookie | K12: {=IF(OR(ISBLANK(RosterPlan25[[#This Row],[player_id]]),NOT(ISNA(MATCH(RosterPlan25[[#This Row],[player_id]],INDIRECT("Rookies" & SEASON &"[player_id]"),0)))), SEASON, _xlfn.IFNA(INDEX(Draft2025[Contract Year],RosterPlan25[[#This Row],[DraftIndex]]),IF(IN_SEASON,SEASON,SEASON-1)))} -> 2025 | L12: =IF(_xlfn.IFNA(INDEX(Draft2025[KEEPER],RosterPlan25[[#This Row],[DraftIndex]]),"")="K","Yes","") | M12: {=IF(RosterPlan25[[#This Row],[Contract]]="Rookie", "", IF(_xlfn.IFNA(INDEX(Draft2025[Contract Year],RosterPlan25[[#This Row],[DraftIndex]]),IF(IN_SEASON,SEASON,SEASON-1))+3<SEASON, SEASON, _xlfn.IFNA(INDEX(Draft2025[Contract Year],RosterPlan25[[#This Row],[DraftIndex]]),IF(IN_SEASON,SEASON,SEASON-1))+3))} | N12: =ROUNDDOWN(RosterPlan25[[#This Row],[Optimal $]]*IF(RosterPlan25[[#This Row],[Contract]]="Rookie",0.3,0.15),0) -> 0 | O12: =IF(RosterPlan25[[#This Row],[SOURCE]]="Rookie", INDEX(INDIRECT("Rookies" & SEASON & "[salary]"),MATCH(RosterPlan25[[#This Row],[PLAYER]],INDIRECT("Rookies"& SEASON & "[full_name]"),0)), MAX(RosterPlan25[[#This Row],[$ PREV]] + IF(RAISES_ENABLED,RosterPlan25[[#This Row],[$↑ VAR]],0),1)) -> 5 | P12: =IF(VARG="MANUAL",RosterPlan25[[#This Row],[ManualVARG]],IF(VARG="GOOD",RosterPlan25[[#This Row],[GoodVARG]],"ERR")) -> -0.025005977 | Q12: =_xlfn.IFNA(IF(RosterPlan25[[#This Row],[POS]]="K",0,INDEX(GoodSheets[MG VARG],MATCH(TEXT(RosterPlan25[[#This Row],[player_id]],"0"),GoodSheets[sleeper_id],0))), IF(RosterPlan25[[#This Row],[POS]]="QB",-12,IF(RosterPlan25[[#This Row],[POS]]="RB",-8,IF(RosterPlan25[[#This Row],[POS]]="WR",-8,-5)))) -> -0.025005977 | R12: =_xlfn.IFNA(INDEX(ALL_Athletic[VARG], MATCH(RosterPlan25[[#This Row],[player_id]],ALL_Athletic[SleeperID],0)), IF(RosterPlan25[[#This Row],[POS]]="QB",-12,IF(RosterPlan25[[#This Row],[POS]]="RB",-8,IF(RosterPlan25[[#This Row],[POS]]="WR",-8,-5)))) -> -8 | S12: K | T12: =_xlfn.IFNA(INDEX(Draft2025[Net Keeper Count],RosterPlan25[[#This Row],[DraftIndex]]),0)+IF(RosterPlan25[[#This Row],[KEEPER / RFA]]="K",1,0) -> 1 | U12: =IF(RosterPlan25[[#This Row],[KEEPER / RFA]]="RFA",RosterPlan25[[#This Row],[Pure Inflated $]],"") | V12: =IF(RosterPlan25[[#This Row],[VAR/G]]>0, ROUND(IF(VARG="GOOD",$AG$29,IF(VARG="ATHLETIC",$AH$29,99999999999))*RosterPlan25[[#This Row],[VAR/G]],0), 0) + 1 -> 1 | W12: =RosterPlan25[[#This Row],[Optimal $]]-RosterPlan25[[#This Row],[$ CURR]] -> -4 | X12: =IF(OR(RosterPlan25[[#This Row],[SOURCE]]="Rookie",RosterPlan25[[#This Row],[POS]]="K"),0,RosterPlan25[[#This Row],[VAR/G]]+3.3) -> 3.274994 | Y12: =IF(RosterPlan25[[#This Row],[VAW/G]]>0,ROUND(RosterPlan25[[#This Row],[VAW/G]]*$AG$56,0)+1,1) -> 55 | Z12: =RosterPlan25[[#This Row],[VAWG Market $]]-_xlfn.IFNA(RosterPlan25[[#This Row],[$ CURR]],1) -> 50 | AA12: =IF(RosterPlan25[[#This Row],[VAR/G]]>0,1+ROUND(RosterPlan25[[#This Row],[VAR/G]]*IF(RosterPlan25[[#This Row],[KEEPER / RFA]]="K",($AG$34+RosterPlan25[[#This Row],[$ CURR]]-1)/($AG$23+RosterPlan25[[#This Row],[VAR/G]]),$AG$35),0),1) -> 1 | AB12: =RosterPlan25[[#This Row],[Pure Inflated $]]-RosterPlan25[[#This Row],[$ CURR]] -> -4 | AC12: =INDEX(players[age],MATCH(RosterPlan25[[#This Row],[player_id]],players[sleeper_id],0)) -> 25 | AG12: =SUM(AG2:AG11) -> 2073 | AH12: =SUM(AH2:AH11) -> 2073 | AJ12: =SUM(AJ2:AJ11) -> 207 | AL12: =SUM(AL2:AL11) -> 2 | AM12: =SUM(AM2:AM11) -> 2106 | AN12: =SUM(AN2:AN11) -> 179.66451 | AO12: =SUM(AO2:AO11) -> 0 | AP12: =SUM(AP2:AP11) -> 0 | AR12: =SUM(AR2:AR11) -> 234.07171
A13: 11638 | B13: BobbyBaby | C13: Ricky Pearsall | D13: =_xlfn.IFNA(MATCH(RosterPlan25[[#This Row],[player_id]],CompositeRoster[sleeper_id],0), MATCH(RosterPlan25[[#This Row],[PLAYER]],CompositeRoster[full_name],0)) -> 12 | E13: =MATCH(RosterPlan25[[#This Row],[player_id]],Draft2025[sleeper_id],0) -> 13 | F13: =INDEX(CompositeRoster[team],RosterPlan25[[#This Row],[RosterIndex]])&"" -> SF | G13: =INDEX(CompositeRoster[position],RosterPlan25[[#This Row],[RosterIndex]])&"" -> WR | H13: =INDEX(CompositeRoster[source],RosterPlan25[[#This Row],[RosterIndex]]) -> Roster | I13: =_xlfn.IFNA(INDEX(Draft2025[PRICE],RosterPlan25[[#This Row],[DraftIndex]]),0) -> 5 | J13: =IF(RosterPlan25[[#This Row],[SOURCE]]="Rookie","Rookie",_xlfn.IFNA(INDEX(Draft2025[Current Contract],RosterPlan25[[#This Row],[DraftIndex]]),"Undrafted")) -> Rookie | K13: {=IF(OR(ISBLANK(RosterPlan25[[#This Row],[player_id]]),NOT(ISNA(MATCH(RosterPlan25[[#This Row],[player_id]],INDIRECT("Rookies" & SEASON &"[player_id]"),0)))), SEASON, _xlfn.IFNA(INDEX(Draft2025[Contract Year],RosterPlan25[[#This Row],[DraftIndex]]),IF(IN_SEASON,SEASON,SEASON-1)))} -> 2024 | L13: =IF(_xlfn.IFNA(INDEX(Draft2025[KEEPER],RosterPlan25[[#This Row],[DraftIndex]]),"")="K","Yes","") -> Yes | M13: {=IF(RosterPlan25[[#This Row],[Contract]]="Rookie", "", IF(_xlfn.IFNA(INDEX(Draft2025[Contract Year],RosterPlan25[[#This Row],[DraftIndex]]),IF(IN_SEASON,SEASON,SEASON-1))+3<SEASON, SEASON, _xlfn.IFNA(INDEX(Draft2025[Contract Year],RosterPlan25[[#This Row],[DraftIndex]]),IF(IN_SEASON,SEASON,SEASON-1))+3))} | N13: =ROUNDDOWN(RosterPlan25[[#This Row],[Optimal $]]*IF(RosterPlan25[[#This Row],[Contract]]="Rookie",0.3,0.15),0) -> 0 | O13: =IF(RosterPlan25[[#This Row],[SOURCE]]="Rookie", INDEX(INDIRECT("Rookies" & SEASON & "[salary]"),MATCH(RosterPlan25[[#This Row],[PLAYER]],INDIRECT("Rookies"& SEASON & "[full_name]"),0)), MAX(RosterPlan25[[#This Row],[$ PREV]] + IF(RAISES_ENABLED,RosterPlan25[[#This Row],[$↑ VAR]],0),1)) -> 5 | P13: =IF(VARG="MANUAL",RosterPlan25[[#This Row],[ManualVARG]],IF(VARG="GOOD",RosterPlan25[[#This Row],[GoodVARG]],"ERR")) -> -2.5011323 | Q13: =_xlfn.IFNA(IF(RosterPlan25[[#This Row],[POS]]="K",0,INDEX(GoodSheets[MG VARG],MATCH(TEXT(RosterPlan25[[#This Row],[player_id]],"0"),GoodSheets[sleeper_id],0))), IF(RosterPlan25[[#This Row],[POS]]="QB",-12,IF(RosterPlan25[[#This Row],[POS]]="RB",-8,IF(RosterPlan25[[#This Row],[POS]]="WR",-8,-5)))) -> -2.5011323 | R13: =_xlfn.IFNA(INDEX(ALL_Athletic[VARG], MATCH(RosterPlan25[[#This Row],[player_id]],ALL_Athletic[SleeperID],0)), IF(RosterPlan25[[#This Row],[POS]]="QB",-12,IF(RosterPlan25[[#This Row],[POS]]="RB",-8,IF(RosterPlan25[[#This Row],[POS]]="WR",-8,-5)))) -> -8 | S13: K | T13: =_xlfn.IFNA(INDEX(Draft2025[Net Keeper Count],RosterPlan25[[#This Row],[DraftIndex]]),0)+IF(RosterPlan25[[#This Row],[KEEPER / RFA]]="K",1,0) -> 2 | U13: =IF(RosterPlan25[[#This Row],[KEEPER / RFA]]="RFA",RosterPlan25[[#This Row],[Pure Inflated $]],"") | V13: =IF(RosterPlan25[[#This Row],[VAR/G]]>0, ROUND(IF(VARG="GOOD",$AG$29,IF(VARG="ATHLETIC",$AH$29,99999999999))*RosterPlan25[[#This Row],[VAR/G]],0), 0) + 1 -> 1 | W13: =RosterPlan25[[#This Row],[Optimal $]]-RosterPlan25[[#This Row],[$ CURR]] -> -4 | X13: =IF(OR(RosterPlan25[[#This Row],[SOURCE]]="Rookie",RosterPlan25[[#This Row],[POS]]="K"),0,RosterPlan25[[#This Row],[VAR/G]]+3.3) -> 0.79886766 | Y13: =IF(RosterPlan25[[#This Row],[VAW/G]]>0,ROUND(RosterPlan25[[#This Row],[VAW/G]]*$AG$56,0)+1,1) -> 14 | Z13: =RosterPlan25[[#This Row],[VAWG Market $]]-_xlfn.IFNA(RosterPlan25[[#This Row],[$ CURR]],1) -> 9 | AA13: =IF(RosterPlan25[[#This Row],[VAR/G]]>0,1+ROUND(RosterPlan25[[#This Row],[VAR/G]]*IF(RosterPlan25[[#This Row],[KEEPER / RFA]]="K",($AG$34+RosterPlan25[[#This Row],[$ CURR]]-1)/($AG$23+RosterPlan25[[#This Row],[VAR/G]]),$AG$35),0),1) -> 1 | AB13: =RosterPlan25[[#This Row],[Pure Inflated $]]-RosterPlan25[[#This Row],[$ CURR]] -> -4 | AC13: =INDEX(players[age],MATCH(RosterPlan25[[#This Row],[player_id]],players[sleeper_id],0)) -> 25
A14: 2449 | B14: BobbyBaby | C14: Stefon Diggs | D14: =_xlfn.IFNA(MATCH(RosterPlan25[[#This Row],[player_id]],CompositeRoster[sleeper_id],0), MATCH(RosterPlan25[[#This Row],[PLAYER]],CompositeRoster[full_name],0)) -> 13 | E14: =MATCH(RosterPlan25[[#This Row],[player_id]],Draft2025[sleeper_id],0) -> 3 | F14: =INDEX(CompositeRoster[team],RosterPlan25[[#This Row],[RosterIndex]])&"" -> WAS | G14: =INDEX(CompositeRoster[position],RosterPlan25[[#This Row],[RosterIndex]])&"" -> WR | H14: =INDEX(CompositeRoster[source],RosterPlan25[[#This Row],[RosterIndex]]) -> Roster | I14: =_xlfn.IFNA(INDEX(Draft2025[PRICE],RosterPlan25[[#This Row],[DraftIndex]]),0) -> 3 | J14: =IF(RosterPlan25[[#This Row],[SOURCE]]="Rookie","Rookie",_xlfn.IFNA(INDEX(Draft2025[Current Contract],RosterPlan25[[#This Row],[DraftIndex]]),"Undrafted")) -> Auction | K14: {=IF(OR(ISBLANK(RosterPlan25[[#This Row],[player_id]]),NOT(ISNA(MATCH(RosterPlan25[[#This Row],[player_id]],INDIRECT("Rookies" & SEASON &"[player_id]"),0)))), SEASON, _xlfn.IFNA(INDEX(Draft2025[Contract Year],RosterPlan25[[#This Row],[DraftIndex]]),IF(IN_SEASON,SEASON,SEASON-1)))} -> 2025 | L14: =IF(_xlfn.IFNA(INDEX(Draft2025[KEEPER],RosterPlan25[[#This Row],[DraftIndex]]),"")="K","Yes","") -> Yes | M14: {=IF(RosterPlan25[[#This Row],[Contract]]="Rookie", "", IF(_xlfn.IFNA(INDEX(Draft2025[Contract Year],RosterPlan25[[#This Row],[DraftIndex]]),IF(IN_SEASON,SEASON,SEASON-1))+3<SEASON, SEASON, _xlfn.IFNA(INDEX(Draft2025[Contract Year],RosterPlan25[[#This Row],[DraftIndex]]),IF(IN_SEASON,SEASON,SEASON-1))+3))} -> 2028 | N14: =ROUNDDOWN(RosterPlan25[[#This Row],[Optimal $]]*IF(RosterPlan25[[#This Row],[Contract]]="Rookie",0.3,0.15),0) -> 0 | O14: =IF(RosterPlan25[[#This Row],[SOURCE]]="Rookie", INDEX(INDIRECT("Rookies" & SEASON & "[salary]"),MATCH(RosterPlan25[[#This Row],[PLAYER]],INDIRECT("Rookies"& SEASON & "[full_name]"),0)), MAX(RosterPlan25[[#This Row],[$ PREV]] + IF(RAISES_ENABLED,RosterPlan25[[#This Row],[$↑ VAR]],0),1)) -> 3 | P14: =IF(VARG="MANUAL",RosterPlan25[[#This Row],[ManualVARG]],IF(VARG="GOOD",RosterPlan25[[#This Row],[GoodVARG]],"ERR")) -> -8 | Q14: =_xlfn.IFNA(IF(RosterPlan25[[#This Row],[POS]]="K",0,INDEX(GoodSheets[MG VARG],MATCH(TEXT(RosterPlan25[[#This Row],[player_id]],"0"),GoodSheets[sleeper_id],0))), IF(RosterPlan25[[#This Row],[POS]]="QB",-12,IF(RosterPlan25[[#This Row],[POS]]="RB",-8,IF(RosterPlan25[[#This Row],[POS]]="WR",-8,-5)))) -> -8 | R14: =_xlfn.IFNA(INDEX(ALL_Athletic[VARG], MATCH(RosterPlan25[[#This Row],[player_id]],ALL_Athletic[SleeperID],0)), IF(RosterPlan25[[#This Row],[POS]]="QB",-12,IF(RosterPlan25[[#This Row],[POS]]="RB",-8,IF(RosterPlan25[[#This Row],[POS]]="WR",-8,-5)))) -> 4.1727501 | S14: K | T14: =_xlfn.IFNA(INDEX(Draft2025[Net Keeper Count],RosterPlan25[[#This Row],[DraftIndex]]),0)+IF(RosterPlan25[[#This Row],[KEEPER / RFA]]="K",1,0) -> 1 | U14: =IF(RosterPlan25[[#This Row],[KEEPER / RFA]]="RFA",RosterPlan25[[#This Row],[Pure Inflated $]],"") | V14: =IF(RosterPlan25[[#This Row],[VAR/G]]>0, ROUND(IF(VARG="GOOD",$AG$29,IF(VARG="ATHLETIC",$AH$29,99999999999))*RosterPlan25[[#This Row],[VAR/G]],0), 0) + 1 -> 1 | W14: =RosterPlan25[[#This Row],[Optimal $]]-RosterPlan25[[#This Row],[$ CURR]] -> -2 | X14: =IF(OR(RosterPlan25[[#This Row],[SOURCE]]="Rookie",RosterPlan25[[#This Row],[POS]]="K"),0,RosterPlan25[[#This Row],[VAR/G]]+3.3) -> -4.7 | Y14: =IF(RosterPlan25[[#This Row],[VAW/G]]>0,ROUND(RosterPlan25[[#This Row],[VAW/G]]*$AG$56,0)+1,1) -> 1 | Z14: =RosterPlan25[[#This Row],[VAWG Market $]]-_xlfn.IFNA(RosterPlan25[[#This Row],[$ CURR]],1) -> -2 | AA14: =IF(RosterPlan25[[#This Row],[VAR/G]]>0,1+ROUND(RosterPlan25[[#This Row],[VAR/G]]*IF(RosterPlan25[[#This Row],[KEEPER / RFA]]="K",($AG$34+RosterPlan25[[#This Row],[$ CURR]]-1)/($AG$23+RosterPlan25[[#This Row],[VAR/G]]),$AG$35),0),1) -> 1 | AB14: =RosterPlan25[[#This Row],[Pure Inflated $]]-RosterPlan25[[#This Row],[$ CURR]] -> -2 | AC14: =INDEX(players[age],MATCH(RosterPlan25[[#This Row],[player_id]],players[sleeper_id],0)) -> 32
A15: 12487 | B15: BobbyBaby | C15: Terrance Ferguson | D15: =_xlfn.IFNA(MATCH(RosterPlan25[[#This Row],[player_id]],CompositeRoster[sleeper_id],0), MATCH(RosterPlan25[[#This Row],[PLAYER]],CompositeRoster[full_name],0)) -> 14 | E15: =MATCH(RosterPlan25[[#This Row],[player_id]],Draft2025[sleeper_id],0) -> 23 | F15: =INDEX(CompositeRoster[team],RosterPlan25[[#This Row],[RosterIndex]])&"" -> LAR | G15: =INDEX(CompositeRoster[position],RosterPlan25[[#This Row],[RosterIndex]])&"" -> TE | H15: =INDEX(CompositeRoster[source],RosterPlan25[[#This Row],[RosterIndex]]) -> Roster | I15: =_xlfn.IFNA(INDEX(Draft2025[PRICE],RosterPlan25[[#This Row],[DraftIndex]]),0) -> 3 | J15: =IF(RosterPlan25[[#This Row],[SOURCE]]="Rookie","Rookie",_xlfn.IFNA(INDEX(Draft2025[Current Contract],RosterPlan25[[#This Row],[DraftIndex]]),"Undrafted")) -> Rookie | K15: {=IF(OR(ISBLANK(RosterPlan25[[#This Row],[player_id]]),NOT(ISNA(MATCH(RosterPlan25[[#This Row],[player_id]],INDIRECT("Rookies" & SEASON &"[player_id]"),0)))), SEASON, _xlfn.IFNA(INDEX(Draft2025[Contract Year],RosterPlan25[[#This Row],[DraftIndex]]),IF(IN_SEASON,SEASON,SEASON-1)))} -> 2025 | L15: =IF(_xlfn.IFNA(INDEX(Draft2025[KEEPER],RosterPlan25[[#This Row],[DraftIndex]]),"")="K","Yes","") | M15: {=IF(RosterPlan25[[#This Row],[Contract]]="Rookie", "", IF(_xlfn.IFNA(INDEX(Draft2025[Contract Year],RosterPlan25[[#This Row],[DraftIndex]]),IF(IN_SEASON,SEASON,SEASON-1))+3<SEASON, SEASON, _xlfn.IFNA(INDEX(Draft2025[Contract Year],RosterPlan25[[#This Row],[DraftIndex]]),IF(IN_SEASON,SEASON,SEASON-1))+3))} | N15: =ROUNDDOWN(RosterPlan25[[#This Row],[Optimal $]]*IF(RosterPlan25[[#This Row],[Contract]]="Rookie",0.3,0.15),0) -> 0 | O15: =IF(RosterPlan25[[#This Row],[SOURCE]]="Rookie", INDEX(INDIRECT("Rookies" & SEASON & "[salary]"),MATCH(RosterPlan25[[#This Row],[PLAYER]],INDIRECT("Rookies"& SEASON & "[full_name]"),0)), MAX(RosterPlan25[[#This Row],[$ PREV]] + IF(RAISES_ENABLED,RosterPlan25[[#This Row],[$↑ VAR]],0),1)) -> 3 | P15: =IF(VARG="MANUAL",RosterPlan25[[#This Row],[ManualVARG]],IF(VARG="GOOD",RosterPlan25[[#This Row],[GoodVARG]],"ERR")) -> -2.0876805 | Q15: =_xlfn.IFNA(IF(RosterPlan25[[#This Row],[POS]]="K",0,INDEX(GoodSheets[MG VARG],MATCH(TEXT(RosterPlan25[[#This Row],[player_id]],"0"),GoodSheets[sleeper_id],0))), IF(RosterPlan25[[#This Row],[POS]]="QB",-12,IF(RosterPlan25[[#This Row],[POS]]="RB",-8,IF(RosterPlan25[[#This Row],[POS]]="WR",-8,-5)))) -> -2.0876805 | R15: =_xlfn.IFNA(INDEX(ALL_Athletic[VARG], MATCH(RosterPlan25[[#This Row],[player_id]],ALL_Athletic[SleeperID],0)), IF(RosterPlan25[[#This Row],[POS]]="QB",-12,IF(RosterPlan25[[#This Row],[POS]]="RB",-8,IF(RosterPlan25[[#This Row],[POS]]="WR",-8,-5)))) -> -5 | S15: K | T15: =_xlfn.IFNA(INDEX(Draft2025[Net Keeper Count],RosterPlan25[[#This Row],[DraftIndex]]),0)+IF(RosterPlan25[[#This Row],[KEEPER / RFA]]="K",1,0) -> 1 | U15: =IF(RosterPlan25[[#This Row],[KEEPER / RFA]]="RFA",RosterPlan25[[#This Row],[Pure Inflated $]],"") | V15: =IF(RosterPlan25[[#This Row],[VAR/G]]>0, ROUND(IF(VARG="GOOD",$AG$29,IF(VARG="ATHLETIC",$AH$29,99999999999))*RosterPlan25[[#This Row],[VAR/G]],0), 0) + 1 -> 1 | W15: =RosterPlan25[[#This Row],[Optimal $]]-RosterPlan25[[#This Row],[$ CURR]] -> -2 | X15: =IF(OR(RosterPlan25[[#This Row],[SOURCE]]="Rookie",RosterPlan25[[#This Row],[POS]]="K"),0,RosterPlan25[[#This Row],[VAR/G]]+3.3) -> 1.2123195 | Y15: =IF(RosterPlan25[[#This Row],[VAW/G]]>0,ROUND(RosterPlan25[[#This Row],[VAW/G]]*$AG$56,0)+1,1) -> 21 | Z15: =RosterPlan25[[#This Row],[VAWG Market $]]-_xlfn.IFNA(RosterPlan25[[#This Row],[$ CURR]],1) -> 18 | AA15: =IF(RosterPlan25[[#This Row],[VAR/G]]>0,1+ROUND(RosterPlan25[[#This Row],[VAR/G]]*IF(RosterPlan25[[#This Row],[KEEPER / RFA]]="K",($AG$34+RosterPlan25[[#This Row],[$ CURR]]-1)/($AG$23+RosterPlan25[[#This Row],[VAR/G]]),$AG$35),0),1) -> 1 | AB15: =RosterPlan25[[#This Row],[Pure Inflated $]]-RosterPlan25[[#This Row],[$ CURR]] -> -2 | AC15: =INDEX(players[age],MATCH(RosterPlan25[[#This Row],[player_id]],players[sleeper_id],0)) -> 23 | AE15: 8 | AF15: FA Draft Slots
A16: 12497 | B16: BobbyBaby | C16: Tory Horton | D16: =_xlfn.IFNA(MATCH(RosterPlan25[[#This Row],[player_id]],CompositeRoster[sleeper_id],0), MATCH(RosterPlan25[[#This Row],[PLAYER]],CompositeRoster[full_name],0)) -> 15 | E16: =MATCH(RosterPlan25[[#This Row],[player_id]],Draft2025[sleeper_id],0) -> 24 | F16: =INDEX(CompositeRoster[team],RosterPlan25[[#This Row],[RosterIndex]])&"" -> SEA | G16: =INDEX(CompositeRoster[position],RosterPlan25[[#This Row],[RosterIndex]])&"" -> WR | H16: =INDEX(CompositeRoster[source],RosterPlan25[[#This Row],[RosterIndex]]) -> Roster | I16: =_xlfn.IFNA(INDEX(Draft2025[PRICE],RosterPlan25[[#This Row],[DraftIndex]]),0) -> 2 | J16: =IF(RosterPlan25[[#This Row],[SOURCE]]="Rookie","Rookie",_xlfn.IFNA(INDEX(Draft2025[Current Contract],RosterPlan25[[#This Row],[DraftIndex]]),"Undrafted")) -> Rookie | K16: {=IF(OR(ISBLANK(RosterPlan25[[#This Row],[player_id]]),NOT(ISNA(MATCH(RosterPlan25[[#This Row],[player_id]],INDIRECT("Rookies" & SEASON &"[player_id]"),0)))), SEASON, _xlfn.IFNA(INDEX(Draft2025[Contract Year],RosterPlan25[[#This Row],[DraftIndex]]),IF(IN_SEASON,SEASON,SEASON-1)))} -> 2025 | L16: =IF(_xlfn.IFNA(INDEX(Draft2025[KEEPER],RosterPlan25[[#This Row],[DraftIndex]]),"")="K","Yes","") | M16: {=IF(RosterPlan25[[#This Row],[Contract]]="Rookie", "", IF(_xlfn.IFNA(INDEX(Draft2025[Contract Year],RosterPlan25[[#This Row],[DraftIndex]]),IF(IN_SEASON,SEASON,SEASON-1))+3<SEASON, SEASON, _xlfn.IFNA(INDEX(Draft2025[Contract Year],RosterPlan25[[#This Row],[DraftIndex]]),IF(IN_SEASON,SEASON,SEASON-1))+3))} | N16: =ROUNDDOWN(RosterPlan25[[#This Row],[Optimal $]]*IF(RosterPlan25[[#This Row],[Contract]]="Rookie",0.3,0.15),0) -> 0 | O16: =IF(RosterPlan25[[#This Row],[SOURCE]]="Rookie", INDEX(INDIRECT("Rookies" & SEASON & "[salary]"),MATCH(RosterPlan25[[#This Row],[PLAYER]],INDIRECT("Rookies"& SEASON & "[full_name]"),0)), MAX(RosterPlan25[[#This Row],[$ PREV]] + IF(RAISES_ENABLED,RosterPlan25[[#This Row],[$↑ VAR]],0),1)) -> 2 | P16: =IF(VARG="MANUAL",RosterPlan25[[#This Row],[ManualVARG]],IF(VARG="GOOD",RosterPlan25[[#This Row],[GoodVARG]],"ERR")) -> -3.6156912 | Q16: =_xlfn.IFNA(IF(RosterPlan25[[#This Row],[POS]]="K",0,INDEX(GoodSheets[MG VARG],MATCH(TEXT(RosterPlan25[[#This Row],[player_id]],"0"),GoodSheets[sleeper_id],0))), IF(RosterPlan25[[#This Row],[POS]]="QB",-12,IF(RosterPlan25[[#This Row],[POS]]="RB",-8,IF(RosterPlan25[[#This Row],[POS]]="WR",-8,-5)))) -> -3.6156912 | R16: =_xlfn.IFNA(INDEX(ALL_Athletic[VARG], MATCH(RosterPlan25[[#This Row],[player_id]],ALL_Athletic[SleeperID],0)), IF(RosterPlan25[[#This Row],[POS]]="QB",-12,IF(RosterPlan25[[#This Row],[POS]]="RB",-8,IF(RosterPlan25[[#This Row],[POS]]="WR",-8,-5)))) -> -8 | S16: K | T16: =_xlfn.IFNA(INDEX(Draft2025[Net Keeper Count],RosterPlan25[[#This Row],[DraftIndex]]),0)+IF(RosterPlan25[[#This Row],[KEEPER / RFA]]="K",1,0) -> 1 | U16: =IF(RosterPlan25[[#This Row],[KEEPER / RFA]]="RFA",RosterPlan25[[#This Row],[Pure Inflated $]],"") | V16: =IF(RosterPlan25[[#This Row],[VAR/G]]>0, ROUND(IF(VARG="GOOD",$AG$29,IF(VARG="ATHLETIC",$AH$29,99999999999))*RosterPlan25[[#This Row],[VAR/G]],0), 0) + 1 -> 1 | W16: =RosterPlan25[[#This Row],[Optimal $]]-RosterPlan25[[#This Row],[$ CURR]] -> -1 | X16: =IF(OR(RosterPlan25[[#This Row],[SOURCE]]="Rookie",RosterPlan25[[#This Row],[POS]]="K"),0,RosterPlan25[[#This Row],[VAR/G]]+3.3) -> -0.31569123 | Y16: =IF(RosterPlan25[[#This Row],[VAW/G]]>0,ROUND(RosterPlan25[[#This Row],[VAW/G]]*$AG$56,0)+1,1) -> 1 | Z16: =RosterPlan25[[#This Row],[VAWG Market $]]-_xlfn.IFNA(RosterPlan25[[#This Row],[$ CURR]],1) -> -1 | AA16: =IF(RosterPlan25[[#This Row],[VAR/G]]>0,1+ROUND(RosterPlan25[[#This Row],[VAR/G]]*IF(RosterPlan25[[#This Row],[KEEPER / RFA]]="K",($AG$34+RosterPlan25[[#This Row],[$ CURR]]-1)/($AG$23+RosterPlan25[[#This Row],[VAR/G]]),$AG$35),0),1) -> 1 | AB16: =RosterPlan25[[#This Row],[Pure Inflated $]]-RosterPlan25[[#This Row],[$ CURR]] -> -1 | AC16: =INDEX(players[age],MATCH(RosterPlan25[[#This Row],[player_id]],players[sleeper_id],0)) -> 23
A17: 7523 | B17: BobbyBaby | C17: Trevor Lawrence | D17: =_xlfn.IFNA(MATCH(RosterPlan25[[#This Row],[player_id]],CompositeRoster[sleeper_id],0), MATCH(RosterPlan25[[#This Row],[PLAYER]],CompositeRoster[full_name],0)) -> 16 | E17: =MATCH(RosterPlan25[[#This Row],[player_id]],Draft2025[sleeper_id],0) -> 16 | F17: =INDEX(CompositeRoster[team],RosterPlan25[[#This Row],[RosterIndex]])&"" -> JAX | G17: =INDEX(CompositeRoster[position],RosterPlan25[[#This Row],[RosterIndex]])&"" -> QB | H17: =INDEX(CompositeRoster[source],RosterPlan25[[#This Row],[RosterIndex]]) -> Roster | I17: =_xlfn.IFNA(INDEX(Draft2025[PRICE],RosterPlan25[[#This Row],[DraftIndex]]),0) -> 7 | J17: =IF(RosterPlan25[[#This Row],[SOURCE]]="Rookie","Rookie",_xlfn.IFNA(INDEX(Draft2025[Current Contract],RosterPlan25[[#This Row],[DraftIndex]]),"Undrafted")) -> Rookie | K17: {=IF(OR(ISBLANK(RosterPlan25[[#This Row],[player_id]]),NOT(ISNA(MATCH(RosterPlan25[[#This Row],[player_id]],INDIRECT("Rookies" & SEASON &"[player_id]"),0)))), SEASON, _xlfn.IFNA(INDEX(Draft2025[Contract Year],RosterPlan25[[#This Row],[DraftIndex]]),IF(IN_SEASON,SEASON,SEASON-1)))} -> 2021 | L17: =IF(_xlfn.IFNA(INDEX(Draft2025[KEEPER],RosterPlan25[[#This Row],[DraftIndex]]),"")="K","Yes","") -> Yes | M17: {=IF(RosterPlan25[[#This Row],[Contract]]="Rookie", "", IF(_xlfn.IFNA(INDEX(Draft2025[Contract Year],RosterPlan25[[#This Row],[DraftIndex]]),IF(IN_SEASON,SEASON,SEASON-1))+3<SEASON, SEASON, _xlfn.IFNA(INDEX(Draft2025[Contract Year],RosterPlan25[[#This Row],[DraftIndex]]),IF(IN_SEASON,SEASON,SEASON-1))+3))} | N17: =ROUNDDOWN(RosterPlan25[[#This Row],[Optimal $]]*IF(RosterPlan25[[#This Row],[Contract]]="Rookie",0.3,0.15),0) -> 0 | O17: =IF(RosterPlan25[[#This Row],[SOURCE]]="Rookie", INDEX(INDIRECT("Rookies" & SEASON & "[salary]"),MATCH(RosterPlan25[[#This Row],[PLAYER]],INDIRECT("Rookies"& SEASON & "[full_name]"),0)), MAX(RosterPlan25[[#This Row],[$ PREV]] + IF(RAISES_ENABLED,RosterPlan25[[#This Row],[$↑ VAR]],0),1)) -> 7 | P17: =IF(VARG="MANUAL",RosterPlan25[[#This Row],[ManualVARG]],IF(VARG="GOOD",RosterPlan25[[#This Row],[GoodVARG]],"ERR")) -> 0 | Q17: =_xlfn.IFNA(IF(RosterPlan25[[#This Row],[POS]]="K",0,INDEX(GoodSheets[MG VARG],MATCH(TEXT(RosterPlan25[[#This Row],[player_id]],"0"),GoodSheets[sleeper_id],0))), IF(RosterPlan25[[#This Row],[POS]]="QB",-12,IF(RosterPlan25[[#This Row],[POS]]="RB",-8,IF(RosterPlan25[[#This Row],[POS]]="WR",-8,-5)))) -> 0 | R17: =_xlfn.IFNA(INDEX(ALL_Athletic[VARG], MATCH(RosterPlan25[[#This Row],[player_id]],ALL_Athletic[SleeperID],0)), IF(RosterPlan25[[#This Row],[POS]]="QB",-12,IF(RosterPlan25[[#This Row],[POS]]="RB",-8,IF(RosterPlan25[[#This Row],[POS]]="WR",-8,-5)))) -> 1.0064399 | S17: K | T17: =_xlfn.IFNA(INDEX(Draft2025[Net Keeper Count],RosterPlan25[[#This Row],[DraftIndex]]),0)+IF(RosterPlan25[[#This Row],[KEEPER / RFA]]="K",1,0) -> 5 | U17: =IF(RosterPlan25[[#This Row],[KEEPER / RFA]]="RFA",RosterPlan25[[#This Row],[Pure Inflated $]],"") | V17: =IF(RosterPlan25[[#This Row],[VAR/G]]>0, ROUND(IF(VARG="GOOD",$AG$29,IF(VARG="ATHLETIC",$AH$29,99999999999))*RosterPlan25[[#This Row],[VAR/G]],0), 0) + 1 -> 1 | W17: =RosterPlan25[[#This Row],[Optimal $]]-RosterPlan25[[#This Row],[$ CURR]] -> -6 | X17: =IF(OR(RosterPlan25[[#This Row],[SOURCE]]="Rookie",RosterPlan25[[#This Row],[POS]]="K"),0,RosterPlan25[[#This Row],[VAR/G]]+3.3) -> 3.3 | Y17: =IF(RosterPlan25[[#This Row],[VAW/G]]>0,ROUND(RosterPlan25[[#This Row],[VAW/G]]*$AG$56,0)+1,1) -> 55 | Z17: =RosterPlan25[[#This Row],[VAWG Market $]]-_xlfn.IFNA(RosterPlan25[[#This Row],[$ CURR]],1) -> 48 | AA17: =IF(RosterPlan25[[#This Row],[VAR/G]]>0,1+ROUND(RosterPlan25[[#This Row],[VAR/G]]*IF(RosterPlan25[[#This Row],[KEEPER / RFA]]="K",($AG$34+RosterPlan25[[#This Row],[$ CURR]]-1)/($AG$23+RosterPlan25[[#This Row],[VAR/G]]),$AG$35),0),1) -> 1 | AB17: =RosterPlan25[[#This Row],[Pure Inflated $]]-RosterPlan25[[#This Row],[$ CURR]] -> -6 | AC17: =INDEX(players[age],MATCH(RosterPlan25[[#This Row],[player_id]],players[sleeper_id],0)) -> 26
A18: 9508 | B18: BobbyBaby | C18: Tyjae Spears | D18: =_xlfn.IFNA(MATCH(RosterPlan25[[#This Row],[player_id]],CompositeRoster[sleeper_id],0), MATCH(RosterPlan25[[#This Row],[PLAYER]],CompositeRoster[full_name],0)) -> 17 | E18: =MATCH(RosterPlan25[[#This Row],[player_id]],Draft2025[sleeper_id],0) -> 17 | F18: =INDEX(CompositeRoster[team],RosterPlan25[[#This Row],[RosterIndex]])&"" -> TEN | G18: =INDEX(CompositeRoster[position],RosterPlan25[[#This Row],[RosterIndex]])&"" -> RB | H18: =INDEX(CompositeRoster[source],RosterPlan25[[#This Row],[RosterIndex]]) -> Roster | I18: =_xlfn.IFNA(INDEX(Draft2025[PRICE],RosterPlan25[[#This Row],[DraftIndex]]),0) -> 4 | J18: =IF(RosterPlan25[[#This Row],[SOURCE]]="Rookie","Rookie",_xlfn.IFNA(INDEX(Draft2025[Current Contract],RosterPlan25[[#This Row],[DraftIndex]]),"Undrafted")) -> Rookie | K18: {=IF(OR(ISBLANK(RosterPlan25[[#This Row],[player_id]]),NOT(ISNA(MATCH(RosterPlan25[[#This Row],[player_id]],INDIRECT("Rookies" & SEASON &"[player_id]"),0)))), SEASON, _xlfn.IFNA(INDEX(Draft2025[Contract Year],RosterPlan25[[#This Row],[DraftIndex]]),IF(IN_SEASON,SEASON,SEASON-1)))} -> 2023 | L18: =IF(_xlfn.IFNA(INDEX(Draft2025[KEEPER],RosterPlan25[[#This Row],[DraftIndex]]),"")="K","Yes","") -> Yes | M18: {=IF(RosterPlan25[[#This Row],[Contract]]="Rookie", "", IF(_xlfn.IFNA(INDEX(Draft2025[Contract Year],RosterPlan25[[#This Row],[DraftIndex]]),IF(IN_SEASON,SEASON,SEASON-1))+3<SEASON, SEASON, _xlfn.IFNA(INDEX(Draft2025[Contract Year],RosterPlan25[[#This Row],[DraftIndex]]),IF(IN_SEASON,SEASON,SEASON-1))+3))} | N18: =ROUNDDOWN(RosterPlan25[[#This Row],[Optimal $]]*IF(RosterPlan25[[#This Row],[Contract]]="Rookie",0.3,0.15),0) -> 0 | O18: =IF(RosterPlan25[[#This Row],[SOURCE]]="Rookie", INDEX(INDIRECT("Rookies" & SEASON & "[salary]"),MATCH(RosterPlan25[[#This Row],[PLAYER]],INDIRECT("Rookies"& SEASON & "[full_name]"),0)), MAX(RosterPlan25[[#This Row],[$ PREV]] + IF(RAISES_ENABLED,RosterPlan25[[#This Row],[$↑ VAR]],0),1)) -> 4 | P18: =IF(VARG="MANUAL",RosterPlan25[[#This Row],[ManualVARG]],IF(VARG="GOOD",RosterPlan25[[#This Row],[GoodVARG]],"ERR")) -> -2.1598978 | Q18: =_xlfn.IFNA(IF(RosterPlan25[[#This Row],[POS]]="K",0,INDEX(GoodSheets[MG VARG],MATCH(TEXT(RosterPlan25[[#This Row],[player_id]],"0"),GoodSheets[sleeper_id],0))), IF(RosterPlan25[[#This Row],[POS]]="QB",-12,IF(RosterPlan25[[#This Row],[POS]]="RB",-8,IF(RosterPlan25[[#This Row],[POS]]="WR",-8,-5)))) -> -2.1598978 | R18: =_xlfn.IFNA(INDEX(ALL_Athletic[VARG], MATCH(RosterPlan25[[#This Row],[player_id]],ALL_Athletic[SleeperID],0)), IF(RosterPlan25[[#This Row],[POS]]="QB",-12,IF(RosterPlan25[[#This Row],[POS]]="RB",-8,IF(RosterPlan25[[#This Row],[POS]]="WR",-8,-5)))) -> -3.026472 | S18: K | T18: =_xlfn.IFNA(INDEX(Draft2025[Net Keeper Count],RosterPlan25[[#This Row],[DraftIndex]]),0)+IF(RosterPlan25[[#This Row],[KEEPER / RFA]]="K",1,0) -> 3 | U18: =IF(RosterPlan25[[#This Row],[KEEPER / RFA]]="RFA",RosterPlan25[[#This Row],[Pure Inflated $]],"") | V18: =IF(RosterPlan25[[#This Row],[VAR/G]]>0, ROUND(IF(VARG="GOOD",$AG$29,IF(VARG="ATHLETIC",$AH$29,99999999999))*RosterPlan25[[#This Row],[VAR/G]],0), 0) + 1 -> 1 | W18: =RosterPlan25[[#This Row],[Optimal $]]-RosterPlan25[[#This Row],[$ CURR]] -> -3 | X18: =IF(OR(RosterPlan25[[#This Row],[SOURCE]]="Rookie",RosterPlan25[[#This Row],[POS]]="K"),0,RosterPlan25[[#This Row],[VAR/G]]+3.3) -> 1.1401022 | Y18: =IF(RosterPlan25[[#This Row],[VAW/G]]>0,ROUND(RosterPlan25[[#This Row],[VAW/G]]*$AG$56,0)+1,1) -> 20 | Z18: =RosterPlan25[[#This Row],[VAWG Market $]]-_xlfn.IFNA(RosterPlan25[[#This Row],[$ CURR]],1) -> 16 | AA18: =IF(RosterPlan25[[#This Row],[VAR/G]]>0,1+ROUND(RosterPlan25[[#This Row],[VAR/G]]*IF(RosterPlan25[[#This Row],[KEEPER / RFA]]="K",($AG$34+RosterPlan25[[#This Row],[$ CURR]]-1)/($AG$23+RosterPlan25[[#This Row],[VAR/G]]),$AG$35),0),1) -> 1 | AB18: =RosterPlan25[[#This Row],[Pure Inflated $]]-RosterPlan25[[#This Row],[$ CURR]] -> -3 | AC18: =INDEX(players[age],MATCH(RosterPlan25[[#This Row],[player_id]],players[sleeper_id],0)) -> 25
A19: 9753 | B19: BobbyBaby | C19: Zach Charbonnet | D19: =_xlfn.IFNA(MATCH(RosterPlan25[[#This Row],[player_id]],CompositeRoster[sleeper_id],0), MATCH(RosterPlan25[[#This Row],[PLAYER]],CompositeRoster[full_name],0)) -> 18 | E19: =MATCH(RosterPlan25[[#This Row],[player_id]],Draft2025[sleeper_id],0) -> 18 | F19: =INDEX(CompositeRoster[team],RosterPlan25[[#This Row],[RosterIndex]])&"" -> SEA | G19: =INDEX(CompositeRoster[position],RosterPlan25[[#This Row],[RosterIndex]])&"" -> RB | H19: =INDEX(CompositeRoster[source],RosterPlan25[[#This Row],[RosterIndex]]) -> Roster | I19: =_xlfn.IFNA(INDEX(Draft2025[PRICE],RosterPlan25[[#This Row],[DraftIndex]]),0) -> 6 | J19: =IF(RosterPlan25[[#This Row],[SOURCE]]="Rookie","Rookie",_xlfn.IFNA(INDEX(Draft2025[Current Contract],RosterPlan25[[#This Row],[DraftIndex]]),"Undrafted")) -> Rookie | K19: {=IF(OR(ISBLANK(RosterPlan25[[#This Row],[player_id]]),NOT(ISNA(MATCH(RosterPlan25[[#This Row],[player_id]],INDIRECT("Rookies" & SEASON &"[player_id]"),0)))), SEASON, _xlfn.IFNA(INDEX(Draft2025[Contract Year],RosterPlan25[[#This Row],[DraftIndex]]),IF(IN_SEASON,SEASON,SEASON-1)))} -> 2023 | L19: =IF(_xlfn.IFNA(INDEX(Draft2025[KEEPER],RosterPlan25[[#This Row],[DraftIndex]]),"")="K","Yes","") -> Yes | M19: {=IF(RosterPlan25[[#This Row],[Contract]]="Rookie", "", IF(_xlfn.IFNA(INDEX(Draft2025[Contract Year],RosterPlan25[[#This Row],[DraftIndex]]),IF(IN_SEASON,SEASON,SEASON-1))+3<SEASON, SEASON, _xlfn.IFNA(INDEX(Draft2025[Contract Year],RosterPlan25[[#This Row],[DraftIndex]]),IF(IN_SEASON,SEASON,SEASON-1))+3))} | N19: =ROUNDDOWN(RosterPlan25[[#This Row],[Optimal $]]*IF(RosterPlan25[[#This Row],[Contract]]="Rookie",0.3,0.15),0) -> 0 | O19: =IF(RosterPlan25[[#This Row],[SOURCE]]="Rookie", INDEX(INDIRECT("Rookies" & SEASON & "[salary]"),MATCH(RosterPlan25[[#This Row],[PLAYER]],INDIRECT("Rookies"& SEASON & "[full_name]"),0)), MAX(RosterPlan25[[#This Row],[$ PREV]] + IF(RAISES_ENABLED,RosterPlan25[[#This Row],[$↑ VAR]],0),1)) -> 6 | P19: =IF(VARG="MANUAL",RosterPlan25[[#This Row],[ManualVARG]],IF(VARG="GOOD",RosterPlan25[[#This Row],[GoodVARG]],"ERR")) -> -2.5801855 | Q19: =_xlfn.IFNA(IF(RosterPlan25[[#This Row],[POS]]="K",0,INDEX(GoodSheets[MG VARG],MATCH(TEXT(RosterPlan25[[#This Row],[player_id]],"0"),GoodSheets[sleeper_id],0))), IF(RosterPlan25[[#This Row],[POS]]="QB",-12,IF(RosterPlan25[[#This Row],[POS]]="RB",-8,IF(RosterPlan25[[#This Row],[POS]]="WR",-8,-5)))) -> -2.5801855 | R19: =_xlfn.IFNA(INDEX(ALL_Athletic[VARG], MATCH(RosterPlan25[[#This Row],[player_id]],ALL_Athletic[SleeperID],0)), IF(RosterPlan25[[#This Row],[POS]]="QB",-12,IF(RosterPlan25[[#This Row],[POS]]="RB",-8,IF(RosterPlan25[[#This Row],[POS]]="WR",-8,-5)))) -> -1.2770553 | S19: K | T19: =_xlfn.IFNA(INDEX(Draft2025[Net Keeper Count],RosterPlan25[[#This Row],[DraftIndex]]),0)+IF(RosterPlan25[[#This Row],[KEEPER / RFA]]="K",1,0) -> 3 | U19: =IF(RosterPlan25[[#This Row],[KEEPER / RFA]]="RFA",RosterPlan25[[#This Row],[Pure Inflated $]],"") | V19: =IF(RosterPlan25[[#This Row],[VAR/G]]>0, ROUND(IF(VARG="GOOD",$AG$29,IF(VARG="ATHLETIC",$AH$29,99999999999))*RosterPlan25[[#This Row],[VAR/G]],0), 0) + 1 -> 1 | W19: =RosterPlan25[[#This Row],[Optimal $]]-RosterPlan25[[#This Row],[$ CURR]] -> -5 | X19: =IF(OR(RosterPlan25[[#This Row],[SOURCE]]="Rookie",RosterPlan25[[#This Row],[POS]]="K"),0,RosterPlan25[[#This Row],[VAR/G]]+3.3) -> 0.71981446 | Y19: =IF(RosterPlan25[[#This Row],[VAW/G]]>0,ROUND(RosterPlan25[[#This Row],[VAW/G]]*$AG$56,0)+1,1) -> 13 | Z19: =RosterPlan25[[#This Row],[VAWG Market $]]-_xlfn.IFNA(RosterPlan25[[#This Row],[$ CURR]],1) -> 7 | AA19: =IF(RosterPlan25[[#This Row],[VAR/G]]>0,1+ROUND(RosterPlan25[[#This Row],[VAR/G]]*IF(RosterPlan25[[#This Row],[KEEPER / RFA]]="K",($AG$34+RosterPlan25[[#This Row],[$ CURR]]-1)/($AG$23+RosterPlan25[[#This Row],[VAR/G]]),$AG$35),0),1) -> 1 | AB19: =RosterPlan25[[#This Row],[Pure Inflated $]]-RosterPlan25[[#This Row],[$ CURR]] -> -5 | AC19: =INDEX(players[age],MATCH(RosterPlan25[[#This Row],[player_id]],players[sleeper_id],0)) -> 25
A20: 13311 | B20: BobbyBaby | C20: Chris Bell | D20: =_xlfn.IFNA(MATCH(RosterPlan25[[#This Row],[player_id]],CompositeRoster[sleeper_id],0), MATCH(RosterPlan25[[#This Row],[PLAYER]],CompositeRoster[full_name],0)) -> 19 | E20: =MATCH(RosterPlan25[[#This Row],[player_id]],Draft2025[sleeper_id],0) -> #N/A | F20: =INDEX(CompositeRoster[team],RosterPlan25[[#This Row],[RosterIndex]])&"" -> MIA | G20: =INDEX(CompositeRoster[position],RosterPlan25[[#This Row],[RosterIndex]])&"" -> WR | H20: =INDEX(CompositeRoster[source],RosterPlan25[[#This Row],[RosterIndex]]) -> Rookie | I20: =_xlfn.IFNA(INDEX(Draft2025[PRICE],RosterPlan25[[#This Row],[DraftIndex]]),0) -> 0 | J20: =IF(RosterPlan25[[#This Row],[SOURCE]]="Rookie","Rookie",_xlfn.IFNA(INDEX(Draft2025[Current Contract],RosterPlan25[[#This Row],[DraftIndex]]),"Undrafted")) -> Rookie | K20: {=IF(OR(ISBLANK(RosterPlan25[[#This Row],[player_id]]),NOT(ISNA(MATCH(RosterPlan25[[#This Row],[player_id]],INDIRECT("Rookies" & SEASON &"[player_id]"),0)))), SEASON, _xlfn.IFNA(INDEX(Draft2025[Contract Year],RosterPlan25[[#This Row],[DraftIndex]]),IF(IN_SEASON,SEASON,SEASON-1)))} -> 2026 | L20: =IF(_xlfn.IFNA(INDEX(Draft2025[KEEPER],RosterPlan25[[#This Row],[DraftIndex]]),"")="K","Yes","") | M20: {=IF(RosterPlan25[[#This Row],[Contract]]="Rookie", "", IF(_xlfn.IFNA(INDEX(Draft2025[Contract Year],RosterPlan25[[#This Row],[DraftIndex]]),IF(IN_SEASON,SEASON,SEASON-1))+3<SEASON, SEASON, _xlfn.IFNA(INDEX(Draft2025[Contract Year],RosterPlan25[[#This Row],[DraftIndex]]),IF(IN_SEASON,SEASON,SEASON-1))+3))} | N20: =ROUNDDOWN(RosterPlan25[[#This Row],[Optimal $]]*IF(RosterPlan25[[#This Row],[Contract]]="Rookie",0.3,0.15),0) -> 0 | O20: =IF(RosterPlan25[[#This Row],[SOURCE]]="Rookie", INDEX(INDIRECT("Rookies" & SEASON & "[salary]"),MATCH(RosterPlan25[[#This Row],[PLAYER]],INDIRECT("Rookies"& SEASON & "[full_name]"),0)), MAX(RosterPlan25[[#This Row],[$ PREV]] + IF(RAISES_ENABLED,RosterPlan25[[#This Row],[$↑ VAR]],0),1)) -> 4 | P20: =IF(VARG="MANUAL",RosterPlan25[[#This Row],[ManualVARG]],IF(VARG="GOOD",RosterPlan25[[#This Row],[GoodVARG]],"ERR")) -> -3.5900987 | Q20: =_xlfn.IFNA(IF(RosterPlan25[[#This Row],[POS]]="K",0,INDEX(GoodSheets[MG VARG],MATCH(TEXT(RosterPlan25[[#This Row],[player_id]],"0"),GoodSheets[sleeper_id],0))), IF(RosterPlan25[[#This Row],[POS]]="QB",-12,IF(RosterPlan25[[#This Row],[POS]]="RB",-8,IF(RosterPlan25[[#This Row],[POS]]="WR",-8,-5)))) -> -3.5900987 | R20: =_xlfn.IFNA(INDEX(ALL_Athletic[VARG], MATCH(RosterPlan25[[#This Row],[player_id]],ALL_Athletic[SleeperID],0)), IF(RosterPlan25[[#This Row],[POS]]="QB",-12,IF(RosterPlan25[[#This Row],[POS]]="RB",-8,IF(RosterPlan25[[#This Row],[POS]]="WR",-8,-5)))) -> -8 | S20: K | T20: =_xlfn.IFNA(INDEX(Draft2025[Net Keeper Count],RosterPlan25[[#This Row],[DraftIndex]]),0)+IF(RosterPlan25[[#This Row],[KEEPER / RFA]]="K",1,0) -> 1 | U20: =IF(RosterPlan25[[#This Row],[KEEPER / RFA]]="RFA",RosterPlan25[[#This Row],[Pure Inflated $]],"") | V20: =IF(RosterPlan25[[#This Row],[VAR/G]]>0, ROUND(IF(VARG="GOOD",$AG$29,IF(VARG="ATHLETIC",$AH$29,99999999999))*RosterPlan25[[#This Row],[VAR/G]],0), 0) + 1 -> 1 | W20: =RosterPlan25[[#This Row],[Optimal $]]-RosterPlan25[[#This Row],[$ CURR]] -> -3 | X20: =IF(OR(RosterPlan25[[#This Row],[SOURCE]]="Rookie",RosterPlan25[[#This Row],[POS]]="K"),0,RosterPlan25[[#This Row],[VAR/G]]+3.3) -> 0 | Y20: =IF(RosterPlan25[[#This Row],[VAW/G]]>0,ROUND(RosterPlan25[[#This Row],[VAW/G]]*$AG$56,0)+1,1) -> 1 | Z20: =RosterPlan25[[#This Row],[VAWG Market $]]-_xlfn.IFNA(RosterPlan25[[#This Row],[$ CURR]],1) -> -3 | AA20: =IF(RosterPlan25[[#This Row],[VAR/G]]>0,1+ROUND(RosterPlan25[[#This Row],[VAR/G]]*IF(RosterPlan25[[#This Row],[KEEPER / RFA]]="K",($AG$34+RosterPlan25[[#This Row],[$ CURR]]-1)/($AG$23+RosterPlan25[[#This Row],[VAR/G]]),$AG$35),0),1) -> 1 | AB20: =RosterPlan25[[#This Row],[Pure Inflated $]]-RosterPlan25[[#This Row],[$ CURR]] -> -3 | AC20: =INDEX(players[age],MATCH(RosterPlan25[[#This Row],[player_id]],players[sleeper_id],0)) -> 22 | AG20: BEER | AH20: ATH
A21: 13353 | B21: BobbyBaby | C21: Chris Brazzell | D21: =_xlfn.IFNA(MATCH(RosterPlan25[[#This Row],[player_id]],CompositeRoster[sleeper_id],0), MATCH(RosterPlan25[[#This Row],[PLAYER]],CompositeRoster[full_name],0)) -> 20 | E21: =MATCH(RosterPlan25[[#This Row],[player_id]],Draft2025[sleeper_id],0) -> #N/A | F21: =INDEX(CompositeRoster[team],RosterPlan25[[#This Row],[RosterIndex]])&"" -> CAR | G21: =INDEX(CompositeRoster[position],RosterPlan25[[#This Row],[RosterIndex]])&"" -> WR | H21: =INDEX(CompositeRoster[source],RosterPlan25[[#This Row],[RosterIndex]]) -> Rookie | I21: =_xlfn.IFNA(INDEX(Draft2025[PRICE],RosterPlan25[[#This Row],[DraftIndex]]),0) -> 0 | J21: =IF(RosterPlan25[[#This Row],[SOURCE]]="Rookie","Rookie",_xlfn.IFNA(INDEX(Draft2025[Current Contract],RosterPlan25[[#This Row],[DraftIndex]]),"Undrafted")) -> Rookie | K21: {=IF(OR(ISBLANK(RosterPlan25[[#This Row],[player_id]]),NOT(ISNA(MATCH(RosterPlan25[[#This Row],[player_id]],INDIRECT("Rookies" & SEASON &"[player_id]"),0)))), SEASON, _xlfn.IFNA(INDEX(Draft2025[Contract Year],RosterPlan25[[#This Row],[DraftIndex]]),IF(IN_SEASON,SEASON,SEASON-1)))} -> 2026 | L21: =IF(_xlfn.IFNA(INDEX(Draft2025[KEEPER],RosterPlan25[[#This Row],[DraftIndex]]),"")="K","Yes","") | M21: {=IF(RosterPlan25[[#This Row],[Contract]]="Rookie", "", IF(_xlfn.IFNA(INDEX(Draft2025[Contract Year],RosterPlan25[[#This Row],[DraftIndex]]),IF(IN_SEASON,SEASON,SEASON-1))+3<SEASON, SEASON, _xlfn.IFNA(INDEX(Draft2025[Contract Year],RosterPlan25[[#This Row],[DraftIndex]]),IF(IN_SEASON,SEASON,SEASON-1))+3))} | N21: =ROUNDDOWN(RosterPlan25[[#This Row],[Optimal $]]*IF(RosterPlan25[[#This Row],[Contract]]="Rookie",0.3,0.15),0) -> 0 | O21: =IF(RosterPlan25[[#This Row],[SOURCE]]="Rookie", INDEX(INDIRECT("Rookies" & SEASON & "[salary]"),MATCH(RosterPlan25[[#This Row],[PLAYER]],INDIRECT("Rookies"& SEASON & "[full_name]"),0)), MAX(RosterPlan25[[#This Row],[$ PREV]] + IF(RAISES_ENABLED,RosterPlan25[[#This Row],[$↑ VAR]],0),1)) -> 3 | P21: =IF(VARG="MANUAL",RosterPlan25[[#This Row],[ManualVARG]],IF(VARG="GOOD",RosterPlan25[[#This Row],[GoodVARG]],"ERR")) -> -4.351468 | Q21: =_xlfn.IFNA(IF(RosterPlan25[[#This Row],[POS]]="K",0,INDEX(GoodSheets[MG VARG],MATCH(TEXT(RosterPlan25[[#This Row],[player_id]],"0"),GoodSheets[sleeper_id],0))), IF(RosterPlan25[[#This Row],[POS]]="QB",-12,IF(RosterPlan25[[#This Row],[POS]]="RB",-8,IF(RosterPlan25[[#This Row],[POS]]="WR",-8,-5)))) -> -4.351468 | R21: =_xlfn.IFNA(INDEX(ALL_Athletic[VARG], MATCH(RosterPlan25[[#This Row],[player_id]],ALL_Athletic[SleeperID],0)), IF(RosterPlan25[[#This Row],[POS]]="QB",-12,IF(RosterPlan25[[#This Row],[POS]]="RB",-8,IF(RosterPlan25[[#This Row],[POS]]="WR",-8,-5)))) -> -8 | S21: K | T21: =_xlfn.IFNA(INDEX(Draft2025[Net Keeper Count],RosterPlan25[[#This Row],[DraftIndex]]),0)+IF(RosterPlan25[[#This Row],[KEEPER / RFA]]="K",1,0) -> 1 | U21: =IF(RosterPlan25[[#This Row],[KEEPER / RFA]]="RFA",RosterPlan25[[#This Row],[Pure Inflated $]],"") | V21: =IF(RosterPlan25[[#This Row],[VAR/G]]>0, ROUND(IF(VARG="GOOD",$AG$29,IF(VARG="ATHLETIC",$AH$29,99999999999))*RosterPlan25[[#This Row],[VAR/G]],0), 0) + 1 -> 1 | W21: =RosterPlan25[[#This Row],[Optimal $]]-RosterPlan25[[#This Row],[$ CURR]] -> -2 | X21: =IF(OR(RosterPlan25[[#This Row],[SOURCE]]="Rookie",RosterPlan25[[#This Row],[POS]]="K"),0,RosterPlan25[[#This Row],[VAR/G]]+3.3) -> 0 | Y21: =IF(RosterPlan25[[#This Row],[VAW/G]]>0,ROUND(RosterPlan25[[#This Row],[VAW/G]]*$AG$56,0)+1,1) -> 1 | Z21: =RosterPlan25[[#This Row],[VAWG Market $]]-_xlfn.IFNA(RosterPlan25[[#This Row],[$ CURR]],1) -> -2 | AA21: =IF(RosterPlan25[[#This Row],[VAR/G]]>0,1+ROUND(RosterPlan25[[#This Row],[VAR/G]]*IF(RosterPlan25[[#This Row],[KEEPER / RFA]]="K",($AG$34+RosterPlan25[[#This Row],[$ CURR]]-1)/($AG$23+RosterPlan25[[#This Row],[VAR/G]]),$AG$35),0),1) -> 1 | AB21: =RosterPlan25[[#This Row],[Pure Inflated $]]-RosterPlan25[[#This Row],[$ CURR]] -> -2 | AC21: =INDEX(players[age],MATCH(RosterPlan25[[#This Row],[player_id]],players[sleeper_id],0)) -> 22 | AF21: Total VAR/G | AG21: =SUMIFS(GoodSheets[MG VARG],GoodSheets[MG VARG],">0") -> 233.94999 | AH21: =SUMIFS(ALL_Athletic[VARG],ALL_Athletic[VARG],">0") -> 248.39284
A22: 13287 | B22: BobbyBaby | C22: Jeremiyah Love | D22: =_xlfn.IFNA(MATCH(RosterPlan25[[#This Row],[player_id]],CompositeRoster[sleeper_id],0), MATCH(RosterPlan25[[#This Row],[PLAYER]],CompositeRoster[full_name],0)) -> 21 | E22: =MATCH(RosterPlan25[[#This Row],[player_id]],Draft2025[sleeper_id],0) -> #N/A | F22: =INDEX(CompositeRoster[team],RosterPlan25[[#This Row],[RosterIndex]])&"" -> ARI | G22: =INDEX(CompositeRoster[position],RosterPlan25[[#This Row],[RosterIndex]])&"" -> RB | H22: =INDEX(CompositeRoster[source],RosterPlan25[[#This Row],[RosterIndex]]) -> Rookie | I22: =_xlfn.IFNA(INDEX(Draft2025[PRICE],RosterPlan25[[#This Row],[DraftIndex]]),0) -> 0 | J22: =IF(RosterPlan25[[#This Row],[SOURCE]]="Rookie","Rookie",_xlfn.IFNA(INDEX(Draft2025[Current Contract],RosterPlan25[[#This Row],[DraftIndex]]),"Undrafted")) -> Rookie | K22: {=IF(OR(ISBLANK(RosterPlan25[[#This Row],[player_id]]),NOT(ISNA(MATCH(RosterPlan25[[#This Row],[player_id]],INDIRECT("Rookies" & SEASON &"[player_id]"),0)))), SEASON, _xlfn.IFNA(INDEX(Draft2025[Contract Year],RosterPlan25[[#This Row],[DraftIndex]]),IF(IN_SEASON,SEASON,SEASON-1)))} -> 2026 | L22: =IF(_xlfn.IFNA(INDEX(Draft2025[KEEPER],RosterPlan25[[#This Row],[DraftIndex]]),"")="K","Yes","") | M22: {=IF(RosterPlan25[[#This Row],[Contract]]="Rookie", "", IF(_xlfn.IFNA(INDEX(Draft2025[Contract Year],RosterPlan25[[#This Row],[DraftIndex]]),IF(IN_SEASON,SEASON,SEASON-1))+3<SEASON, SEASON, _xlfn.IFNA(INDEX(Draft2025[Contract Year],RosterPlan25[[#This Row],[DraftIndex]]),IF(IN_SEASON,SEASON,SEASON-1))+3))} | N22: =ROUNDDOWN(RosterPlan25[[#This Row],[Optimal $]]*IF(RosterPlan25[[#This Row],[Contract]]="Rookie",0.3,0.15),0) -> 12 | O22: =IF(RosterPlan25[[#This Row],[SOURCE]]="Rookie", INDEX(INDIRECT("Rookies" & SEASON & "[salary]"),MATCH(RosterPlan25[[#This Row],[PLAYER]],INDIRECT("Rookies"& SEASON & "[full_name]"),0)), MAX(RosterPlan25[[#This Row],[$ PREV]] + IF(RAISES_ENABLED,RosterPlan25[[#This Row],[$↑ VAR]],0),1)) -> 6 | P22: =IF(VARG="MANUAL",RosterPlan25[[#This Row],[ManualVARG]],IF(VARG="GOOD",RosterPlan25[[#This Row],[GoodVARG]],"ERR")) -> 3.4984182 | Q22: =_xlfn.IFNA(IF(RosterPlan25[[#This Row],[POS]]="K",0,INDEX(GoodSheets[MG VARG],MATCH(TEXT(RosterPlan25[[#This Row],[player_id]],"0"),GoodSheets[sleeper_id],0))), IF(RosterPlan25[[#This Row],[POS]]="QB",-12,IF(RosterPlan25[[#This Row],[POS]]="RB",-8,IF(RosterPlan25[[#This Row],[POS]]="WR",-8,-5)))) -> 3.4984182 | R22: =_xlfn.IFNA(INDEX(ALL_Athletic[VARG], MATCH(RosterPlan25[[#This Row],[player_id]],ALL_Athletic[SleeperID],0)), IF(RosterPlan25[[#This Row],[POS]]="QB",-12,IF(RosterPlan25[[#This Row],[POS]]="RB",-8,IF(RosterPlan25[[#This Row],[POS]]="WR",-8,-5)))) -> -8 | S22: K | T22: =_xlfn.IFNA(INDEX(Draft2025[Net Keeper Count],RosterPlan25[[#This Row],[DraftIndex]]),0)+IF(RosterPlan25[[#This Row],[KEEPER / RFA]]="K",1,0) -> 1 | U22: =IF(RosterPlan25[[#This Row],[KEEPER / RFA]]="RFA",RosterPlan25[[#This Row],[Pure Inflated $]],"") | V22: =IF(RosterPlan25[[#This Row],[VAR/G]]>0, ROUND(IF(VARG="GOOD",$AG$29,IF(VARG="ATHLETIC",$AH$29,99999999999))*RosterPlan25[[#This Row],[VAR/G]],0), 0) + 1 -> 42 | W22: =RosterPlan25[[#This Row],[Optimal $]]-RosterPlan25[[#This Row],[$ CURR]] -> 36 | X22: =IF(OR(RosterPlan25[[#This Row],[SOURCE]]="Rookie",RosterPlan25[[#This Row],[POS]]="K"),0,RosterPlan25[[#This Row],[VAR/G]]+3.3) -> 0 | Y22: =IF(RosterPlan25[[#This Row],[VAW/G]]>0,ROUND(RosterPlan25[[#This Row],[VAW/G]]*$AG$56,0)+1,1) -> 1 | Z22: =RosterPlan25[[#This Row],[VAWG Market $]]-_xlfn.IFNA(RosterPlan25[[#This Row],[$ CURR]],1) -> -5 | AA22: =IF(RosterPlan25[[#This Row],[VAR/G]]>0,1+ROUND(RosterPlan25[[#This Row],[VAR/G]]*IF(RosterPlan25[[#This Row],[KEEPER / RFA]]="K",($AG$34+RosterPlan25[[#This Row],[$ CURR]]-1)/($AG$23+RosterPlan25[[#This Row],[VAR/G]]),$AG$35),0),1) -> 55 | AB22: =RosterPlan25[[#This Row],[Pure Inflated $]]-RosterPlan25[[#This Row],[$ CURR]] -> 49 | AC22: =INDEX(players[age],MATCH(RosterPlan25[[#This Row],[player_id]],players[sleeper_id],0)) -> 21 | AF22: Total Keeper VAR/G | AG22: =AN12 -> 179.66451 | AH22: =AN12 -> 179.66451
A23: 11579 | B23: cthultu | C23: Audric Estime | D23: =_xlfn.IFNA(MATCH(RosterPlan25[[#This Row],[player_id]],CompositeRoster[sleeper_id],0), MATCH(RosterPlan25[[#This Row],[PLAYER]],CompositeRoster[full_name],0)) -> 22 | E23: =MATCH(RosterPlan25[[#This Row],[player_id]],Draft2025[sleeper_id],0) -> #N/A | F23: =INDEX(CompositeRoster[team],RosterPlan25[[#This Row],[RosterIndex]])&"" -> NO | G23: =INDEX(CompositeRoster[position],RosterPlan25[[#This Row],[RosterIndex]])&"" -> RB | H23: =INDEX(CompositeRoster[source],RosterPlan25[[#This Row],[RosterIndex]]) -> Roster | I23: =_xlfn.IFNA(INDEX(Draft2025[PRICE],RosterPlan25[[#This Row],[DraftIndex]]),0) -> 0 | J23: =IF(RosterPlan25[[#This Row],[SOURCE]]="Rookie","Rookie",_xlfn.IFNA(INDEX(Draft2025[Current Contract],RosterPlan25[[#This Row],[DraftIndex]]),"Undrafted")) -> Undrafted | K23: {=IF(OR(ISBLANK(RosterPlan25[[#This Row],[player_id]]),NOT(ISNA(MATCH(RosterPlan25[[#This Row],[player_id]],INDIRECT("Rookies" & SEASON &"[player_id]"),0)))), SEASON, _xlfn.IFNA(INDEX(Draft2025[Contract Year],RosterPlan25[[#This Row],[DraftIndex]]),IF(IN_SEASON,SEASON,SEASON-1)))} -> 2025 | L23: =IF(_xlfn.IFNA(INDEX(Draft2025[KEEPER],RosterPlan25[[#This Row],[DraftIndex]]),"")="K","Yes","") | M23: {=IF(RosterPlan25[[#This Row],[Contract]]="Rookie", "", IF(_xlfn.IFNA(INDEX(Draft2025[Contract Year],RosterPlan25[[#This Row],[DraftIndex]]),IF(IN_SEASON,SEASON,SEASON-1))+3<SEASON, SEASON, _xlfn.IFNA(INDEX(Draft2025[Contract Year],RosterPlan25[[#This Row],[DraftIndex]]),IF(IN_SEASON,SEASON,SEASON-1))+3))} -> 2028 | N23: =ROUNDDOWN(RosterPlan25[[#This Row],[Optimal $]]*IF(RosterPlan25[[#This Row],[Contract]]="Rookie",0.3,0.15),0) -> 0 | O23: =IF(RosterPlan25[[#This Row],[SOURCE]]="Rookie", INDEX(INDIRECT("Rookies" & SEASON & "[salary]"),MATCH(RosterPlan25[[#This Row],[PLAYER]],INDIRECT("Rookies"& SEASON & "[full_name]"),0)), MAX(RosterPlan25[[#This Row],[$ PREV]] + IF(RAISES_ENABLED,RosterPlan25[[#This Row],[$↑ VAR]],0),1)) -> 1 | P23: =IF(VARG="MANUAL",RosterPlan25[[#This Row],[ManualVARG]],IF(VARG="GOOD",RosterPlan25[[#This Row],[GoodVARG]],"ERR")) -> -5.8572707 | Q23: =_xlfn.IFNA(IF(RosterPlan25[[#This Row],[POS]]="K",0,INDEX(GoodSheets[MG VARG],MATCH(TEXT(RosterPlan25[[#This Row],[player_id]],"0"),GoodSheets[sleeper_id],0))), IF(RosterPlan25[[#This Row],[POS]]="QB",-12,IF(RosterPlan25[[#This Row],[POS]]="RB",-8,IF(RosterPlan25[[#This Row],[POS]]="WR",-8,-5)))) -> -5.8572707 | R23: =_xlfn.IFNA(INDEX(ALL_Athletic[VARG], MATCH(RosterPlan25[[#This Row],[player_id]],ALL_Athletic[SleeperID],0)), IF(RosterPlan25[[#This Row],[POS]]="QB",-12,IF(RosterPlan25[[#This Row],[POS]]="RB",-8,IF(RosterPlan25[[#This Row],[POS]]="WR",-8,-5)))) -> -8 | S23: K | T23: =_xlfn.IFNA(INDEX(Draft2025[Net Keeper Count],RosterPlan25[[#This Row],[DraftIndex]]),0)+IF(RosterPlan25[[#This Row],[KEEPER / RFA]]="K",1,0) -> 1 | U23: =IF(RosterPlan25[[#This Row],[KEEPER / RFA]]="RFA",RosterPlan25[[#This Row],[Pure Inflated $]],"") | V23: =IF(RosterPlan25[[#This Row],[VAR/G]]>0, ROUND(IF(VARG="GOOD",$AG$29,IF(VARG="ATHLETIC",$AH$29,99999999999))*RosterPlan25[[#This Row],[VAR/G]],0), 0) + 1 -> 1 | W23: =RosterPlan25[[#This Row],[Optimal $]]-RosterPlan25[[#This Row],[$ CURR]] -> 0 | X23: =IF(OR(RosterPlan25[[#This Row],[SOURCE]]="Rookie",RosterPlan25[[#This Row],[POS]]="K"),0,RosterPlan25[[#This Row],[VAR/G]]+3.3) -> -2.5572707 | Y23: =IF(RosterPlan25[[#This Row],[VAW/G]]>0,ROUND(RosterPlan25[[#This Row],[VAW/G]]*$AG$56,0)+1,1) -> 1 | Z23: =RosterPlan25[[#This Row],[VAWG Market $]]-_xlfn.IFNA(RosterPlan25[[#This Row],[$ CURR]],1) -> 0 | AA23: =IF(RosterPlan25[[#This Row],[VAR/G]]>0,1+ROUND(RosterPlan25[[#This Row],[VAR/G]]*IF(RosterPlan25[[#This Row],[KEEPER / RFA]]="K",($AG$34+RosterPlan25[[#This Row],[$ CURR]]-1)/($AG$23+RosterPlan25[[#This Row],[VAR/G]]),$AG$35),0),1) -> 1 | AB23: =RosterPlan25[[#This Row],[Pure Inflated $]]-RosterPlan25[[#This Row],[$ CURR]] -> 0 | AC23: =INDEX(players[age],MATCH(RosterPlan25[[#This Row],[player_id]],players[sleeper_id],0)) -> 22 | AF23: Total Free Agent VAR/G | AG23: =AG21-AG22 -> 54.285485 | AH23: =AH21-AH22 -> 68.728331
A24: 5001 | B24: cthultu | C24: Dalton Schultz | D24: =_xlfn.IFNA(MATCH(RosterPlan25[[#This Row],[player_id]],CompositeRoster[sleeper_id],0), MATCH(RosterPlan25[[#This Row],[PLAYER]],CompositeRoster[full_name],0)) -> 23 | E24: =MATCH(RosterPlan25[[#This Row],[player_id]],Draft2025[sleeper_id],0) -> #N/A | F24: =INDEX(CompositeRoster[team],RosterPlan25[[#This Row],[RosterIndex]])&"" -> HOU | G24: =INDEX(CompositeRoster[position],RosterPlan25[[#This Row],[RosterIndex]])&"" -> TE | H24: =INDEX(CompositeRoster[source],RosterPlan25[[#This Row],[RosterIndex]]) -> Roster | I24: =_xlfn.IFNA(INDEX(Draft2025[PRICE],RosterPlan25[[#This Row],[DraftIndex]]),0) -> 0 | J24: =IF(RosterPlan25[[#This Row],[SOURCE]]="Rookie","Rookie",_xlfn.IFNA(INDEX(Draft2025[Current Contract],RosterPlan25[[#This Row],[DraftIndex]]),"Undrafted")) -> Undrafted | K24: {=IF(OR(ISBLANK(RosterPlan25[[#This Row],[player_id]]),NOT(ISNA(MATCH(RosterPlan25[[#This Row],[player_id]],INDIRECT("Rookies" & SEASON &"[player_id]"),0)))), SEASON, _xlfn.IFNA(INDEX(Draft2025[Contract Year],RosterPlan25[[#This Row],[DraftIndex]]),IF(IN_SEASON,SEASON,SEASON-1)))} -> 2025 | L24: =IF(_xlfn.IFNA(INDEX(Draft2025[KEEPER],RosterPlan25[[#This Row],[DraftIndex]]),"")="K","Yes","") | M24: {=IF(RosterPlan25[[#This Row],[Contract]]="Rookie", "", IF(_xlfn.IFNA(INDEX(Draft2025[Contract Year],RosterPlan25[[#This Row],[DraftIndex]]),IF(IN_SEASON,SEASON,SEASON-1))+3<SEASON, SEASON, _xlfn.IFNA(INDEX(Draft2025[Contract Year],RosterPlan25[[#This Row],[DraftIndex]]),IF(IN_SEASON,SEASON,SEASON-1))+3))} -> 2028 | N24: =ROUNDDOWN(RosterPlan25[[#This Row],[Optimal $]]*IF(RosterPlan25[[#This Row],[Contract]]="Rookie",0.3,0.15),0) -> 0 | O24: =IF(RosterPlan25[[#This Row],[SOURCE]]="Rookie", INDEX(INDIRECT("Rookies" & SEASON & "[salary]"),MATCH(RosterPlan25[[#This Row],[PLAYER]],INDIRECT("Rookies"& SEASON & "[full_name]"),0)), MAX(RosterPlan25[[#This Row],[$ PREV]] + IF(RAISES_ENABLED,RosterPlan25[[#This Row],[$↑ VAR]],0),1)) -> 1 | P24: =IF(VARG="MANUAL",RosterPlan25[[#This Row],[ManualVARG]],IF(VARG="GOOD",RosterPlan25[[#This Row],[GoodVARG]],"ERR")) -> -0.14177505 | Q24: =_xlfn.IFNA(IF(RosterPlan25[[#This Row],[POS]]="K",0,INDEX(GoodSheets[MG VARG],MATCH(TEXT(RosterPlan25[[#This Row],[player_id]],"0"),GoodSheets[sleeper_id],0))), IF(RosterPlan25[[#This Row],[POS]]="QB",-12,IF(RosterPlan25[[#This Row],[POS]]="RB",-8,IF(RosterPlan25[[#This Row],[POS]]="WR",-8,-5)))) -> -0.14177505 | R24: =_xlfn.IFNA(INDEX(ALL_Athletic[VARG], MATCH(RosterPlan25[[#This Row],[player_id]],ALL_Athletic[SleeperID],0)), IF(RosterPlan25[[#This Row],[POS]]="QB",-12,IF(RosterPlan25[[#This Row],[POS]]="RB",-8,IF(RosterPlan25[[#This Row],[POS]]="WR",-8,-5)))) -> 0.35937774 | S24: K | T24: =_xlfn.IFNA(INDEX(Draft2025[Net Keeper Count],RosterPlan25[[#This Row],[DraftIndex]]),0)+IF(RosterPlan25[[#This Row],[KEEPER / RFA]]="K",1,0) -> 1 | U24: =IF(RosterPlan25[[#This Row],[KEEPER / RFA]]="RFA",RosterPlan25[[#This Row],[Pure Inflated $]],"") | V24: =IF(RosterPlan25[[#This Row],[VAR/G]]>0, ROUND(IF(VARG="GOOD",$AG$29,IF(VARG="ATHLETIC",$AH$29,99999999999))*RosterPlan25[[#This Row],[VAR/G]],0), 0) + 1 -> 1 | W24: =RosterPlan25[[#This Row],[Optimal $]]-RosterPlan25[[#This Row],[$ CURR]] -> 0 | X24: =IF(OR(RosterPlan25[[#This Row],[SOURCE]]="Rookie",RosterPlan25[[#This Row],[POS]]="K"),0,RosterPlan25[[#This Row],[VAR/G]]+3.3) -> 3.158225 | Y24: =IF(RosterPlan25[[#This Row],[VAW/G]]>0,ROUND(RosterPlan25[[#This Row],[VAW/G]]*$AG$56,0)+1,1) -> 53 | Z24: =RosterPlan25[[#This Row],[VAWG Market $]]-_xlfn.IFNA(RosterPlan25[[#This Row],[$ CURR]],1) -> 52 | AA24: =IF(RosterPlan25[[#This Row],[VAR/G]]>0,1+ROUND(RosterPlan25[[#This Row],[VAR/G]]*IF(RosterPlan25[[#This Row],[KEEPER / RFA]]="K",($AG$34+RosterPlan25[[#This Row],[$ CURR]]-1)/($AG$23+RosterPlan25[[#This Row],[VAR/G]]),$AG$35),0),1) -> 1 | AB24: =RosterPlan25[[#This Row],[Pure Inflated $]]-RosterPlan25[[#This Row],[$ CURR]] -> 0 | AC24: =INDEX(players[age],MATCH(RosterPlan25[[#This Row],[player_id]],players[sleeper_id],0)) -> 30 | AF24: Total Rookie VAR/G | AG24: =SUMIFS(GoodSheets[MG VARG],GoodSheets[MG VARG],">0",GoodSheets[years_exp],"0") -> 5.9922847 | AH24: =SUMIFS(ALL_Athletic[VARG],ALL_Athletic[VARG],">0",ALL_Athletic[Years Exp],"=0") -> 0
A25: 7090 | B25: cthultu | C25: Darnell Mooney | D25: =_xlfn.IFNA(MATCH(RosterPlan25[[#This Row],[player_id]],CompositeRoster[sleeper_id],0), MATCH(RosterPlan25[[#This Row],[PLAYER]],CompositeRoster[full_name],0)) -> 24 | E25: =MATCH(RosterPlan25[[#This Row],[player_id]],Draft2025[sleeper_id],0) -> 33 | F25: =INDEX(CompositeRoster[team],RosterPlan25[[#This Row],[RosterIndex]])&"" -> NYG | G25: =INDEX(CompositeRoster[position],RosterPlan25[[#This Row],[RosterIndex]])&"" -> WR | H25: =INDEX(CompositeRoster[source],RosterPlan25[[#This Row],[RosterIndex]]) -> Roster | I25: =_xlfn.IFNA(INDEX(Draft2025[PRICE],RosterPlan25[[#This Row],[DraftIndex]]),0) -> 3 | J25: =IF(RosterPlan25[[#This Row],[SOURCE]]="Rookie","Rookie",_xlfn.IFNA(INDEX(Draft2025[Current Contract],RosterPlan25[[#This Row],[DraftIndex]]),"Undrafted")) -> Auction | K25: {=IF(OR(ISBLANK(RosterPlan25[[#This Row],[player_id]]),NOT(ISNA(MATCH(RosterPlan25[[#This Row],[player_id]],INDIRECT("Rookies" & SEASON &"[player_id]"),0)))), SEASON, _xlfn.IFNA(INDEX(Draft2025[Contract Year],RosterPlan25[[#This Row],[DraftIndex]]),IF(IN_SEASON,SEASON,SEASON-1)))} -> 2024 | L25: =IF(_xlfn.IFNA(INDEX(Draft2025[KEEPER],RosterPlan25[[#This Row],[DraftIndex]]),"")="K","Yes","") -> Yes | M25: {=IF(RosterPlan25[[#This Row],[Contract]]="Rookie", "", IF(_xlfn.IFNA(INDEX(Draft2025[Contract Year],RosterPlan25[[#This Row],[DraftIndex]]),IF(IN_SEASON,SEASON,SEASON-1))+3<SEASON, SEASON, _xlfn.IFNA(INDEX(Draft2025[Contract Year],RosterPlan25[[#This Row],[DraftIndex]]),IF(IN_SEASON,SEASON,SEASON-1))+3))} -> 2027 | N25: =ROUNDDOWN(RosterPlan25[[#This Row],[Optimal $]]*IF(RosterPlan25[[#This Row],[Contract]]="Rookie",0.3,0.15),0) -> 0 | O25: =IF(RosterPlan25[[#This Row],[SOURCE]]="Rookie", INDEX(INDIRECT("Rookies" & SEASON & "[salary]"),MATCH(RosterPlan25[[#This Row],[PLAYER]],INDIRECT("Rookies"& SEASON & "[full_name]"),0)), MAX(RosterPlan25[[#This Row],[$ PREV]] + IF(RAISES_ENABLED,RosterPlan25[[#This Row],[$↑ VAR]],0),1)) -> 3 | P25: =IF(VARG="MANUAL",RosterPlan25[[#This Row],[ManualVARG]],IF(VARG="GOOD",RosterPlan25[[#This Row],[GoodVARG]],"ERR")) -> -3.0238252 | Q25: =_xlfn.IFNA(IF(RosterPlan25[[#This Row],[POS]]="K",0,INDEX(GoodSheets[MG VARG],MATCH(TEXT(RosterPlan25[[#This Row],[player_id]],"0"),GoodSheets[sleeper_id],0))), IF(RosterPlan25[[#This Row],[POS]]="QB",-12,IF(RosterPlan25[[#This Row],[POS]]="RB",-8,IF(RosterPlan25[[#This Row],[POS]]="WR",-8,-5)))) -> -3.0238252 | R25: =_xlfn.IFNA(INDEX(ALL_Athletic[VARG], MATCH(RosterPlan25[[#This Row],[player_id]],ALL_Athletic[SleeperID],0)), IF(RosterPlan25[[#This Row],[POS]]="QB",-12,IF(RosterPlan25[[#This Row],[POS]]="RB",-8,IF(RosterPlan25[[#This Row],[POS]]="WR",-8,-5)))) -> -0.83198711 | S25: K | T25: =_xlfn.IFNA(INDEX(Draft2025[Net Keeper Count],RosterPlan25[[#This Row],[DraftIndex]]),0)+IF(RosterPlan25[[#This Row],[KEEPER / RFA]]="K",1,0) -> 2 | U25: =IF(RosterPlan25[[#This Row],[KEEPER / RFA]]="RFA",RosterPlan25[[#This Row],[Pure Inflated $]],"") | V25: =IF(RosterPlan25[[#This Row],[VAR/G]]>0, ROUND(IF(VARG="GOOD",$AG$29,IF(VARG="ATHLETIC",$AH$29,99999999999))*RosterPlan25[[#This Row],[VAR/G]],0), 0) + 1 -> 1 | W25: =RosterPlan25[[#This Row],[Optimal $]]-RosterPlan25[[#This Row],[$ CURR]] -> -2 | X25: =IF(OR(RosterPlan25[[#This Row],[SOURCE]]="Rookie",RosterPlan25[[#This Row],[POS]]="K"),0,RosterPlan25[[#This Row],[VAR/G]]+3.3) -> 0.27617475 | Y25: =IF(RosterPlan25[[#This Row],[VAW/G]]>0,ROUND(RosterPlan25[[#This Row],[VAW/G]]*$AG$56,0)+1,1) -> 6 | Z25: =RosterPlan25[[#This Row],[VAWG Market $]]-_xlfn.IFNA(RosterPlan25[[#This Row],[$ CURR]],1) -> 3 | AA25: =IF(RosterPlan25[[#This Row],[VAR/G]]>0,1+ROUND(RosterPlan25[[#This Row],[VAR/G]]*IF(RosterPlan25[[#This Row],[KEEPER / RFA]]="K",($AG$34+RosterPlan25[[#This Row],[$ CURR]]-1)/($AG$23+RosterPlan25[[#This Row],[VAR/G]]),$AG$35),0),1) -> 1 | AB25: =RosterPlan25[[#This Row],[Pure Inflated $]]-RosterPlan25[[#This Row],[$ CURR]] -> -2 | AC25: =INDEX(players[age],MATCH(RosterPlan25[[#This Row],[player_id]],players[sleeper_id],0)) -> 28 | AF25: Total Non Rookie Free Agent VAR/G | AG25: =AG23 -> 54.285485 | AH25: =AH23 -> 68.728331
A26: 12476 | B26: cthultu | C26: Devin Neal | D26: =_xlfn.IFNA(MATCH(RosterPlan25[[#This Row],[player_id]],CompositeRoster[sleeper_id],0), MATCH(RosterPlan25[[#This Row],[PLAYER]],CompositeRoster[full_name],0)) -> 25 | E26: =MATCH(RosterPlan25[[#This Row],[player_id]],Draft2025[sleeper_id],0) -> 43 | F26: =INDEX(CompositeRoster[team],RosterPlan25[[#This Row],[RosterIndex]])&"" -> NO | G26: =INDEX(CompositeRoster[position],RosterPlan25[[#This Row],[RosterIndex]])&"" -> RB | H26: =INDEX(CompositeRoster[source],RosterPlan25[[#This Row],[RosterIndex]]) -> Roster | I26: =_xlfn.IFNA(INDEX(Draft2025[PRICE],RosterPlan25[[#This Row],[DraftIndex]]),0) -> 3 | J26: =IF(RosterPlan25[[#This Row],[SOURCE]]="Rookie","Rookie",_xlfn.IFNA(INDEX(Draft2025[Current Contract],RosterPlan25[[#This Row],[DraftIndex]]),"Undrafted")) -> Rookie | K26: {=IF(OR(ISBLANK(RosterPlan25[[#This Row],[player_id]]),NOT(ISNA(MATCH(RosterPlan25[[#This Row],[player_id]],INDIRECT("Rookies" & SEASON &"[player_id]"),0)))), SEASON, _xlfn.IFNA(INDEX(Draft2025[Contract Year],RosterPlan25[[#This Row],[DraftIndex]]),IF(IN_SEASON,SEASON,SEASON-1)))} -> 2025 | L26: =IF(_xlfn.IFNA(INDEX(Draft2025[KEEPER],RosterPlan25[[#This Row],[DraftIndex]]),"")="K","Yes","") | M26: {=IF(RosterPlan25[[#This Row],[Contract]]="Rookie", "", IF(_xlfn.IFNA(INDEX(Draft2025[Contract Year],RosterPlan25[[#This Row],[DraftIndex]]),IF(IN_SEASON,SEASON,SEASON-1))+3<SEASON, SEASON, _xlfn.IFNA(INDEX(Draft2025[Contract Year],RosterPlan25[[#This Row],[DraftIndex]]),IF(IN_SEASON,SEASON,SEASON-1))+3))} | N26: =ROUNDDOWN(RosterPlan25[[#This Row],[Optimal $]]*IF(RosterPlan25[[#This Row],[Contract]]="Rookie",0.3,0.15),0) -> 0 | O26: =IF(RosterPlan25[[#This Row],[SOURCE]]="Rookie", INDEX(INDIRECT("Rookies" & SEASON & "[salary]"),MATCH(RosterPlan25[[#This Row],[PLAYER]],INDIRECT("Rookies"& SEASON & "[full_name]"),0)), MAX(RosterPlan25[[#This Row],[$ PREV]] + IF(RAISES_ENABLED,RosterPlan25[[#This Row],[$↑ VAR]],0),1)) -> 3 | P26: =IF(VARG="MANUAL",RosterPlan25[[#This Row],[ManualVARG]],IF(VARG="GOOD",RosterPlan25[[#This Row],[GoodVARG]],"ERR")) -> -5.5456798 | Q26: =_xlfn.IFNA(IF(RosterPlan25[[#This Row],[POS]]="K",0,INDEX(GoodSheets[MG VARG],MATCH(TEXT(RosterPlan25[[#This Row],[player_id]],"0"),GoodSheets[sleeper_id],0))), IF(RosterPlan25[[#This Row],[POS]]="QB",-12,IF(RosterPlan25[[#This Row],[POS]]="RB",-8,IF(RosterPlan25[[#This Row],[POS]]="WR",-8,-5)))) -> -5.5456798 | R26: =_xlfn.IFNA(INDEX(ALL_Athletic[VARG], MATCH(RosterPlan25[[#This Row],[player_id]],ALL_Athletic[SleeperID],0)), IF(RosterPlan25[[#This Row],[POS]]="QB",-12,IF(RosterPlan25[[#This Row],[POS]]="RB",-8,IF(RosterPlan25[[#This Row],[POS]]="WR",-8,-5)))) -> -8 | S26: K | T26: =_xlfn.IFNA(INDEX(Draft2025[Net Keeper Count],RosterPlan25[[#This Row],[DraftIndex]]),0)+IF(RosterPlan25[[#This Row],[KEEPER / RFA]]="K",1,0) -> 1 | U26: =IF(RosterPlan25[[#This Row],[KEEPER / RFA]]="RFA",RosterPlan25[[#This Row],[Pure Inflated $]],"") | V26: =IF(RosterPlan25[[#This Row],[VAR/G]]>0, ROUND(IF(VARG="GOOD",$AG$29,IF(VARG="ATHLETIC",$AH$29,99999999999))*RosterPlan25[[#This Row],[VAR/G]],0), 0) + 1 -> 1 | W26: =RosterPlan25[[#This Row],[Optimal $]]-RosterPlan25[[#This Row],[$ CURR]] -> -2 | X26: =IF(OR(RosterPlan25[[#This Row],[SOURCE]]="Rookie",RosterPlan25[[#This Row],[POS]]="K"),0,RosterPlan25[[#This Row],[VAR/G]]+3.3) -> -2.2456798 | Y26: =IF(RosterPlan25[[#This Row],[VAW/G]]>0,ROUND(RosterPlan25[[#This Row],[VAW/G]]*$AG$56,0)+1,1) -> 1 | Z26: =RosterPlan25[[#This Row],[VAWG Market $]]-_xlfn.IFNA(RosterPlan25[[#This Row],[$ CURR]],1) -> -2 | AA26: =IF(RosterPlan25[[#This Row],[VAR/G]]>0,1+ROUND(RosterPlan25[[#This Row],[VAR/G]]*IF(RosterPlan25[[#This Row],[KEEPER / RFA]]="K",($AG$34+RosterPlan25[[#This Row],[$ CURR]]-1)/($AG$23+RosterPlan25[[#This Row],[VAR/G]]),$AG$35),0),1) -> 1 | AB26: =RosterPlan25[[#This Row],[Pure Inflated $]]-RosterPlan25[[#This Row],[$ CURR]] -> -2 | AC26: =INDEX(players[age],MATCH(RosterPlan25[[#This Row],[player_id]],players[sleeper_id],0)) -> 22 | AF26: Total Salary Cap | AG26: =3000-AL12 -> 2998 | AH26: 3000
A27: 11199 | B27: cthultu | C27: Emari Demercado | D27: =_xlfn.IFNA(MATCH(RosterPlan25[[#This Row],[player_id]],CompositeRoster[sleeper_id],0), MATCH(RosterPlan25[[#This Row],[PLAYER]],CompositeRoster[full_name],0)) -> 26 | E27: =MATCH(RosterPlan25[[#This Row],[player_id]],Draft2025[sleeper_id],0) -> #N/A | F27: =INDEX(CompositeRoster[team],RosterPlan25[[#This Row],[RosterIndex]])&"" -> KC | G27: =INDEX(CompositeRoster[position],RosterPlan25[[#This Row],[RosterIndex]])&"" -> RB | H27: =INDEX(CompositeRoster[source],RosterPlan25[[#This Row],[RosterIndex]]) -> Roster | I27: =_xlfn.IFNA(INDEX(Draft2025[PRICE],RosterPlan25[[#This Row],[DraftIndex]]),0) -> 0 | J27: =IF(RosterPlan25[[#This Row],[SOURCE]]="Rookie","Rookie",_xlfn.IFNA(INDEX(Draft2025[Current Contract],RosterPlan25[[#This Row],[DraftIndex]]),"Undrafted")) -> Undrafted | K27: {=IF(OR(ISBLANK(RosterPlan25[[#This Row],[player_id]]),NOT(ISNA(MATCH(RosterPlan25[[#This Row],[player_id]],INDIRECT("Rookies" & SEASON &"[player_id]"),0)))), SEASON, _xlfn.IFNA(INDEX(Draft2025[Contract Year],RosterPlan25[[#This Row],[DraftIndex]]),IF(IN_SEASON,SEASON,SEASON-1)))} -> 2025 | L27: =IF(_xlfn.IFNA(INDEX(Draft2025[KEEPER],RosterPlan25[[#This Row],[DraftIndex]]),"")="K","Yes","") | M27: {=IF(RosterPlan25[[#This Row],[Contract]]="Rookie", "", IF(_xlfn.IFNA(INDEX(Draft2025[Contract Year],RosterPlan25[[#This Row],[DraftIndex]]),IF(IN_SEASON,SEASON,SEASON-1))+3<SEASON, SEASON, _xlfn.IFNA(INDEX(Draft2025[Contract Year],RosterPlan25[[#This Row],[DraftIndex]]),IF(IN_SEASON,SEASON,SEASON-1))+3))} -> 2028 | N27: =ROUNDDOWN(RosterPlan25[[#This Row],[Optimal $]]*IF(RosterPlan25[[#This Row],[Contract]]="Rookie",0.3,0.15),0) -> 0 | O27: =IF(RosterPlan25[[#This Row],[SOURCE]]="Rookie", INDEX(INDIRECT("Rookies" & SEASON & "[salary]"),MATCH(RosterPlan25[[#This Row],[PLAYER]],INDIRECT("Rookies"& SEASON & "[full_name]"),0)), MAX(RosterPlan25[[#This Row],[$ PREV]] + IF(RAISES_ENABLED,RosterPlan25[[#This Row],[$↑ VAR]],0),1)) -> 1 | P27: =IF(VARG="MANUAL",RosterPlan25[[#This Row],[ManualVARG]],IF(VARG="GOOD",RosterPlan25[[#This Row],[GoodVARG]],"ERR")) -> -4.1910056 | Q27: =_xlfn.IFNA(IF(RosterPlan25[[#This Row],[POS]]="K",0,INDEX(GoodSheets[MG VARG],MATCH(TEXT(RosterPlan25[[#This Row],[player_id]],"0"),GoodSheets[sleeper_id],0))), IF(RosterPlan25[[#This Row],[POS]]="QB",-12,IF(RosterPlan25[[#This Row],[POS]]="RB",-8,IF(RosterPlan25[[#This Row],[POS]]="WR",-8,-5)))) -> -4.1910056 | R27: =_xlfn.IFNA(INDEX(ALL_Athletic[VARG], MATCH(RosterPlan25[[#This Row],[player_id]],ALL_Athletic[SleeperID],0)), IF(RosterPlan25[[#This Row],[POS]]="QB",-12,IF(RosterPlan25[[#This Row],[POS]]="RB",-8,IF(RosterPlan25[[#This Row],[POS]]="WR",-8,-5)))) -> -8 | S27: K | T27: =_xlfn.IFNA(INDEX(Draft2025[Net Keeper Count],RosterPlan25[[#This Row],[DraftIndex]]),0)+IF(RosterPlan25[[#This Row],[KEEPER / RFA]]="K",1,0) -> 1 | U27: =IF(RosterPlan25[[#This Row],[KEEPER / RFA]]="RFA",RosterPlan25[[#This Row],[Pure Inflated $]],"") | V27: =IF(RosterPlan25[[#This Row],[VAR/G]]>0, ROUND(IF(VARG="GOOD",$AG$29,IF(VARG="ATHLETIC",$AH$29,99999999999))*RosterPlan25[[#This Row],[VAR/G]],0), 0) + 1 -> 1 | W27: =RosterPlan25[[#This Row],[Optimal $]]-RosterPlan25[[#This Row],[$ CURR]] -> 0 | X27: =IF(OR(RosterPlan25[[#This Row],[SOURCE]]="Rookie",RosterPlan25[[#This Row],[POS]]="K"),0,RosterPlan25[[#This Row],[VAR/G]]+3.3) -> -0.89100561 | Y27: =IF(RosterPlan25[[#This Row],[VAW/G]]>0,ROUND(RosterPlan25[[#This Row],[VAW/G]]*$AG$56,0)+1,1) -> 1 | Z27: =RosterPlan25[[#This Row],[VAWG Market $]]-_xlfn.IFNA(RosterPlan25[[#This Row],[$ CURR]],1) -> 0 | AA27: =IF(RosterPlan25[[#This Row],[VAR/G]]>0,1+ROUND(RosterPlan25[[#This Row],[VAR/G]]*IF(RosterPlan25[[#This Row],[KEEPER / RFA]]="K",($AG$34+RosterPlan25[[#This Row],[$ CURR]]-1)/($AG$23+RosterPlan25[[#This Row],[VAR/G]]),$AG$35),0),1) -> 1 | AB27: =RosterPlan25[[#This Row],[Pure Inflated $]]-RosterPlan25[[#This Row],[$ CURR]] -> 0 | AC27: =INDEX(players[age],MATCH(RosterPlan25[[#This Row],[player_id]],players[sleeper_id],0)) -> 27 | AF27: Keeper Salary | AG27: =AG12 -> 2073 | AH27: =AG12 -> 2073
A28: 8146 | B28: cthultu | C28: Garrett Wilson | D28: =_xlfn.IFNA(MATCH(RosterPlan25[[#This Row],[player_id]],CompositeRoster[sleeper_id],0), MATCH(RosterPlan25[[#This Row],[PLAYER]],CompositeRoster[full_name],0)) -> 27 | E28: =MATCH(RosterPlan25[[#This Row],[player_id]],Draft2025[sleeper_id],0) -> 34 | F28: =INDEX(CompositeRoster[team],RosterPlan25[[#This Row],[RosterIndex]])&"" -> NYJ | G28: =INDEX(CompositeRoster[position],RosterPlan25[[#This Row],[RosterIndex]])&"" -> WR | H28: =INDEX(CompositeRoster[source],RosterPlan25[[#This Row],[RosterIndex]]) -> Roster | I28: =_xlfn.IFNA(INDEX(Draft2025[PRICE],RosterPlan25[[#This Row],[DraftIndex]]),0) -> 26 | J28: =IF(RosterPlan25[[#This Row],[SOURCE]]="Rookie","Rookie",_xlfn.IFNA(INDEX(Draft2025[Current Contract],RosterPlan25[[#This Row],[DraftIndex]]),"Undrafted")) -> Rookie | K28: {=IF(OR(ISBLANK(RosterPlan25[[#This Row],[player_id]]),NOT(ISNA(MATCH(RosterPlan25[[#This Row],[player_id]],INDIRECT("Rookies" & SEASON &"[player_id]"),0)))), SEASON, _xlfn.IFNA(INDEX(Draft2025[Contract Year],RosterPlan25[[#This Row],[DraftIndex]]),IF(IN_SEASON,SEASON,SEASON-1)))} -> 2022 | L28: =IF(_xlfn.IFNA(INDEX(Draft2025[KEEPER],RosterPlan25[[#This Row],[DraftIndex]]),"")="K","Yes","") -> Yes | M28: {=IF(RosterPlan25[[#This Row],[Contract]]="Rookie", "", IF(_xlfn.IFNA(INDEX(Draft2025[Contract Year],RosterPlan25[[#This Row],[DraftIndex]]),IF(IN_SEASON,SEASON,SEASON-1))+3<SEASON, SEASON, _xlfn.IFNA(INDEX(Draft2025[Contract Year],RosterPlan25[[#This Row],[DraftIndex]]),IF(IN_SEASON,SEASON,SEASON-1))+3))} | N28: =ROUNDDOWN(RosterPlan25[[#This Row],[Optimal $]]*IF(RosterPlan25[[#This Row],[Contract]]="Rookie",0.3,0.15),0) -> 6 | O28: =IF(RosterPlan25[[#This Row],[SOURCE]]="Rookie", INDEX(INDIRECT("Rookies" & SEASON & "[salary]"),MATCH(RosterPlan25[[#This Row],[PLAYER]],INDIRECT("Rookies"& SEASON & "[full_name]"),0)), MAX(RosterPlan25[[#This Row],[$ PREV]] + IF(RAISES_ENABLED,RosterPlan25[[#This Row],[$↑ VAR]],0),1)) -> 32 | P28: =IF(VARG="MANUAL",RosterPlan25[[#This Row],[ManualVARG]],IF(VARG="GOOD",RosterPlan25[[#This Row],[GoodVARG]],"ERR")) -> 1.582496 | Q28: =_xlfn.IFNA(IF(RosterPlan25[[#This Row],[POS]]="K",0,INDEX(GoodSheets[MG VARG],MATCH(TEXT(RosterPlan25[[#This Row],[player_id]],"0"),GoodSheets[sleeper_id],0))), IF(RosterPlan25[[#This Row],[POS]]="QB",-12,IF(RosterPlan25[[#This Row],[POS]]="RB",-8,IF(RosterPlan25[[#This Row],[POS]]="WR",-8,-5)))) -> 1.582496 | R28: =_xlfn.IFNA(INDEX(ALL_Athletic[VARG], MATCH(RosterPlan25[[#This Row],[player_id]],ALL_Athletic[SleeperID],0)), IF(RosterPlan25[[#This Row],[POS]]="QB",-12,IF(RosterPlan25[[#This Row],[POS]]="RB",-8,IF(RosterPlan25[[#This Row],[POS]]="WR",-8,-5)))) -> 2.7572242 | S28: K | T28: =_xlfn.IFNA(INDEX(Draft2025[Net Keeper Count],RosterPlan25[[#This Row],[DraftIndex]]),0)+IF(RosterPlan25[[#This Row],[KEEPER / RFA]]="K",1,0) -> 4 | U28: =IF(RosterPlan25[[#This Row],[KEEPER / RFA]]="RFA",RosterPlan25[[#This Row],[Pure Inflated $]],"") | V28: =IF(RosterPlan25[[#This Row],[VAR/G]]>0, ROUND(IF(VARG="GOOD",$AG$29,IF(VARG="ATHLETIC",$AH$29,99999999999))*RosterPlan25[[#This Row],[VAR/G]],0), 0) + 1 -> 20 | W28: =RosterPlan25[[#This Row],[Optimal $]]-RosterPlan25[[#This Row],[$ CURR]] -> -12 | X28: =IF(OR(RosterPlan25[[#This Row],[SOURCE]]="Rookie",RosterPlan25[[#This Row],[POS]]="K"),0,RosterPlan25[[#This Row],[VAR/G]]+3.3) -> 4.882496 | Y28: =IF(RosterPlan25[[#This Row],[VAW/G]]>0,ROUND(RosterPlan25[[#This Row],[VAW/G]]*$AG$56,0)+1,1) -> 81 | Z28: =RosterPlan25[[#This Row],[VAWG Market $]]-_xlfn.IFNA(RosterPlan25[[#This Row],[$ CURR]],1) -> 49 | AA28: =IF(RosterPlan25[[#This Row],[VAR/G]]>0,1+ROUND(RosterPlan25[[#This Row],[VAR/G]]*IF(RosterPlan25[[#This Row],[KEEPER / RFA]]="K",($AG$34+RosterPlan25[[#This Row],[$ CURR]]-1)/($AG$23+RosterPlan25[[#This Row],[VAR/G]]),$AG$35),0),1) -> 27 | AB28: =RosterPlan25[[#This Row],[Pure Inflated $]]-RosterPlan25[[#This Row],[$ CURR]] -> -5 | AC28: =INDEX(players[age],MATCH(RosterPlan25[[#This Row],[player_id]],players[sleeper_id],0)) -> 26 | AF28: Optimal Keeper Salary | AG28: =((AG22)*AG29)+MIN(AJ12,240) -> 2325.0369 | AH28: =((AH22+AH24)*AH29)+MIN(AJ12,240) -> 2203.3299
A29: 12508 | B29: cthultu | C29: Jaxson Dart | D29: =_xlfn.IFNA(MATCH(RosterPlan25[[#This Row],[player_id]],CompositeRoster[sleeper_id],0), MATCH(RosterPlan25[[#This Row],[PLAYER]],CompositeRoster[full_name],0)) -> 28 | E29: =MATCH(RosterPlan25[[#This Row],[player_id]],Draft2025[sleeper_id],0) -> 44 | F29: =INDEX(CompositeRoster[team],RosterPlan25[[#This Row],[RosterIndex]])&"" -> NYG | G29: =INDEX(CompositeRoster[position],RosterPlan25[[#This Row],[RosterIndex]])&"" -> QB | H29: =INDEX(CompositeRoster[source],RosterPlan25[[#This Row],[RosterIndex]]) -> Roster | I29: =_xlfn.IFNA(INDEX(Draft2025[PRICE],RosterPlan25[[#This Row],[DraftIndex]]),0) -> 3 | J29: =IF(RosterPlan25[[#This Row],[SOURCE]]="Rookie","Rookie",_xlfn.IFNA(INDEX(Draft2025[Current Contract],RosterPlan25[[#This Row],[DraftIndex]]),"Undrafted")) -> Rookie | K29: {=IF(OR(ISBLANK(RosterPlan25[[#This Row],[player_id]]),NOT(ISNA(MATCH(RosterPlan25[[#This Row],[player_id]],INDIRECT("Rookies" & SEASON &"[player_id]"),0)))), SEASON, _xlfn.IFNA(INDEX(Draft2025[Contract Year],RosterPlan25[[#This Row],[DraftIndex]]),IF(IN_SEASON,SEASON,SEASON-1)))} -> 2025 | L29: =IF(_xlfn.IFNA(INDEX(Draft2025[KEEPER],RosterPlan25[[#This Row],[DraftIndex]]),"")="K","Yes","") | M29: {=IF(RosterPlan25[[#This Row],[Contract]]="Rookie", "", IF(_xlfn.IFNA(INDEX(Draft2025[Contract Year],RosterPlan25[[#This Row],[DraftIndex]]),IF(IN_SEASON,SEASON,SEASON-1))+3<SEASON, SEASON, _xlfn.IFNA(INDEX(Draft2025[Contract Year],RosterPlan25[[#This Row],[DraftIndex]]),IF(IN_SEASON,SEASON,SEASON-1))+3))} | N29: =ROUNDDOWN(RosterPlan25[[#This Row],[Optimal $]]*IF(RosterPlan25[[#This Row],[Contract]]="Rookie",0.3,0.15),0) -> 0 | O29: =IF(RosterPlan25[[#This Row],[SOURCE]]="Rookie", INDEX(INDIRECT("Rookies" & SEASON & "[salary]"),MATCH(RosterPlan25[[#This Row],[PLAYER]],INDIRECT("Rookies"& SEASON & "[full_name]"),0)), MAX(RosterPlan25[[#This Row],[$ PREV]] + IF(RAISES_ENABLED,RosterPlan25[[#This Row],[$↑ VAR]],0),1)) -> 3 | P29: =IF(VARG="MANUAL",RosterPlan25[[#This Row],[ManualVARG]],IF(VARG="GOOD",RosterPlan25[[#This Row],[GoodVARG]],"ERR")) -> -0.15907573 | Q29: =_xlfn.IFNA(IF(RosterPlan25[[#This Row],[POS]]="K",0,INDEX(GoodSheets[MG VARG],MATCH(TEXT(RosterPlan25[[#This Row],[player_id]],"0"),GoodSheets[sleeper_id],0))), IF(RosterPlan25[[#This Row],[POS]]="QB",-12,IF(RosterPlan25[[#This Row],[POS]]="RB",-8,IF(RosterPlan25[[#This Row],[POS]]="WR",-8,-5)))) -> -0.15907573 | R29: =_xlfn.IFNA(INDEX(ALL_Athletic[VARG], MATCH(RosterPlan25[[#This Row],[player_id]],ALL_Athletic[SleeperID],0)), IF(RosterPlan25[[#This Row],[POS]]="QB",-12,IF(RosterPlan25[[#This Row],[POS]]="RB",-8,IF(RosterPlan25[[#This Row],[POS]]="WR",-8,-5)))) -> -12 | S29: K | T29: =_xlfn.IFNA(INDEX(Draft2025[Net Keeper Count],RosterPlan25[[#This Row],[DraftIndex]]),0)+IF(RosterPlan25[[#This Row],[KEEPER / RFA]]="K",1,0) -> 1 | U29: =IF(RosterPlan25[[#This Row],[KEEPER / RFA]]="RFA",RosterPlan25[[#This Row],[Pure Inflated $]],"") | V29: =IF(RosterPlan25[[#This Row],[VAR/G]]>0, ROUND(IF(VARG="GOOD",$AG$29,IF(VARG="ATHLETIC",$AH$29,99999999999))*RosterPlan25[[#This Row],[VAR/G]],0), 0) + 1 -> 1 | W29: =RosterPlan25[[#This Row],[Optimal $]]-RosterPlan25[[#This Row],[$ CURR]] -> -2 | X29: =IF(OR(RosterPlan25[[#This Row],[SOURCE]]="Rookie",RosterPlan25[[#This Row],[POS]]="K"),0,RosterPlan25[[#This Row],[VAR/G]]+3.3) -> 3.1409243 | Y29: =IF(RosterPlan25[[#This Row],[VAW/G]]>0,ROUND(RosterPlan25[[#This Row],[VAW/G]]*$AG$56,0)+1,1) -> 53 | Z29: =RosterPlan25[[#This Row],[VAWG Market $]]-_xlfn.IFNA(RosterPlan25[[#This Row],[$ CURR]],1) -> 50 | AA29: =IF(RosterPlan25[[#This Row],[VAR/G]]>0,1+ROUND(RosterPlan25[[#This Row],[VAR/G]]*IF(RosterPlan25[[#This Row],[KEEPER / RFA]]="K",($AG$34+RosterPlan25[[#This Row],[$ CURR]]-1)/($AG$23+RosterPlan25[[#This Row],[VAR/G]]),$AG$35),0),1) -> 1 | AB29: =RosterPlan25[[#This Row],[Pure Inflated $]]-RosterPlan25[[#This Row],[$ CURR]] -> -2 | AC29: =INDEX(players[age],MATCH(RosterPlan25[[#This Row],[player_id]],players[sleeper_id],0)) -> 23 | AF29: Optimal $/VARG | AG29: =($AG$26-240)/$AG$21 -> 11.788844 | AH29: =($AH$26-240)/$AH$21 -> 11.111431
A30: 10222 | B30: cthultu | C30: Jayden Reed | D30: =_xlfn.IFNA(MATCH(RosterPlan25[[#This Row],[player_id]],CompositeRoster[sleeper_id],0), MATCH(RosterPlan25[[#This Row],[PLAYER]],CompositeRoster[full_name],0)) -> 29 | E30: =MATCH(RosterPlan25[[#This Row],[player_id]],Draft2025[sleeper_id],0) -> 36 | F30: =INDEX(CompositeRoster[team],RosterPlan25[[#This Row],[RosterIndex]])&"" -> GB | G30: =INDEX(CompositeRoster[position],RosterPlan25[[#This Row],[RosterIndex]])&"" -> WR | H30: =INDEX(CompositeRoster[source],RosterPlan25[[#This Row],[RosterIndex]]) -> Roster | I30: =_xlfn.IFNA(INDEX(Draft2025[PRICE],RosterPlan25[[#This Row],[DraftIndex]]),0) -> 6 | J30: =IF(RosterPlan25[[#This Row],[SOURCE]]="Rookie","Rookie",_xlfn.IFNA(INDEX(Draft2025[Current Contract],RosterPlan25[[#This Row],[DraftIndex]]),"Undrafted")) -> Rookie | K30: {=IF(OR(ISBLANK(RosterPlan25[[#This Row],[player_id]]),NOT(ISNA(MATCH(RosterPlan25[[#This Row],[player_id]],INDIRECT("Rookies" & SEASON &"[player_id]"),0)))), SEASON, _xlfn.IFNA(INDEX(Draft2025[Contract Year],RosterPlan25[[#This Row],[DraftIndex]]),IF(IN_SEASON,SEASON,SEASON-1)))} -> 2023 | L30: =IF(_xlfn.IFNA(INDEX(Draft2025[KEEPER],RosterPlan25[[#This Row],[DraftIndex]]),"")="K","Yes","") -> Yes | M30: {=IF(RosterPlan25[[#This Row],[Contract]]="Rookie", "", IF(_xlfn.IFNA(INDEX(Draft2025[Contract Year],RosterPlan25[[#This Row],[DraftIndex]]),IF(IN_SEASON,SEASON,SEASON-1))+3<SEASON, SEASON, _xlfn.IFNA(INDEX(Draft2025[Contract Year],RosterPlan25[[#This Row],[DraftIndex]]),IF(IN_SEASON,SEASON,SEASON-1))+3))} | N30: =ROUNDDOWN(RosterPlan25[[#This Row],[Optimal $]]*IF(RosterPlan25[[#This Row],[Contract]]="Rookie",0.3,0.15),0) -> 0 | O30: =IF(RosterPlan25[[#This Row],[SOURCE]]="Rookie", INDEX(INDIRECT("Rookies" & SEASON & "[salary]"),MATCH(RosterPlan25[[#This Row],[PLAYER]],INDIRECT("Rookies"& SEASON & "[full_name]"),0)), MAX(RosterPlan25[[#This Row],[$ PREV]] + IF(RAISES_ENABLED,RosterPlan25[[#This Row],[$↑ VAR]],0),1)) -> 6 | P30: =IF(VARG="MANUAL",RosterPlan25[[#This Row],[ManualVARG]],IF(VARG="GOOD",RosterPlan25[[#This Row],[GoodVARG]],"ERR")) -> -0.33962822 | Q30: =_xlfn.IFNA(IF(RosterPlan25[[#This Row],[POS]]="K",0,INDEX(GoodSheets[MG VARG],MATCH(TEXT(RosterPlan25[[#This Row],[player_id]],"0"),GoodSheets[sleeper_id],0))), IF(RosterPlan25[[#This Row],[POS]]="QB",-12,IF(RosterPlan25[[#This Row],[POS]]="RB",-8,IF(RosterPlan25[[#This Row],[POS]]="WR",-8,-5)))) -> -0.33962822 | R30: =_xlfn.IFNA(INDEX(ALL_Athletic[VARG], MATCH(RosterPlan25[[#This Row],[player_id]],ALL_Athletic[SleeperID],0)), IF(RosterPlan25[[#This Row],[POS]]="QB",-12,IF(RosterPlan25[[#This Row],[POS]]="RB",-8,IF(RosterPlan25[[#This Row],[POS]]="WR",-8,-5)))) -> -1.5035682 | S30: K | T30: =_xlfn.IFNA(INDEX(Draft2025[Net Keeper Count],RosterPlan25[[#This Row],[DraftIndex]]),0)+IF(RosterPlan25[[#This Row],[KEEPER / RFA]]="K",1,0) -> 3 | U30: =IF(RosterPlan25[[#This Row],[KEEPER / RFA]]="RFA",RosterPlan25[[#This Row],[Pure Inflated $]],"") | V30: =IF(RosterPlan25[[#This Row],[VAR/G]]>0, ROUND(IF(VARG="GOOD",$AG$29,IF(VARG="ATHLETIC",$AH$29,99999999999))*RosterPlan25[[#This Row],[VAR/G]],0), 0) + 1 -> 1 | W30: =RosterPlan25[[#This Row],[Optimal $]]-RosterPlan25[[#This Row],[$ CURR]] -> -5 | X30: =IF(OR(RosterPlan25[[#This Row],[SOURCE]]="Rookie",RosterPlan25[[#This Row],[POS]]="K"),0,RosterPlan25[[#This Row],[VAR/G]]+3.3) -> 2.9603718 | Y30: =IF(RosterPlan25[[#This Row],[VAW/G]]>0,ROUND(RosterPlan25[[#This Row],[VAW/G]]*$AG$56,0)+1,1) -> 50 | Z30: =RosterPlan25[[#This Row],[VAWG Market $]]-_xlfn.IFNA(RosterPlan25[[#This Row],[$ CURR]],1) -> 44 | AA30: =IF(RosterPlan25[[#This Row],[VAR/G]]>0,1+ROUND(RosterPlan25[[#This Row],[VAR/G]]*IF(RosterPlan25[[#This Row],[KEEPER / RFA]]="K",($AG$34+RosterPlan25[[#This Row],[$ CURR]]-1)/($AG$23+RosterPlan25[[#This Row],[VAR/G]]),$AG$35),0),1) -> 1 | AB30: =RosterPlan25[[#This Row],[Pure Inflated $]]-RosterPlan25[[#This Row],[$ CURR]] -> -5 | AC30: =INDEX(players[age],MATCH(RosterPlan25[[#This Row],[player_id]],players[sleeper_id],0)) -> 26 | AF30: Keepers $/VARG | AG30: =($AG$12-$AJ$12)/(AN12) -> 10.386025 | AH30: =($AG$12-$AJ$12)/(AN12) -> 10.386025
A31: 8408 | B31: cthultu | C31: Jordan Mason | D31: =_xlfn.IFNA(MATCH(RosterPlan25[[#This Row],[player_id]],CompositeRoster[sleeper_id],0), MATCH(RosterPlan25[[#This Row],[PLAYER]],CompositeRoster[full_name],0)) -> 30 | E31: =MATCH(RosterPlan25[[#This Row],[player_id]],Draft2025[sleeper_id],0) -> 26 | F31: =INDEX(CompositeRoster[team],RosterPlan25[[#This Row],[RosterIndex]])&"" -> MIN | G31: =INDEX(CompositeRoster[position],RosterPlan25[[#This Row],[RosterIndex]])&"" -> RB | H31: =INDEX(CompositeRoster[source],RosterPlan25[[#This Row],[RosterIndex]]) -> Roster | I31: =_xlfn.IFNA(INDEX(Draft2025[PRICE],RosterPlan25[[#This Row],[DraftIndex]]),0) -> 12 | J31: =IF(RosterPlan25[[#This Row],[SOURCE]]="Rookie","Rookie",_xlfn.IFNA(INDEX(Draft2025[Current Contract],RosterPlan25[[#This Row],[DraftIndex]]),"Undrafted")) -> Auction | K31: {=IF(OR(ISBLANK(RosterPlan25[[#This Row],[player_id]]),NOT(ISNA(MATCH(RosterPlan25[[#This Row],[player_id]],INDIRECT("Rookies" & SEASON &"[player_id]"),0)))), SEASON, _xlfn.IFNA(INDEX(Draft2025[Contract Year],RosterPlan25[[#This Row],[DraftIndex]]),IF(IN_SEASON,SEASON,SEASON-1)))} -> 2025 | L31: =IF(_xlfn.IFNA(INDEX(Draft2025[KEEPER],RosterPlan25[[#This Row],[DraftIndex]]),"")="K","Yes","") | M31: {=IF(RosterPlan25[[#This Row],[Contract]]="Rookie", "", IF(_xlfn.IFNA(INDEX(Draft2025[Contract Year],RosterPlan25[[#This Row],[DraftIndex]]),IF(IN_SEASON,SEASON,SEASON-1))+3<SEASON, SEASON, _xlfn.IFNA(INDEX(Draft2025[Contract Year],RosterPlan25[[#This Row],[DraftIndex]]),IF(IN_SEASON,SEASON,SEASON-1))+3))} -> 2028 | N31: =ROUNDDOWN(RosterPlan25[[#This Row],[Optimal $]]*IF(RosterPlan25[[#This Row],[Contract]]="Rookie",0.3,0.15),0) -> 0 | O31: =IF(RosterPlan25[[#This Row],[SOURCE]]="Rookie", INDEX(INDIRECT("Rookies" & SEASON & "[salary]"),MATCH(RosterPlan25[[#This Row],[PLAYER]],INDIRECT("Rookies"& SEASON & "[full_name]"),0)), MAX(RosterPlan25[[#This Row],[$ PREV]] + IF(RAISES_ENABLED,RosterPlan25[[#This Row],[$↑ VAR]],0),1)) -> 12 | P31: =IF(VARG="MANUAL",RosterPlan25[[#This Row],[ManualVARG]],IF(VARG="GOOD",RosterPlan25[[#This Row],[GoodVARG]],"ERR")) -> 0 | Q31: =_xlfn.IFNA(IF(RosterPlan25[[#This Row],[POS]]="K",0,INDEX(GoodSheets[MG VARG],MATCH(TEXT(RosterPlan25[[#This Row],[player_id]],"0"),GoodSheets[sleeper_id],0))), IF(RosterPlan25[[#This Row],[POS]]="QB",-12,IF(RosterPlan25[[#This Row],[POS]]="RB",-8,IF(RosterPlan25[[#This Row],[POS]]="WR",-8,-5)))) -> 0 | R31: =_xlfn.IFNA(INDEX(ALL_Athletic[VARG], MATCH(RosterPlan25[[#This Row],[player_id]],ALL_Athletic[SleeperID],0)), IF(RosterPlan25[[#This Row],[POS]]="QB",-12,IF(RosterPlan25[[#This Row],[POS]]="RB",-8,IF(RosterPlan25[[#This Row],[POS]]="WR",-8,-5)))) -> -4.5740569 | S31: K | T31: =_xlfn.IFNA(INDEX(Draft2025[Net Keeper Count],RosterPlan25[[#This Row],[DraftIndex]]),0)+IF(RosterPlan25[[#This Row],[KEEPER / RFA]]="K",1,0) -> 1 | U31: =IF(RosterPlan25[[#This Row],[KEEPER / RFA]]="RFA",RosterPlan25[[#This Row],[Pure Inflated $]],"") | V31: =IF(RosterPlan25[[#This Row],[VAR/G]]>0, ROUND(IF(VARG="GOOD",$AG$29,IF(VARG="ATHLETIC",$AH$29,99999999999))*RosterPlan25[[#This Row],[VAR/G]],0), 0) + 1 -> 1 | W31: =RosterPlan25[[#This Row],[Optimal $]]-RosterPlan25[[#This Row],[$ CURR]] -> -11 | X31: =IF(OR(RosterPlan25[[#This Row],[SOURCE]]="Rookie",RosterPlan25[[#This Row],[POS]]="K"),0,RosterPlan25[[#This Row],[VAR/G]]+3.3) -> 3.3 | Y31: =IF(RosterPlan25[[#This Row],[VAW/G]]>0,ROUND(RosterPlan25[[#This Row],[VAW/G]]*$AG$56,0)+1,1) -> 55 | Z31: =RosterPlan25[[#This Row],[VAWG Market $]]-_xlfn.IFNA(RosterPlan25[[#This Row],[$ CURR]],1) -> 43 | AA31: =IF(RosterPlan25[[#This Row],[VAR/G]]>0,1+ROUND(RosterPlan25[[#This Row],[VAR/G]]*IF(RosterPlan25[[#This Row],[KEEPER / RFA]]="K",($AG$34+RosterPlan25[[#This Row],[$ CURR]]-1)/($AG$23+RosterPlan25[[#This Row],[VAR/G]]),$AG$35),0),1) -> 1 | AB31: =RosterPlan25[[#This Row],[Pure Inflated $]]-RosterPlan25[[#This Row],[$ CURR]] -> -11 | AC31: =INDEX(players[age],MATCH(RosterPlan25[[#This Row],[player_id]],players[sleeper_id],0)) -> 27
